Workbook

Sheet collected_variables_EU
A1: var_name | B1: var_display_name | C1: var_description | D1: var_source_name | E1: var_source_link | F1: var_source_citation | G1: var_source_license | H1: tag_sector | I1: tag_type | J1: tag_commodity | K1: tag_resource | L1: tag_link | M1: tag_other | N1: var_unit | O1: var_aggregation_method | P1: spatial_level | Q1: to_stage? | R1: staging_calculation | S1: post_disagg_calculation_eq | T1: Shruthi's notes | U1: is_used_for_SOIs? | V1: is_used_in_midas_model? | W1: is_used_for_manual_eucalc_disaggregation? | X1: is_used_indirectly_for_disaggregation? | Y1: used_anywhere? | Z1: threshold for rounding down to 0 | AA1: round to integer midas
A2: active_citizenship | B2: Active citizenship | C2: Share of people who claimed they had participated in any of the following activities: activities in a political party or local interest group; public consultation; peaceful protest or demonstration, including signing a petition; writing a letter to a politician or to the media (voting in an election excluded) | D2: EU Social Progress Index - 2020 | E2: https://cohesiondata.ec.europa.eu/stories/s/EU-Social-Progress-Index-2020/8qk9-xq96/ | F2: Paola Annoni and Paolo Bolsi, “EU Social Progress Index - 2020.” https://cohesiondata.ec.europa.eu/stories/s/EU-Social-Progress-Index-2020/8qk9-xq96/ (accessed Aug. 10, 2023). | G2: Creative Commons Attribution 4.0 International (CC BY 4.0) | H2: general stat | N2: percentage | O2: AVG | P2: NUTS0 | Q2: yes | U2: =IF(COUNTIF(soi_input_variables!A:A,A2)>0,"yes","no") -> yes | V2: =IF(COUNTIF(midas_input_variables!A:A,A2)>0,"yes","no") -> no | W2: =IF(OR(COUNTIF(eucalc_variables_proxies!C:C,"*"&A2&"*")>0,COUNTIF(eucalc_variables_proxies!F:F,"*"&A2&"*")>0),"yes","no") -> no | X2: =IF(COUNTIF(collected_variables_proxies!C:C,"*"&A2&"*")>0,"yes","no") -> no | Y2: =IF(OR(U2="yes",V2="yes",W2="yes",X2="yes"),"yes","no") -> yes
A3: agriculture_with_natural_vegetation_cover | B3: Agriculture with natural vegetation cover | C3: Please note that only elements which are at least 25 hectares in area are captured here | D3: Copernicus Land Monitoring Service - Corine Land Cover | E3: https://land.copernicus.eu/pan-european/corine-land-cover/clc2018 | F3: Corine Land Cover, ‘CLC 2018 — Copernicus Land Monitoring Service’. https://land.copernicus.eu/pan-european/corine-land-cover/clc2018 (accessed Nov. 29, 2022). | H3: land use, agriculture and forestry | K3: land area | N3: square kilometer | O3: SUM | P3: LAU | Q3: yes | U3: =IF(COUNTIF(soi_input_variables!A:A,A3)>0,"yes","no") -> yes | V3: =IF(COUNTIF(midas_input_variables!A:A,A3)>0,"yes","no") -> no | W3: =IF(OR(COUNTIF(eucalc_variables_proxies!C:C,"*"&A3&"*")>0,COUNTIF(eucalc_variables_proxies!F:F,"*"&A3&"*")>0),"yes","no") -> yes | X3: =IF(COUNTIF(collected_variables_proxies!C:C,"*"&A3&"*")>0,"yes","no") -> yes | Y3: =IF(OR(U3="yes",V3="yes",W3="yes",X3="yes"),"yes","no") -> yes
A4: agro_forestry_areas_cover | B4: Agro-forestry areas cover | C4: Please note that only elements which are at least 25 hectares in area are captured here | D4: Copernicus Land Monitoring Service - Corine Land Cover | E4: https://land.copernicus.eu/pan-european/corine-land-cover/clc2018 | F4: Corine Land Cover, ‘CLC 2018 — Copernicus Land Monitoring Service’. https://land.copernicus.eu/pan-european/corine-land-cover/clc2018 (accessed Nov. 29, 2022). | H4: land use, agriculture and forestry | K4: land area | N4: square kilometer | O4: SUM | P4: LAU | Q4: yes | U4: =IF(COUNTIF(soi_input_variables!A:A,A4)>0,"yes","no") -> yes | V4: =IF(COUNTIF(midas_input_variables!A:A,A4)>0,"yes","no") -> no | W4: =IF(OR(COUNTIF(eucalc_variables_proxies!C:C,"*"&A4&"*")>0,COUNTIF(eucalc_variables_proxies!F:F,"*"&A4&"*")>0),"yes","no") -> yes | X4: =IF(COUNTIF(collected_variables_proxies!C:C,"*"&A4&"*")>0,"yes","no") -> yes | Y4: =IF(OR(U4="yes",V4="yes",W4="yes",X4="yes"),"yes","no") -> yes
A5: air_transport_of_freight | B5: Air transport of freight | C5: Traffic and transport measurement: Freight loaded and unloaded | D5: Eurostat | E5: https://ec.europa.eu/eurostat/databrowser/view/tran_r_avgo_nm/default/table?lang=en | F5: Eurostat, ‘Air transport of freight by NUTS 2 regions’, 2022. https://ec.europa.eu/eurostat/databrowser/view/tran_r_avgo_nm/default/table?lang=en (accessed Nov. 23, 2022). | G5: Creative Commons Attribution 4.0 International (CC BY 4.0) | H5: transport | I5: cargo | L5: tra_emissions-CO2e_freight_aviation | N5: Mt | O5: SUM | P5: NUTS2 | Q5: yes | U5: =IF(COUNTIF(soi_input_variables!A:A,A5)>0,"yes","no") -> no | V5: =IF(COUNTIF(midas_input_variables!A:A,A5)>0,"yes","no") -> yes | W5: =IF(OR(COUNTIF(eucalc_variables_proxies!C:C,"*"&A5&"*")>0,COUNTIF(eucalc_variables_proxies!F:F,"*"&A5&"*")>0),"yes","no") -> yes | X5: =IF(COUNTIF(collected_variables_proxies!C:C,"*"&A5&"*")>0,"yes","no") -> yes | Y5: =IF(OR(U5="yes",V5="yes",W5="yes",X5="yes"),"yes","no") -> yes
A6: air_transport_of_passengers | B6: Air transport of passengers | C6: Traffic and transport measurement: Passengers carried | D6: Eurostat | E6: https://ec.europa.eu/eurostat/databrowser/view/tgs00077/default/table?lang=en | F6: Eurostat, ‘Air transport of passengers by NUTS 2 regions’, 2022. https://ec.europa.eu/eurostat/databrowser/view/tgs00077/default/table?lang=en (accessed Nov. 23, 2022). | G6: Creative Commons Attribution 4.0 International (CC BY 4.0) | H6: transport | I6: stock | L6: tra_emissions-CO2e_passenger_aviation | N6: number | O6: SUM | P6: NUTS2 | Q6: yes | U6: =IF(COUNTIF(soi_input_variables!A:A,A6)>0,"yes","no") -> no | V6: =IF(COUNTIF(midas_input_variables!A:A,A6)>0,"yes","no") -> yes | W6: =IF(OR(COUNTIF(eucalc_variables_proxies!C:C,"*"&A6&"*")>0,COUNTIF(eucalc_variables_proxies!F:F,"*"&A6&"*")>0),"yes","no") -> yes | X6: =IF(COUNTIF(collected_variables_proxies!C:C,"*"&A6&"*")>0,"yes","no") -> yes | Y6: =IF(OR(U6="yes",V6="yes",W6="yes",X6="yes"),"yes","no") -> yes
A7: airports_cover | B7: Airports cover | C7: Please note that only elements which are at least 25 hectares in area are captured here | D7: Copernicus Land Monitoring Service - Corine Land Cover | E7: https://land.copernicus.eu/pan-european/corine-land-cover/clc2018 | F7: Corine Land Cover, ‘CLC 2018 — Copernicus Land Monitoring Service’. https://land.copernicus.eu/pan-european/corine-land-cover/clc2018 (accessed Nov. 29, 2022). | H7: land use, transport | N7: square kilometer | O7: SUM | P7: LAU | Q7: yes | U7: =IF(COUNTIF(soi_input_variables!A:A,A7)>0,"yes","no") -> no | V7: =IF(COUNTIF(midas_input_variables!A:A,A7)>0,"yes","no") -> no | W7: =IF(OR(COUNTIF(eucalc_variables_proxies!C:C,"*"&A7&"*")>0,COUNTIF(eucalc_variables_proxies!F:F,"*"&A7&"*")>0),"yes","no") -> yes | X7: =IF(COUNTIF(collected_variables_proxies!C:C,"*"&A7&"*")>0,"yes","no") -> yes | Y7: =IF(OR(U7="yes",V7="yes",W7="yes",X7="yes"),"yes","no") -> yes
A8: animal_and_mixed_food_and_vegetal_waste | B8: Animal and mixed food and vegetal waste | D8: Eurostat | E8: https://ec.europa.eu/eurostat/databrowser/view/ENV_WASGEN/default/table?lang=en | F8: Eurostat, “Generation of waste by waste category, hazardousness and NACE Rev. 2 activity.” Accessed: Oct. 04, 2023. [Online]. Available: https://ec.europa.eu/eurostat/databrowser/view/ENV_WASGEN/default/table?lang=en | G8: Creative Commons Attribution 4.0 International (CC BY 4.0) | H8: waste | N8: kilogram | O8: SUM | P8: NUTS0 | Q8: yes | U8: =IF(COUNTIF(soi_input_variables!A:A,A8)>0,"yes","no") -> yes | V8: =IF(COUNTIF(midas_input_variables!A:A,A8)>0,"yes","no") -> no | W8: =IF(OR(COUNTIF(eucalc_variables_proxies!C:C,"*"&A8&"*")>0,COUNTIF(eucalc_variables_proxies!F:F,"*"&A8&"*")>0),"yes","no") -> no | X8: =IF(COUNTIF(collected_variables_proxies!C:C,"*"&A8&"*")>0,"yes","no") -> no | Y8: =IF(OR(U8="yes",V8="yes",W8="yes",X8="yes"),"yes","no") -> yes
A9: cproj_annual_mean_maximum_temperature | B9: Annual mean of daily maximum temperature | C9: Daily maximum temperature averaged over a year | D9: EURO-CORDEX: new high-resolution climate change projections for European impact research | E9: https://www.euro-cordex.net/060378/index.php.en | F9: D. Jacob et al., ‘EURO-CORDEX: new high-resolution climate change projections for European impact research’, Regional environmental change, vol. 14, no. 2, pp. 563–578, 2014. | H9: weather and climate | N9: degree celsius | O9: AVG | P9: NUTS3 | Q9: yes | U9: =IF(COUNTIF(soi_input_variables!A:A,A9)>0,"yes","no") -> no | V9: =IF(COUNTIF(midas_input_variables!A:A,A9)>0,"yes","no") -> no | W9: =IF(OR(COUNTIF(eucalc_variables_proxies!C:C,"*"&A9&"*")>0,COUNTIF(eucalc_variables_proxies!F:F,"*"&A9&"*")>0),"yes","no") -> no | X9: =IF(COUNTIF(collected_variables_proxies!C:C,"*"&A9&"*")>0,"yes","no") -> no | Y9: =IF(OR(U9="yes",V9="yes",W9="yes",X9="yes"),"yes","no") -> no | Z9: 0.1
A10: cproj_annual_mean_mean_temperature | B10: Annual mean of daily mean temperature | C10: Daily mean temperature averaged over a year | D10: EURO-CORDEX: new high-resolution climate change projections for European impact research | E10: https://www.euro-cordex.net/060378/index.php.en | F10: D. Jacob et al., ‘EURO-CORDEX: new high-resolution climate change projections for European impact research’, Regional environmental change, vol. 14, no. 2, pp. 563–578, 2014. | H10: weather and climate | N10: degree celsius | O10: AVG | P10: NUTS3 | Q10: yes | U10: =IF(COUNTIF(soi_input_variables!A:A,A10)>0,"yes","no") -> no | V10: =IF(COUNTIF(midas_input_variables!A:A,A10)>0,"yes","no") -> no | W10: =IF(OR(COUNTIF(eucalc_variables_proxies!C:C,"*"&A10&"*")>0,COUNTIF(eucalc_variables_proxies!F:F,"*"&A10&"*")>0),"yes","no") -> no | X10: =IF(COUNTIF(collected_variables_proxies!C:C,"*"&A10&"*")>0,"yes","no") -> no | Y10: =IF(OR(U10="yes",V10="yes",W10="yes",X10="yes"),"yes","no") -> no | Z10: 0.1
A11: cproj_annual_mean_minimum_temperature | B11: Annual mean of daily minimum temperature | C11: Daily minimum temperature averaged over a year | D11: EURO-CORDEX: new high-resolution climate change projections for European impact research | E11: https://www.euro-cordex.net/060378/index.php.en | F11: D. Jacob et al., ‘EURO-CORDEX: new high-resolution climate change projections for European impact research’, Regional environmental change, vol. 14, no. 2, pp. 563–578, 2014. | H11: weather and climate | N11: degree celsius | O11: AVG | P11: NUTS3 | Q11: yes | U11: =IF(COUNTIF(soi_input_variables!A:A,A11)>0,"yes","no") -> no | V11: =IF(COUNTIF(midas_input_variables!A:A,A11)>0,"yes","no") -> no | W11: =IF(OR(COUNTIF(eucalc_variables_proxies!C:C,"*"&A11&"*")>0,COUNTIF(eucalc_variables_proxies!F:F,"*"&A11&"*")>0),"yes","no") -> no | X11: =IF(COUNTIF(collected_variables_proxies!C:C,"*"&A11&"*")>0,"yes","no") -> no | Y11: =IF(OR(U11="yes",V11="yes",W11="yes",X11="yes"),"yes","no") -> no | Z11: 0.1
A12: cproj_annual_mean_precipitation | B12: Annual mean precipitation | C12: Daily precipitation averaged over a year | D12: EURO-CORDEX: new high-resolution climate change projections for European impact research | E12: https://www.euro-cordex.net/060378/index.php.en | F12: D. Jacob et al., ‘EURO-CORDEX: new high-resolution climate change projections for European impact research’, Regional environmental change, vol. 14, no. 2, pp. 563–578, 2014. | H12: weather and climate | N12: mm/day | O12: AVG | P12: NUTS3 | Q12: yes | U12: =IF(COUNTIF(soi_input_variables!A:A,A12)>0,"yes","no") -> no | V12: =IF(COUNTIF(midas_input_variables!A:A,A12)>0,"yes","no") -> no | W12: =IF(OR(COUNTIF(eucalc_variables_proxies!C:C,"*"&A12&"*")>0,COUNTIF(eucalc_variables_proxies!F:F,"*"&A12&"*")>0),"yes","no") -> no | X12: =IF(COUNTIF(collected_variables_proxies!C:C,"*"&A12&"*")>0,"yes","no") -> no | Y12: =IF(OR(U12="yes",V12="yes",W12="yes",X12="yes"),"yes","no") -> no | Z12: 0.1
A13: cproj_annual_total_precipitation | B13: Annual total precipitation | C13: Daily precipitation summed over a year | D13: EURO-CORDEX: new high-resolution climate change projections for European impact research | E13: https://www.euro-cordex.net/060378/index.php.en | F13: D. Jacob et al., ‘EURO-CORDEX: new high-resolution climate change projections for European impact research’, Regional environmental change, vol. 14, no. 2, pp. 563–578, 2014. | H13: weather and climate | N13: mm | O13: AVG | P13: NUTS3 | Q13: yes | U13: =IF(COUNTIF(soi_input_variables!A:A,A13)>0,"yes","no") -> no | V13: =IF(COUNTIF(midas_input_variables!A:A,A13)>0,"yes","no") -> no | W13: =IF(OR(COUNTIF(eucalc_variables_proxies!C:C,"*"&A13&"*")>0,COUNTIF(eucalc_variables_proxies!F:F,"*"&A13&"*")>0),"yes","no") -> no | X13: =IF(COUNTIF(collected_variables_proxies!C:C,"*"&A13&"*")>0,"yes","no") -> no | Y13: =IF(OR(U13="yes",V13="yes",W13="yes",X13="yes"),"yes","no") -> no | Z13: 0.1
A14: aquaculture_area | B14: Aquaculture area | D14: OpenStreetMap | E14: https://download.geofabrik.de/ | F14: OpenStreetMap contributors (2017). Planet dump retrieved from https://planet.osm.org . https://www. openstreetmap.org. | G14: Open Data Commons Open Database License (ODbL) | H14: land use, water | N14: square kilometer | O14: SUM | P14: LAU | Q14: yes | U14: =IF(COUNTIF(soi_input_variables!A:A,A14)>0,"yes","no") -> no | V14: =IF(COUNTIF(midas_input_variables!A:A,A14)>0,"yes","no") -> no | W14: =IF(OR(COUNTIF(eucalc_variables_proxies!C:C,"*"&A14&"*")>0,COUNTIF(eucalc_variables_proxies!F:F,"*"&A14&"*")>0),"yes","no") -> no | X14: =IF(COUNTIF(collected_variables_proxies!C:C,"*"&A14&"*")>0,"yes","no") -> no | Y14: =IF(OR(U14="yes",V14="yes",W14="yes",X14="yes"),"yes","no") -> no
A15: area | B15: Area | D15: GISCO - Eurostat | E15: https://ec.europa.eu/eurostat/web/gisco/geodata/statistical-units/local-administrative-units | F15: GISCO - Eurostat, ‘NUTS - GISCO - Eurostat’, 2021. https://ec.europa.eu/eurostat/web/gisco/geodata/reference-data/administrative-units-statistical-units/lau (accessed Nov. 23, 2022). | G15: Creative Commons Attribution 4.0 International (CC BY 4.0) | H15: general stat | N15: square kilometer | O15: SUM | P15: LAU | Q15: yes | U15: =IF(COUNTIF(soi_input_variables!A:A,A15)>0,"yes","no") -> yes | V15: =IF(COUNTIF(midas_input_variables!A:A,A15)>0,"yes","no") -> no | W15: =IF(OR(COUNTIF(eucalc_variables_proxies!C:C,"*"&A15&"*")>0,COUNTIF(eucalc_variables_proxies!F:F,"*"&A15&"*")>0),"yes","no") -> yes | X15: =IF(COUNTIF(collected_variables_proxies!C:C,"*"&A15&"*")>0,"yes","no") -> yes | Y15: =IF(OR(U15="yes",V15="yes",W15="yes",X15="yes"),"yes","no") -> yes
A16: average_air_pollution_due_to_no2 | B16: Average air pollution due to NO2 | D16: European Environmental Agency | E16: https://www.eea.europa.eu/en/datahub/datahubitem-view/34bd02bf-be87-4122-b9a2-1e846c27a786 | F16: European Environment Agency. “NO2, European Air Quality Data, (Interpolated Data).” Accessed July 16, 2024. https://www.eea.europa.eu/en/datahub/datahubitem-view/34bd02bf-be87-4122-b9a2-1e846c27a786. | G16: Creative Commons Attribution 4.0 International (CC BY 4.0) | H16: environmental and biodiversity | N16: ug/m3 | O16: AVG | P16: LAU | Q16: yes | U16: =IF(COUNTIF(soi_input_variables!A:A,A16)>0,"yes","no") -> yes | V16: =IF(COUNTIF(midas_input_variables!A:A,A16)>0,"yes","no") -> no | W16: =IF(OR(COUNTIF(eucalc_variables_proxies!C:C,"*"&A16&"*")>0,COUNTIF(eucalc_variables_proxies!F:F,"*"&A16&"*")>0),"yes","no") -> no | X16: =IF(COUNTIF(collected_variables_proxies!C:C,"*"&A16&"*")>0,"yes","no") -> yes | Y16: =IF(OR(U16="yes",V16="yes",W16="yes",X16="yes"),"yes","no") -> yes
A17: average_air_pollution_due_to_o3 | B17: Average air pollution due to O3 | D17: European Environmental Agency | E17: https://www.eea.europa.eu/en/datahub/datahubitem-view/c816f363-a892-4f62-86d1-0460437bc023 | F17: European Environment Agency. “O3, European Air Quality Data, (Interpolated Data).” Accessed July 16, 2024. https://www.eea.europa.eu/en/datahub/datahubitem-view/c816f363-a892-4f62-86d1-0460437bc023. | G17: Creative Commons Attribution 4.0 International (CC BY 4.0) | H17: environmental and biodiversity | N17: ug/m3 | O17: AVG | P17: LAU | Q17: yes | U17: =IF(COUNTIF(soi_input_variables!A:A,A17)>0,"yes","no") -> yes | V17: =IF(COUNTIF(midas_input_variables!A:A,A17)>0,"yes","no") -> no | W17: =IF(OR(COUNTIF(eucalc_variables_proxies!C:C,"*"&A17&"*")>0,COUNTIF(eucalc_variables_proxies!F:F,"*"&A17&"*")>0),"yes","no") -> no | X17: =IF(COUNTIF(collected_variables_proxies!C:C,"*"&A17&"*")>0,"yes","no") -> yes | Y17: =IF(OR(U17="yes",V17="yes",W17="yes",X17="yes"),"yes","no") -> yes
A18: average_air_pollution_due_to_pm10 | B18: Average air pollution due to PM10 | D18: European Environmental Agency | E18: https://www.eea.europa.eu/en/datahub/datahubitem-view/abc66a42-b595-4e0f-9772-b862dc454e9f | F18: European Environment Agency. “PM10, European Air Quality Data, (Interpolated Data).” Accessed July 16, 2024. https://www.eea.europa.eu/en/datahub/datahubitem-view/abc66a42-b595-4e0f-9772-b862dc454e9f. | G18: Creative Commons Attribution 4.0 International (CC BY 4.0) | H18: environmental and biodiversity | N18: ug/m3 | O18: AVG | P18: LAU | Q18: yes | U18: =IF(COUNTIF(soi_input_variables!A:A,A18)>0,"yes","no") -> no | V18: =IF(COUNTIF(midas_input_variables!A:A,A18)>0,"yes","no") -> no | W18: =IF(OR(COUNTIF(eucalc_variables_proxies!C:C,"*"&A18&"*")>0,COUNTIF(eucalc_variables_proxies!F:F,"*"&A18&"*")>0),"yes","no") -> no | X18: =IF(COUNTIF(collected_variables_proxies!C:C,"*"&A18&"*")>0,"yes","no") -> no | Y18: =IF(OR(U18="yes",V18="yes",W18="yes",X18="yes"),"yes","no") -> no
A19: average_air_pollution_due_to_pm25 | B19: Average air pollution due to PM2.5 | C19: Particulate matter 2.5 | D19: European Environmental Agency | E19: https://www.eea.europa.eu/en/datahub/datahubitem-view/938bea70-07fc-47e9-8559-8a09f7f92494 | F19: European Environment Agency. “Pm25, European Air Quality Data, (Interpolated Data).” Accessed July 16, 2024. https://www.eea.europa.eu/en/datahub/datahubitem-view/938bea70-07fc-47e9-8559-8a09f7f92494. | G19: Creative Commons Attribution 4.0 International (CC BY 4.0) | H19: environmental and biodiversity | N19: ug/m3 | O19: AVG | P19: LAU | Q19: yes | U19: =IF(COUNTIF(soi_input_variables!A:A,A19)>0,"yes","no") -> yes | V19: =IF(COUNTIF(midas_input_variables!A:A,A19)>0,"yes","no") -> no | W19: =IF(OR(COUNTIF(eucalc_variables_proxies!C:C,"*"&A19&"*")>0,COUNTIF(eucalc_variables_proxies!F:F,"*"&A19&"*")>0),"yes","no") -> no | X19: =IF(COUNTIF(collected_variables_proxies!C:C,"*"&A19&"*")>0,"yes","no") -> yes | Y19: =IF(OR(U19="yes",V19="yes",W19="yes",X19="yes"),"yes","no") -> yes
A20: bare_rocks_cover | B20: Bare rocks cover | C20: Please note that only elements which are at least 25 hectares in area are captured here | D20: Copernicus Land Monitoring Service - Corine Land Cover | E20: https://land.copernicus.eu/pan-european/corine-land-cover/clc2018 | F20: Corine Land Cover, ‘CLC 2018 — Copernicus Land Monitoring Service’. https://land.copernicus.eu/pan-european/corine-land-cover/clc2018 (accessed Nov. 29, 2022). | H20: land use | K20: land area | N20: square kilometer | O20: SUM | P20: LAU | Q20: yes | U20: =IF(COUNTIF(soi_input_variables!A:A,A20)>0,"yes","no") -> no | V20: =IF(COUNTIF(midas_input_variables!A:A,A20)>0,"yes","no") -> yes | W20: =IF(OR(COUNTIF(eucalc_variables_proxies!C:C,"*"&A20&"*")>0,COUNTIF(eucalc_variables_proxies!F:F,"*"&A20&"*")>0),"yes","no") -> no | X20: =IF(COUNTIF(collected_variables_proxies!C:C,"*"&A20&"*")>0,"yes","no") -> no | Y20: =IF(OR(U20="yes",V20="yes",W20="yes",X20="yes"),"yes","no") -> yes
A21: beaches_dunes_and_sand_cover | B21: Beaches, dunes, and sand cover | C21: Please note that only elements which are at least 25 hectares in area are captured here | D21: Copernicus Land Monitoring Service - Corine Land Cover | E21: https://land.copernicus.eu/pan-european/corine-land-cover/clc2018 | F21: Corine Land Cover, ‘CLC 2018 — Copernicus Land Monitoring Service’. https://land.copernicus.eu/pan-european/corine-land-cover/clc2018 (accessed Nov. 29, 2022). | H21: land use, water | K21: coastal area | N21: square kilometer | O21: SUM | P21: LAU | Q21: yes | U21: =IF(COUNTIF(soi_input_variables!A:A,A21)>0,"yes","no") -> no | V21: =IF(COUNTIF(midas_input_variables!A:A,A21)>0,"yes","no") -> yes | W21: =IF(OR(COUNTIF(eucalc_variables_proxies!C:C,"*"&A21&"*")>0,COUNTIF(eucalc_variables_proxies!F:F,"*"&A21&"*")>0),"yes","no") -> no | X21: =IF(COUNTIF(collected_variables_proxies!C:C,"*"&A21&"*")>0,"yes","no") -> no | Y21: =IF(OR(U21="yes",V21="yes",W21="yes",X21="yes"),"yes","no") -> yes
A22: broad_leaved_forest_cover | B22: Broad-leaved forest cover | C22: Please note that only elements which are at least 25 hectares in area are captured here | D22: Copernicus Land Monitoring Service - Corine Land Cover | E22: https://land.copernicus.eu/pan-european/corine-land-cover/clc2018 | F22: Corine Land Cover, ‘CLC 2018 — Copernicus Land Monitoring Service’. https://land.copernicus.eu/pan-european/corine-land-cover/clc2018 (accessed Nov. 29, 2022). | H22: land use, agriculture and forestry | K22: land area | N22: square kilometer | O22: SUM | P22: LAU | Q22: yes | U22: =IF(COUNTIF(soi_input_variables!A:A,A22)>0,"yes","no") -> yes | V22: =IF(COUNTIF(midas_input_variables!A:A,A22)>0,"yes","no") -> no | W22: =IF(OR(COUNTIF(eucalc_variables_proxies!C:C,"*"&A22&"*")>0,COUNTIF(eucalc_variables_proxies!F:F,"*"&A22&"*")>0),"yes","no") -> yes | X22: =IF(COUNTIF(collected_variables_proxies!C:C,"*"&A22&"*")>0,"yes","no") -> no | Y22: =IF(OR(U22="yes",V22="yes",W22="yes",X22="yes"),"yes","no") -> yes
A23: burnt_areas_cover | B23: Burnt areas cover | C23: Please note that only elements which are at least 25 hectares in area are captured here | D23: Copernicus Land Monitoring Service - Corine Land Cover | E23: https://land.copernicus.eu/pan-european/corine-land-cover/clc2018 | F23: Corine Land Cover, ‘CLC 2018 — Copernicus Land Monitoring Service’. https://land.copernicus.eu/pan-european/corine-land-cover/clc2018 (accessed Nov. 29, 2022). | H23: land use | K23: land area | N23: square kilometer | O23: SUM | P23: LAU | Q23: yes | U23: =IF(COUNTIF(soi_input_variables!A:A,A23)>0,"yes","no") -> no | V23: =IF(COUNTIF(midas_input_variables!A:A,A23)>0,"yes","no") -> yes | W23: =IF(OR(COUNTIF(eucalc_variables_proxies!C:C,"*"&A23&"*")>0,COUNTIF(eucalc_variables_proxies!F:F,"*"&A23&"*")>0),"yes","no") -> yes | X23: =IF(COUNTIF(collected_variables_proxies!C:C,"*"&A23&"*")>0,"yes","no") -> no | Y23: =IF(OR(U23="yes",V23="yes",W23="yes",X23="yes"),"yes","no") -> yes
A24: business_investment | B24: Business investment | C24: The indicator gives the share of GDP that is used for business investment (rather than being used for e.g. consumption or exports). | D24: Eurostat | E24: https://ec.europa.eu/eurostat/databrowser/view/tec00132/default/table?lang=en | F24: Eurostat, ‘Investment by institutional sectors’, 2022. https://ec.europa.eu/eurostat/databrowser/view/tec00132/default/table?lang=en (accessed Nov. 23, 2022). | G24: Creative Commons Attribution 4.0 International (CC BY 4.0) | H24: general stat | I24: investment | N24: percentage | O24: AVG | P24: NUTS0 | Q24: yes | U24: =IF(COUNTIF(soi_input_variables!A:A,A24)>0,"yes","no") -> no | V24: =IF(COUNTIF(midas_input_variables!A:A,A24)>0,"yes","no") -> no | W24: =IF(OR(COUNTIF(eucalc_variables_proxies!C:C,"*"&A24&"*")>0,COUNTIF(eucalc_variables_proxies!F:F,"*"&A24&"*")>0),"yes","no") -> no | X24: =IF(COUNTIF(collected_variables_proxies!C:C,"*"&A24&"*")>0,"yes","no") -> no | Y24: =IF(OR(U24="yes",V24="yes",W24="yes",X24="yes"),"yes","no") -> no
A25: capital_stock_based_productivity_in_agriculture | B25: Capital stock-based productivity in agriculture | C25: Calculated by: Gross value added/input capital stock. Unit is index, base period for productivity measurement is 2015. | D25: Eurostat | E25: https://ec.europa.eu/eurostat/databrowser/view/nama_10_cp_a21/default/table?lang=en | F25: Eurostat, ‘Capital stock based productivity indicators at industry level’, 2022. https://ec.europa.eu/eurostat/databrowser/view/nama_10_cp_a21/default/table?lang=en (accessed Nov. 23, 2022). | G25: Creative Commons Attribution 4.0 International (CC BY 4.0) | H25: general stat, agriculture and forestry | I25: finance | N25: index | O25: AVG | P25: NUTS0 | Q25: yes | U25: =IF(COUNTIF(soi_input_variables!A:A,A25)>0,"yes","no") -> no | V25: =IF(COUNTIF(midas_input_variables!A:A,A25)>0,"yes","no") -> no | W25: =IF(OR(COUNTIF(eucalc_variables_proxies!C:C,"*"&A25&"*")>0,COUNTIF(eucalc_variables_proxies!F:F,"*"&A25&"*")>0),"yes","no") -> no | X25: =IF(COUNTIF(collected_variables_proxies!C:C,"*"&A25&"*")>0,"yes","no") -> no | Y25: =IF(OR(U25="yes",V25="yes",W25="yes",X25="yes"),"yes","no") -> no
A26: capital_stock_based_productivity_in_manufacturing | B26: Capital stock-based productivity in manufacturing | C26: Calculated by: Gross value added/input capital stock. Unit is index, base period for productivity measurement is 2015. | D26: Eurostat | E26: https://ec.europa.eu/eurostat/databrowser/view/nama_10_cp_a21/default/table?lang=en | F26: Eurostat, ‘Capital stock based productivity indicators at industry level’, 2022. https://ec.europa.eu/eurostat/databrowser/view/nama_10_cp_a21/default/table?lang=en (accessed Nov. 23, 2022). | G26: Creative Commons Attribution 4.0 International (CC BY 4.0) | H26: general stat, industry | I26: finance | N26: index | O26: AVG | P26: NUTS0 | Q26: yes | U26: =IF(COUNTIF(soi_input_variables!A:A,A26)>0,"yes","no") -> no | V26: =IF(COUNTIF(midas_input_variables!A:A,A26)>0,"yes","no") -> no | W26: =IF(OR(COUNTIF(eucalc_variables_proxies!C:C,"*"&A26&"*")>0,COUNTIF(eucalc_variables_proxies!F:F,"*"&A26&"*")>0),"yes","no") -> no | X26: =IF(COUNTIF(collected_variables_proxies!C:C,"*"&A26&"*")>0,"yes","no") -> no | Y26: =IF(OR(U26="yes",V26="yes",W26="yes",X26="yes"),"yes","no") -> no
A27: capital_stock_based_productivity_in_transportation | B27: Capital stock-based productivity in transportation | C27: Calculated by: Gross value added/input capital stock. Unit is index, base period for productivity measurement is 2015. | D27: Eurostat | E27: https://ec.europa.eu/eurostat/databrowser/view/nama_10_cp_a21/default/table?lang=en | F27: Eurostat, ‘Capital stock based productivity indicators at industry level’, 2022. https://ec.europa.eu/eurostat/databrowser/view/nama_10_cp_a21/default/table?lang=en (accessed Nov. 23, 2022). | G27: Creative Commons Attribution 4.0 International (CC BY 4.0) | H27: general stat, transport, service | I27: finance | N27: index | O27: AVG | P27: NUTS0 | Q27: yes | U27: =IF(COUNTIF(soi_input_variables!A:A,A27)>0,"yes","no") -> no | V27: =IF(COUNTIF(midas_input_variables!A:A,A27)>0,"yes","no") -> no | W27: =IF(OR(COUNTIF(eucalc_variables_proxies!C:C,"*"&A27&"*")>0,COUNTIF(eucalc_variables_proxies!F:F,"*"&A27&"*")>0),"yes","no") -> no | X27: =IF(COUNTIF(collected_variables_proxies!C:C,"*"&A27&"*")>0,"yes","no") -> no | Y27: =IF(OR(U27="yes",V27="yes",W27="yes",X27="yes"),"yes","no") -> no
A28: cimp_change_in_frequency_of_coldwaves_maximum | B28: Change in frequency of coldwaves -maximum | C28: Projected change summer coldwave days frequency and time frame, rescaled by max Values and their meanings: 1 = Increase, 0 = No Change, -1 = Decrease, -5 = Uncertain, -10 = Not Known | D28: EURO-CORDEX: new high-resolution climate change projections for European impact research | E28: https://www.euro-cordex.net/060378/index.php.en | F28: D. Jacob et al., ‘EURO-CORDEX: new high-resolution climate change projections for European impact research’, Regional environmental change, vol. 14, no. 2, pp. 563–578, 2014. | H28: climate hazard | I28: frequency | M28: coldwave | N28: (categorical) | O28: MAX | P28: NUTS3 | Q28: yes | U28: =IF(COUNTIF(soi_input_variables!A:A,A28)>0,"yes","no") -> no | V28: =IF(COUNTIF(midas_input_variables!A:A,A28)>0,"yes","no") -> no | W28: =IF(OR(COUNTIF(eucalc_variables_proxies!C:C,"*"&A28&"*")>0,COUNTIF(eucalc_variables_proxies!F:F,"*"&A28&"*")>0),"yes","no") -> no | X28: =IF(COUNTIF(collected_variables_proxies!C:C,"*"&A28&"*")>0,"yes","no") -> no | Y28: =IF(OR(U28="yes",V28="yes",W28="yes",X28="yes"),"yes","no") -> no
A29: cimp_change_in_frequency_of_coldwaves_mean | B29: Change in frequency of coldwaves -mean | C29: Projected change summer coldwave days frequency and time frame, rescaled by mean Values and their meanings: 1 = Increase, 0 = No Change, -1 = Decrease, -5 = Uncertain, -10 = Not Known | D29: EURO-CORDEX: new high-resolution climate change projections for European impact research | E29: https://www.euro-cordex.net/060378/index.php.en | F29: D. Jacob et al., ‘EURO-CORDEX: new high-resolution climate change projections for European impact research’, Regional environmental change, vol. 14, no. 2, pp. 563–578, 2014. | H29: climate hazard | I29: frequency | N29: (categorical) | O29: MAX | P29: NUTS3 | Q29: yes | U29: =IF(COUNTIF(soi_input_variables!A:A,A29)>0,"yes","no") -> yes | V29: =IF(COUNTIF(midas_input_variables!A:A,A29)>0,"yes","no") -> no | W29: =IF(OR(COUNTIF(eucalc_variables_proxies!C:C,"*"&A29&"*")>0,COUNTIF(eucalc_variables_proxies!F:F,"*"&A29&"*")>0),"yes","no") -> no | X29: =IF(COUNTIF(collected_variables_proxies!C:C,"*"&A29&"*")>0,"yes","no") -> no | Y29: =IF(OR(U29="yes",V29="yes",W29="yes",X29="yes"),"yes","no") -> yes
A30: cimp_change_in_frequency_of_extreme_drought_maximum | B30: Change in frequency of extreme drought - maximum | C30: Projected change in frequency of extreme drought days (2021-2100) and time frame, rescaled by max Values and their meanings: 1 = Increase, 0 = No Change, -1 = Decrease, -5 = Uncertain, -10 = Not Known | D30: EURO-CORDEX: new high-resolution climate change projections for European impact research | E30: https://www.euro-cordex.net/060378/index.php.en | F30: D. Jacob et al., ‘EURO-CORDEX: new high-resolution climate change projections for European impact research’, Regional environmental change, vol. 14, no. 2, pp. 563–578, 2014. | H30: climate hazard | I30: frequency | N30: (categorical) | O30: MAX | P30: NUTS3 | Q30: yes | U30: =IF(COUNTIF(soi_input_variables!A:A,A30)>0,"yes","no") -> no | V30: =IF(COUNTIF(midas_input_variables!A:A,A30)>0,"yes","no") -> no | W30: =IF(OR(COUNTIF(eucalc_variables_proxies!C:C,"*"&A30&"*")>0,COUNTIF(eucalc_variables_proxies!F:F,"*"&A30&"*")>0),"yes","no") -> no | X30: =IF(COUNTIF(collected_variables_proxies!C:C,"*"&A30&"*")>0,"yes","no") -> no | Y30: =IF(OR(U30="yes",V30="yes",W30="yes",X30="yes"),"yes","no") -> no
A31: cimp_change_in_frequency_of_extreme_drought_mean | B31: Change in frequency of extreme drought - mean | C31: Projected change in frequency of extreme drought days (2021-2100) and time frame, rescaled by mean Values and their meanings: 1 = Increase, 0 = No Change, -1 = Decrease, -5 = Uncertain, -10 = Not Known | D31: EURO-CORDEX: new high-resolution climate change projections for European impact research | E31: https://www.euro-cordex.net/060378/index.php.en | F31: D. Jacob et al., ‘EURO-CORDEX: new high-resolution climate change projections for European impact research’, Regional environmental change, vol. 14, no. 2, pp. 563–578, 2014. | H31: climate hazard | I31: frequency | N31: (categorical) | O31: MAX | P31: NUTS3 | Q31: yes | U31: =IF(COUNTIF(soi_input_variables!A:A,A31)>0,"yes","no") -> no | V31: =IF(COUNTIF(midas_input_variables!A:A,A31)>0,"yes","no") -> no | W31: =IF(OR(COUNTIF(eucalc_variables_proxies!C:C,"*"&A31&"*")>0,COUNTIF(eucalc_variables_proxies!F:F,"*"&A31&"*")>0),"yes","no") -> no | X31: =IF(COUNTIF(collected_variables_proxies!C:C,"*"&A31&"*")>0,"yes","no") -> no | Y31: =IF(OR(U31="yes",V31="yes",W31="yes",X31="yes"),"yes","no") -> no
A32: cimp_change_in_frequency_of_heatwaves_maximum | B32: Change in frequency of heatwaves -maximum | C32: Projected change summer heatwave days frequency and time frame, rescaled by max Values and their meanings: 1 = Increase, 0 = No Change, -1 = Decrease, -5 = Uncertain, -10 = Not Known | D32: EURO-CORDEX: new high-resolution climate change projections for European impact research | E32: https://www.euro-cordex.net/060378/index.php.en | F32: D. Jacob et al., ‘EURO-CORDEX: new high-resolution climate change projections for European impact research’, Regional environmental change, vol. 14, no. 2, pp. 563–578, 2014. | H32: climate hazard | I32: frequency | N32: (categorical) | O32: MAX | P32: NUTS3 | Q32: yes | U32: =IF(COUNTIF(soi_input_variables!A:A,A32)>0,"yes","no") -> no | V32: =IF(COUNTIF(midas_input_variables!A:A,A32)>0,"yes","no") -> no | W32: =IF(OR(COUNTIF(eucalc_variables_proxies!C:C,"*"&A32&"*")>0,COUNTIF(eucalc_variables_proxies!F:F,"*"&A32&"*")>0),"yes","no") -> no | X32: =IF(COUNTIF(collected_variables_proxies!C:C,"*"&A32&"*")>0,"yes","no") -> no | Y32: =IF(OR(U32="yes",V32="yes",W32="yes",X32="yes"),"yes","no") -> no
A33: cimp_change_in_frequency_of_heatwaves_mean | B33: Change in frequency of heatwaves -mean | C33: Projected change summer heatwave days frequency and time frame, rescaled by mean Values and their meanings: 1 = Increase, 0 = No Change, -1 = Decrease, -5 = Uncertain, -10 = Not Known | D33: EURO-CORDEX: new high-resolution climate change projections for European impact research | E33: https://www.euro-cordex.net/060378/index.php.en | F33: D. Jacob et al., ‘EURO-CORDEX: new high-resolution climate change projections for European impact research’, Regional environmental change, vol. 14, no. 2, pp. 563–578, 2014. | H33: climate hazard | I33: frequency | N33: (categorical) | O33: MAX | P33: NUTS3 | Q33: yes | U33: =IF(COUNTIF(soi_input_variables!A:A,A33)>0,"yes","no") -> yes | V33: =IF(COUNTIF(midas_input_variables!A:A,A33)>0,"yes","no") -> no | W33: =IF(OR(COUNTIF(eucalc_variables_proxies!C:C,"*"&A33&"*")>0,COUNTIF(eucalc_variables_proxies!F:F,"*"&A33&"*")>0),"yes","no") -> no | X33: =IF(COUNTIF(collected_variables_proxies!C:C,"*"&A33&"*")>0,"yes","no") -> no | Y33: =IF(OR(U33="yes",V33="yes",W33="yes",X33="yes"),"yes","no") -> yes
A34: cimp_change_in_frequency_of_heavy_precipitation_maximum | B34: Change in frequency of heavy precipitation - maximum | C34: Projected change of frequency of days (2021-2100) with precipitation >20mm and time frame, rescaled by max Values and their meanings: 1 = Increase, 0 = No Change, -1 = Decrease, -5 = Uncertain, -10 = Not Known | D34: EURO-CORDEX: new high-resolution climate change projections for European impact research | E34: https://www.euro-cordex.net/060378/index.php.en | F34: D. Jacob et al., ‘EURO-CORDEX: new high-resolution climate change projections for European impact research’, Regional environmental change, vol. 14, no. 2, pp. 563–578, 2014. | H34: climate hazard | I34: frequency | N34: (categorical) | O34: MAX | P34: NUTS3 | Q34: yes | U34: =IF(COUNTIF(soi_input_variables!A:A,A34)>0,"yes","no") -> no | V34: =IF(COUNTIF(midas_input_variables!A:A,A34)>0,"yes","no") -> no | W34: =IF(OR(COUNTIF(eucalc_variables_proxies!C:C,"*"&A34&"*")>0,COUNTIF(eucalc_variables_proxies!F:F,"*"&A34&"*")>0),"yes","no") -> no | X34: =IF(COUNTIF(collected_variables_proxies!C:C,"*"&A34&"*")>0,"yes","no") -> no | Y34: =IF(OR(U34="yes",V34="yes",W34="yes",X34="yes"),"yes","no") -> no
A35: cimp_change_in_frequency_of_heavy_precipitation_mean | B35: Change in frequency of heavy precipitation - mean | C35: Projected change of frequency of days with precipitation >20mm and time frame,rescaled by mean Values and their meanings: 1 = Increase, 0 = No Change, -1 = Decrease, -5 = Uncertain, -10 = Not Known | D35: EURO-CORDEX: new high-resolution climate change projections for European impact research | E35: https://www.euro-cordex.net/060378/index.php.en | F35: D. Jacob et al., ‘EURO-CORDEX: new high-resolution climate change projections for European impact research’, Regional environmental change, vol. 14, no. 2, pp. 563–578, 2014. | H35: climate hazard | I35: frequency | N35: (categorical) | O35: MAX | P35: NUTS3 | Q35: yes | U35: =IF(COUNTIF(soi_input_variables!A:A,A35)>0,"yes","no") -> yes | V35: =IF(COUNTIF(midas_input_variables!A:A,A35)>0,"yes","no") -> no | W35: =IF(OR(COUNTIF(eucalc_variables_proxies!C:C,"*"&A35&"*")>0,COUNTIF(eucalc_variables_proxies!F:F,"*"&A35&"*")>0),"yes","no") -> no | X35: =IF(COUNTIF(collected_variables_proxies!C:C,"*"&A35&"*")>0,"yes","no") -> no | Y35: =IF(OR(U35="yes",V35="yes",W35="yes",X35="yes"),"yes","no") -> yes
A36: cimp_change_in_frequency_of_high_fire_risk_maximum | B36: Change in frequency of high fire risk -maximum | C36: Projected change of frequency of a summer day (2021-2100) with high fire risk and time frame, rescaled by max Values and their meanings: 1 = Increase, 0 = No Change, -1 = Decrease, -5 = Uncertain, -10 = Not Known | D36: EURO-CORDEX: new high-resolution climate change projections for European impact research | E36: https://www.euro-cordex.net/060378/index.php.en | F36: D. Jacob et al., ‘EURO-CORDEX: new high-resolution climate change projections for European impact research’, Regional environmental change, vol. 14, no. 2, pp. 563–578, 2014. | H36: climate hazard | I36: frequency | N36: (categorical) | O36: MAX | P36: NUTS3 | Q36: yes | U36: =IF(COUNTIF(soi_input_variables!A:A,A36)>0,"yes","no") -> no | V36: =IF(COUNTIF(midas_input_variables!A:A,A36)>0,"yes","no") -> no | W36: =IF(OR(COUNTIF(eucalc_variables_proxies!C:C,"*"&A36&"*")>0,COUNTIF(eucalc_variables_proxies!F:F,"*"&A36&"*")>0),"yes","no") -> no | X36: =IF(COUNTIF(collected_variables_proxies!C:C,"*"&A36&"*")>0,"yes","no") -> no | Y36: =IF(OR(U36="yes",V36="yes",W36="yes",X36="yes"),"yes","no") -> no
A37: cimp_change_in_frequency_of_high_fire_risk_mean | B37: Change in frequency of high fire risk -mean | C37: Projected change of frequency of a summer day (2021-2100) with high fire risk and time frame, rescaled by mean Values and their meanings: 1 = Increase, 0 = No Change, -1 = Decrease, -5 = Uncertain, -10 = Not Known | D37: EURO-CORDEX: new high-resolution climate change projections for European impact research | E37: https://www.euro-cordex.net/060378/index.php.en | F37: D. Jacob et al., ‘EURO-CORDEX: new high-resolution climate change projections for European impact research’, Regional environmental change, vol. 14, no. 2, pp. 563–578, 2014. | H37: climate hazard | I37: frequency | N37: (categorical) | O37: MAX | P37: NUTS3 | Q37: yes | U37: =IF(COUNTIF(soi_input_variables!A:A,A37)>0,"yes","no") -> yes | V37: =IF(COUNTIF(midas_input_variables!A:A,A37)>0,"yes","no") -> no | W37: =IF(OR(COUNTIF(eucalc_variables_proxies!C:C,"*"&A37&"*")>0,COUNTIF(eucalc_variables_proxies!F:F,"*"&A37&"*")>0),"yes","no") -> no | X37: =IF(COUNTIF(collected_variables_proxies!C:C,"*"&A37&"*")>0,"yes","no") -> no | Y37: =IF(OR(U37="yes",V37="yes",W37="yes",X37="yes"),"yes","no") -> yes
A38: cimp_change_in_frequency_of_moderate_fire_risk_maximum | B38: Change in frequency of moderate fire risk - maximum | C38: Projected change of frequency of a summer day (2021-2100) with moderate fire risk and time frame, rescaled by max Values and their meanings: 1 = Increase, 0 = No Change, -1 = Decrease, -5 = Uncertain, -10 = Not Known | D38: EURO-CORDEX: new high-resolution climate change projections for European impact research | E38: https://www.euro-cordex.net/060378/index.php.en | F38: D. Jacob et al., ‘EURO-CORDEX: new high-resolution climate change projections for European impact research’, Regional environmental change, vol. 14, no. 2, pp. 563–578, 2014. | H38: climate hazard | I38: frequency | N38: (categorical) | O38: MAX | P38: NUTS3 | Q38: yes | U38: =IF(COUNTIF(soi_input_variables!A:A,A38)>0,"yes","no") -> no | V38: =IF(COUNTIF(midas_input_variables!A:A,A38)>0,"yes","no") -> no | W38: =IF(OR(COUNTIF(eucalc_variables_proxies!C:C,"*"&A38&"*")>0,COUNTIF(eucalc_variables_proxies!F:F,"*"&A38&"*")>0),"yes","no") -> no | X38: =IF(COUNTIF(collected_variables_proxies!C:C,"*"&A38&"*")>0,"yes","no") -> no | Y38: =IF(OR(U38="yes",V38="yes",W38="yes",X38="yes"),"yes","no") -> no
A39: cimp_change_in_frequency_of_moderate_fire_risk_mean | B39: Change in frequency of moderate fire risk - mean | C39: Projected change of frequency of a summer day (2021-2100) with moderate fire risk and time frame, rescaled by mean Values and their meanings: 1 = Increase, 0 = No Change, -1 = Decrease, -5 = Uncertain, -10 = Not Known | D39: EURO-CORDEX: new high-resolution climate change projections for European impact research | E39: https://www.euro-cordex.net/060378/index.php.en | F39: D. Jacob et al., ‘EURO-CORDEX: new high-resolution climate change projections for European impact research’, Regional environmental change, vol. 14, no. 2, pp. 563–578, 2014. | H39: climate hazard | I39: frequency | N39: (categorical) | O39: MAX | P39: NUTS3 | Q39: yes | U39: =IF(COUNTIF(soi_input_variables!A:A,A39)>0,"yes","no") -> no | V39: =IF(COUNTIF(midas_input_variables!A:A,A39)>0,"yes","no") -> no | W39: =IF(OR(COUNTIF(eucalc_variables_proxies!C:C,"*"&A39&"*")>0,COUNTIF(eucalc_variables_proxies!F:F,"*"&A39&"*")>0),"yes","no") -> no | X39: =IF(COUNTIF(collected_variables_proxies!C:C,"*"&A39&"*")>0,"yes","no") -> no | Y39: =IF(OR(U39="yes",V39="yes",W39="yes",X39="yes"),"yes","no") -> no
A40: cimp_change_in_frequency_of_very_high_fire_risk_maximum | B40: Change in frequency of very high fire risk -maximum | C40: Projected change of frequency of a summer day (2021-2100) with very high fire risk and time frame, rescaled by max Values and their meanings: 1 = Increase, 0 = No Change, -1 = Decrease, -5 = Uncertain, -10 = Not Known | D40: EURO-CORDEX: new high-resolution climate change projections for European impact research | E40: https://www.euro-cordex.net/060378/index.php.en | F40: D. Jacob et al., ‘EURO-CORDEX: new high-resolution climate change projections for European impact research’, Regional environmental change, vol. 14, no. 2, pp. 563–578, 2014. | H40: climate hazard | I40: frequency | N40: (categorical) | O40: MAX | P40: NUTS3 | Q40: yes | U40: =IF(COUNTIF(soi_input_variables!A:A,A40)>0,"yes","no") -> no | V40: =IF(COUNTIF(midas_input_variables!A:A,A40)>0,"yes","no") -> no | W40: =IF(OR(COUNTIF(eucalc_variables_proxies!C:C,"*"&A40&"*")>0,COUNTIF(eucalc_variables_proxies!F:F,"*"&A40&"*")>0),"yes","no") -> no | X40: =IF(COUNTIF(collected_variables_proxies!C:C,"*"&A40&"*")>0,"yes","no") -> no | Y40: =IF(OR(U40="yes",V40="yes",W40="yes",X40="yes"),"yes","no") -> no
A41: cimp_change_in_frequency_of_very_high_fire_risk_mean | B41: Change in frequency of very high fire risk -mean | C41: Projected change of frequency of a summer day (2021-2100) with very high fire risk and time frame, rescaled by mean Values and their meanings: 1 = Increase, 0 = No Change, -1 = Decrease, -5 = Uncertain, -10 = Not Known | D41: EURO-CORDEX: new high-resolution climate change projections for European impact research | E41: https://www.euro-cordex.net/060378/index.php.en | F41: D. Jacob et al., ‘EURO-CORDEX: new high-resolution climate change projections for European impact research’, Regional environmental change, vol. 14, no. 2, pp. 563–578, 2014. | H41: climate hazard | I41: frequency | N41: (categorical) | O41: MAX | P41: NUTS3 | Q41: yes | U41: =IF(COUNTIF(soi_input_variables!A:A,A41)>0,"yes","no") -> no | V41: =IF(COUNTIF(midas_input_variables!A:A,A41)>0,"yes","no") -> no | W41: =IF(OR(COUNTIF(eucalc_variables_proxies!C:C,"*"&A41&"*")>0,COUNTIF(eucalc_variables_proxies!F:F,"*"&A41&"*")>0),"yes","no") -> no | X41: =IF(COUNTIF(collected_variables_proxies!C:C,"*"&A41&"*")>0,"yes","no") -> no | Y41: =IF(OR(U41="yes",V41="yes",W41="yes",X41="yes"),"yes","no") -> no
A42: cimp_change_in_intensity_of_coldwaves_maximum | B42: Change in intensity of coldwaves - maximum | C42: Projected change summer coldwave days intensity and time frame, rescaled by max Values and their meanings: 1 = Increase, 0 = No Change, -1 = Decrease, -5 = Uncertain, -10 = Not Known | D42: EURO-CORDEX: new high-resolution climate change projections for European impact research | E42: https://www.euro-cordex.net/060378/index.php.en | F42: D. Jacob et al., ‘EURO-CORDEX: new high-resolution climate change projections for European impact research’, Regional environmental change, vol. 14, no. 2, pp. 563–578, 2014. | H42: climate hazard | N42: (categorical) | O42: MAX | P42: NUTS3 | Q42: yes | U42: =IF(COUNTIF(soi_input_variables!A:A,A42)>0,"yes","no") -> no | V42: =IF(COUNTIF(midas_input_variables!A:A,A42)>0,"yes","no") -> no | W42: =IF(OR(COUNTIF(eucalc_variables_proxies!C:C,"*"&A42&"*")>0,COUNTIF(eucalc_variables_proxies!F:F,"*"&A42&"*")>0),"yes","no") -> no | X42: =IF(COUNTIF(collected_variables_proxies!C:C,"*"&A42&"*")>0,"yes","no") -> no | Y42: =IF(OR(U42="yes",V42="yes",W42="yes",X42="yes"),"yes","no") -> no
A43: cimp_change_in_intensity_of_coldwaves_mean | B43: Change in intensity of coldwaves - mean | C43: Projected change summer coldwave days intensity and time frame, rescaled by mean Values and their meanings: 1 = Increase, 0 = No Change, -1 = Decrease, -5 = Uncertain, -10 = Not Known | D43: EURO-CORDEX: new high-resolution climate change projections for European impact research | E43: https://www.euro-cordex.net/060378/index.php.en | F43: D. Jacob et al., ‘EURO-CORDEX: new high-resolution climate change projections for European impact research’, Regional environmental change, vol. 14, no. 2, pp. 563–578, 2014. | H43: climate hazard | N43: (categorical) | O43: MAX | P43: NUTS3 | Q43: yes | U43: =IF(COUNTIF(soi_input_variables!A:A,A43)>0,"yes","no") -> yes | V43: =IF(COUNTIF(midas_input_variables!A:A,A43)>0,"yes","no") -> no | W43: =IF(OR(COUNTIF(eucalc_variables_proxies!C:C,"*"&A43&"*")>0,COUNTIF(eucalc_variables_proxies!F:F,"*"&A43&"*")>0),"yes","no") -> no | X43: =IF(COUNTIF(collected_variables_proxies!C:C,"*"&A43&"*")>0,"yes","no") -> no | Y43: =IF(OR(U43="yes",V43="yes",W43="yes",X43="yes"),"yes","no") -> yes
A44: cimp_change_in_intensity_of_extreme_drought_maximum | B44: Change in intensity of extreme drought - maximum | C44: Projected change in intensity of extreme drought days (2021-2100) and time frame, rescaled by max Values and their meanings: 1 = Increase, 0 = No Change, -1 = Decrease, -5 = Uncertain, -10 = Not Known | D44: EURO-CORDEX: new high-resolution climate change projections for European impact research | E44: https://www.euro-cordex.net/060378/index.php.en | F44: D. Jacob et al., ‘EURO-CORDEX: new high-resolution climate change projections for European impact research’, Regional environmental change, vol. 14, no. 2, pp. 563–578, 2014. | H44: climate hazard | N44: (categorical) | O44: MAX | P44: NUTS3 | Q44: yes | U44: =IF(COUNTIF(soi_input_variables!A:A,A44)>0,"yes","no") -> no | V44: =IF(COUNTIF(midas_input_variables!A:A,A44)>0,"yes","no") -> no | W44: =IF(OR(COUNTIF(eucalc_variables_proxies!C:C,"*"&A44&"*")>0,COUNTIF(eucalc_variables_proxies!F:F,"*"&A44&"*")>0),"yes","no") -> no | X44: =IF(COUNTIF(collected_variables_proxies!C:C,"*"&A44&"*")>0,"yes","no") -> no | Y44: =IF(OR(U44="yes",V44="yes",W44="yes",X44="yes"),"yes","no") -> no
A45: cimp_change_in_intensity_of_extreme_drought_mean | B45: Change in intensity of extreme drought - mean | C45: Projected change in intensity of extreme drought days (2021-2100) and time frame, rescaled by mean Values and their meanings: 1 = Increase, 0 = No Change, -1 = Decrease, -5 = Uncertain, -10 = Not Known | D45: EURO-CORDEX: new high-resolution climate change projections for European impact research | E45: https://www.euro-cordex.net/060378/index.php.en | F45: D. Jacob et al., ‘EURO-CORDEX: new high-resolution climate change projections for European impact research’, Regional environmental change, vol. 14, no. 2, pp. 563–578, 2014. | H45: climate hazard | N45: (categorical) | O45: MAX | P45: NUTS3 | Q45: yes | U45: =IF(COUNTIF(soi_input_variables!A:A,A45)>0,"yes","no") -> no | V45: =IF(COUNTIF(midas_input_variables!A:A,A45)>0,"yes","no") -> no | W45: =IF(OR(COUNTIF(eucalc_variables_proxies!C:C,"*"&A45&"*")>0,COUNTIF(eucalc_variables_proxies!F:F,"*"&A45&"*")>0),"yes","no") -> no | X45: =IF(COUNTIF(collected_variables_proxies!C:C,"*"&A45&"*")>0,"yes","no") -> no | Y45: =IF(OR(U45="yes",V45="yes",W45="yes",X45="yes"),"yes","no") -> no
A46: cimp_change_in_intensity_of_heatwaves_maximum | B46: Change in intensity of heatwaves - maximum | C46: Projected change summer heatwave days intensity and time frame, rescaled by max Values and their meanings: 1 = Increase, 0 = No Change, -1 = Decrease, -5 = Uncertain, -10 = Not Known | D46: EURO-CORDEX: new high-resolution climate change projections for European impact research | E46: https://www.euro-cordex.net/060378/index.php.en | F46: D. Jacob et al., ‘EURO-CORDEX: new high-resolution climate change projections for European impact research’, Regional environmental change, vol. 14, no. 2, pp. 563–578, 2014. | H46: climate hazard | N46: (categorical) | O46: MAX | P46: NUTS3 | Q46: yes | U46: =IF(COUNTIF(soi_input_variables!A:A,A46)>0,"yes","no") -> no | V46: =IF(COUNTIF(midas_input_variables!A:A,A46)>0,"yes","no") -> no | W46: =IF(OR(COUNTIF(eucalc_variables_proxies!C:C,"*"&A46&"*")>0,COUNTIF(eucalc_variables_proxies!F:F,"*"&A46&"*")>0),"yes","no") -> no | X46: =IF(COUNTIF(collected_variables_proxies!C:C,"*"&A46&"*")>0,"yes","no") -> no | Y46: =IF(OR(U46="yes",V46="yes",W46="yes",X46="yes"),"yes","no") -> no
A47: cimp_change_in_intensity_of_heatwaves_mean | B47: Change in intensity of heatwaves - mean | C47: Projected change summer heatwave days intensity and time frame, rescaled by mean Values and their meanings: 1 = Increase, 0 = No Change, -1 = Decrease, -5 = Uncertain, -10 = Not Known | D47: EURO-CORDEX: new high-resolution climate change projections for European impact research | E47: https://www.euro-cordex.net/060378/index.php.en | F47: D. Jacob et al., ‘EURO-CORDEX: new high-resolution climate change projections for European impact research’, Regional environmental change, vol. 14, no. 2, pp. 563–578, 2014. | H47: climate hazard | N47: (categorical) | O47: MAX | P47: NUTS3 | Q47: yes | U47: =IF(COUNTIF(soi_input_variables!A:A,A47)>0,"yes","no") -> yes | V47: =IF(COUNTIF(midas_input_variables!A:A,A47)>0,"yes","no") -> no | W47: =IF(OR(COUNTIF(eucalc_variables_proxies!C:C,"*"&A47&"*")>0,COUNTIF(eucalc_variables_proxies!F:F,"*"&A47&"*")>0),"yes","no") -> no | X47: =IF(COUNTIF(collected_variables_proxies!C:C,"*"&A47&"*")>0,"yes","no") -> no | Y47: =IF(OR(U47="yes",V47="yes",W47="yes",X47="yes"),"yes","no") -> yes
A48: cimp_change_in_intensity_of_heavy_precipitation_r20_maximum | B48: Change in intensity of heavy precipitation (r20) - maximum | C48: Projected change of intensity of day (2021-2100) with precipitation >20mm and time frame, rescaled by max Values and their meanings: 1 = Increase, 0 = No Change, -1 = Decrease, -5 = Uncertain, -10 = Not Known | D48: EURO-CORDEX: new high-resolution climate change projections for European impact research | E48: https://www.euro-cordex.net/060378/index.php.en | F48: D. Jacob et al., ‘EURO-CORDEX: new high-resolution climate change projections for European impact research’, Regional environmental change, vol. 14, no. 2, pp. 563–578, 2014. | H48: climate hazard | N48: (categorical) | O48: MAX | P48: NUTS3 | Q48: yes | U48: =IF(COUNTIF(soi_input_variables!A:A,A48)>0,"yes","no") -> no | V48: =IF(COUNTIF(midas_input_variables!A:A,A48)>0,"yes","no") -> no | W48: =IF(OR(COUNTIF(eucalc_variables_proxies!C:C,"*"&A48&"*")>0,COUNTIF(eucalc_variables_proxies!F:F,"*"&A48&"*")>0),"yes","no") -> no | X48: =IF(COUNTIF(collected_variables_proxies!C:C,"*"&A48&"*")>0,"yes","no") -> no | Y48: =IF(OR(U48="yes",V48="yes",W48="yes",X48="yes"),"yes","no") -> no
A49: cimp_change_in_intensity_of_heavy_precipitation_r20_mean | B49: Change in intensity of heavy precipitation (r20) - mean | C49: Projected change of intensity of day (2021-2100) with precipitation >20mm and time frame, rescaled by man Values and their meanings: 1 = Increase, 0 = No Change, -1 = Decrease, -5 = Uncertain, -10 = Not Known | D49: EURO-CORDEX: new high-resolution climate change projections for European impact research | E49: https://www.euro-cordex.net/060378/index.php.en | F49: D. Jacob et al., ‘EURO-CORDEX: new high-resolution climate change projections for European impact research’, Regional environmental change, vol. 14, no. 2, pp. 563–578, 2014. | H49: climate hazard | N49: (categorical) | O49: MAX | P49: NUTS3 | Q49: yes | U49: =IF(COUNTIF(soi_input_variables!A:A,A49)>0,"yes","no") -> yes | V49: =IF(COUNTIF(midas_input_variables!A:A,A49)>0,"yes","no") -> no | W49: =IF(OR(COUNTIF(eucalc_variables_proxies!C:C,"*"&A49&"*")>0,COUNTIF(eucalc_variables_proxies!F:F,"*"&A49&"*")>0),"yes","no") -> no | X49: =IF(COUNTIF(collected_variables_proxies!C:C,"*"&A49&"*")>0,"yes","no") -> no | Y49: =IF(OR(U49="yes",V49="yes",W49="yes",X49="yes"),"yes","no") -> yes
A50: cimp_change_in_intensity_of_high_fire_risk_maximum | B50: Change in intensity of high fire risk - maximum | C50: Projected change of intensity of a summer day (2021-2100) with high fire risk and time frame, rescaled by max Values and their meanings: 1 = Increase, 0 = No Change, -1 = Decrease, -5 = Uncertain, -10 = Not Known | D50: EURO-CORDEX: new high-resolution climate change projections for European impact research | E50: https://www.euro-cordex.net/060378/index.php.en | F50: D. Jacob et al., ‘EURO-CORDEX: new high-resolution climate change projections for European impact research’, Regional environmental change, vol. 14, no. 2, pp. 563–578, 2014. | H50: climate hazard | N50: (categorical) | O50: MAX | P50: NUTS3 | Q50: yes | U50: =IF(COUNTIF(soi_input_variables!A:A,A50)>0,"yes","no") -> no | V50: =IF(COUNTIF(midas_input_variables!A:A,A50)>0,"yes","no") -> no | W50: =IF(OR(COUNTIF(eucalc_variables_proxies!C:C,"*"&A50&"*")>0,COUNTIF(eucalc_variables_proxies!F:F,"*"&A50&"*")>0),"yes","no") -> no | X50: =IF(COUNTIF(collected_variables_proxies!C:C,"*"&A50&"*")>0,"yes","no") -> no | Y50: =IF(OR(U50="yes",V50="yes",W50="yes",X50="yes"),"yes","no") -> no
A51: cimp_change_in_intensity_of_high_fire_risk_mean | B51: Change in intensity of high fire risk - mean | C51: Projected change of intensity of a summer day (2021-2100) with high fire risk and time frame, rescaled by mean Values and their meanings: 1 = Increase, 0 = No Change, -1 = Decrease, -5 = Uncertain, -10 = Not Known | D51: EURO-CORDEX: new high-resolution climate change projections for European impact research | E51: https://www.euro-cordex.net/060378/index.php.en | F51: D. Jacob et al., ‘EURO-CORDEX: new high-resolution climate change projections for European impact research’, Regional environmental change, vol. 14, no. 2, pp. 563–578, 2014. | H51: climate hazard | N51: (categorical) | O51: MAX | P51: NUTS3 | Q51: yes | U51: =IF(COUNTIF(soi_input_variables!A:A,A51)>0,"yes","no") -> yes | V51: =IF(COUNTIF(midas_input_variables!A:A,A51)>0,"yes","no") -> no | W51: =IF(OR(COUNTIF(eucalc_variables_proxies!C:C,"*"&A51&"*")>0,COUNTIF(eucalc_variables_proxies!F:F,"*"&A51&"*")>0),"yes","no") -> no | X51: =IF(COUNTIF(collected_variables_proxies!C:C,"*"&A51&"*")>0,"yes","no") -> no | Y51: =IF(OR(U51="yes",V51="yes",W51="yes",X51="yes"),"yes","no") -> yes
A52: cimp_change_in_intensity_of_moderate_fire_risk_maximum | B52: Change in intensity of moderate fire risk - maximum | C52: Projected change of intensity of a summer day (2021-2100) with moderate fire risk and time frame, rescaled by max Values and their meanings: 1 = Increase, 0 = No Change, -1 = Decrease, -5 = Uncertain, -10 = Not Known | D52: EURO-CORDEX: new high-resolution climate change projections for European impact research | E52: https://www.euro-cordex.net/060378/index.php.en | F52: D. Jacob et al., ‘EURO-CORDEX: new high-resolution climate change projections for European impact research’, Regional environmental change, vol. 14, no. 2, pp. 563–578, 2014. | H52: climate hazard | N52: (categorical) | O52: MAX | P52: NUTS3 | Q52: yes | U52: =IF(COUNTIF(soi_input_variables!A:A,A52)>0,"yes","no") -> no | V52: =IF(COUNTIF(midas_input_variables!A:A,A52)>0,"yes","no") -> no | W52: =IF(OR(COUNTIF(eucalc_variables_proxies!C:C,"*"&A52&"*")>0,COUNTIF(eucalc_variables_proxies!F:F,"*"&A52&"*")>0),"yes","no") -> no | X52: =IF(COUNTIF(collected_variables_proxies!C:C,"*"&A52&"*")>0,"yes","no") -> no | Y52: =IF(OR(U52="yes",V52="yes",W52="yes",X52="yes"),"yes","no") -> no
A53: cimp_change_in_intensity_of_moderate_fire_risk_mean | B53: Change in intensity of moderate fire risk - mean | C53: Projected change of intensity of a summer day (2021-2100) with moderate fire risk and time frame, rescaled by mean Values and their meanings: 1 = Increase, 0 = No Change, -1 = Decrease, -5 = Uncertain, -10 = Not Known | D53: EURO-CORDEX: new high-resolution climate change projections for European impact research | E53: https://www.euro-cordex.net/060378/index.php.en | F53: D. Jacob et al., ‘EURO-CORDEX: new high-resolution climate change projections for European impact research’, Regional environmental change, vol. 14, no. 2, pp. 563–578, 2014. | H53: climate hazard | N53: (categorical) | O53: MAX | P53: NUTS3 | Q53: yes | U53: =IF(COUNTIF(soi_input_variables!A:A,A53)>0,"yes","no") -> no | V53: =IF(COUNTIF(midas_input_variables!A:A,A53)>0,"yes","no") -> no | W53: =IF(OR(COUNTIF(eucalc_variables_proxies!C:C,"*"&A53&"*")>0,COUNTIF(eucalc_variables_proxies!F:F,"*"&A53&"*")>0),"yes","no") -> no | X53: =IF(COUNTIF(collected_variables_proxies!C:C,"*"&A53&"*")>0,"yes","no") -> no | Y53: =IF(OR(U53="yes",V53="yes",W53="yes",X53="yes"),"yes","no") -> no
... A55: cimp_change_in_intensity_of_very_high_fire_risk_mean | B55: Change in intensity of very high fire risk - mean | C55: Projected change of intensity of a summer day (2021-2100) with very high fire risk and time frame, rescaled by mean Values and their meanings: 1 = Increase, 0 = No Change, -1 = Decrease, -5 = Uncertain, -10 = Not Known | D55: EURO-CORDEX: new high-resolution climate change projections for European impact research | E55: https://www.euro-cordex.net/060378/index.php.en | F55: D. Jacob et al., ‘EURO-CORDEX: new high-resolution climate change projections for European impact research’, Regional environmental change, vol. 14, no. 2, pp. 563–578, 2014. | H55: climate hazard | N55: (categorical) | O55: MAX | P55: NUTS3 | Q55: yes | U55: =IF(COUNTIF(soi_input_variables!A:A,A55)>0,"yes","no") -> no | V55: =IF(COUNTIF(midas_input_variables!A:A,A55)>0,"yes","no") -> no | W55: =IF(OR(COUNTIF(eucalc_variables_proxies!C:C,"*"&A55&"*")>0,COUNTIF(eucalc_variables_proxies!F:F,"*"&A55&"*")>0),"yes","no") -> no | X55: =IF(COUNTIF(collected_variables_proxies!C:C,"*"&A55&"*")>0,"yes","no") -> no | Y55: =IF(OR(U55="yes",V55="yes",W55="yes",X55="yes"),"yes","no") -> no
A56: cliff_length | B56: Cliff length | D56: OpenStreetMap | E56: https://download.geofabrik.de/ | F56: OpenStreetMap contributors (2017). Planet dump retrieved from https://planet.osm.org . https://www. openstreetmap.org. | G56: Open Data Commons Open Database License (ODbL) | H56: land use | N56: kilometer | O56: SUM | P56: LAU | Q56: yes | U56: =IF(COUNTIF(soi_input_variables!A:A,A56)>0,"yes","no") -> no | V56: =IF(COUNTIF(midas_input_variables!A:A,A56)>0,"yes","no") -> no | W56: =IF(OR(COUNTIF(eucalc_variables_proxies!C:C,"*"&A56&"*")>0,COUNTIF(eucalc_variables_proxies!F:F,"*"&A56&"*")>0),"yes","no") -> no | X56: =IF(COUNTIF(collected_variables_proxies!C:C,"*"&A56&"*")>0,"yes","no") -> no | Y56: =IF(OR(U56="yes",V56="yes",W56="yes",X56="yes"),"yes","no") -> no | Z56: 0.1
A57: coastal_lagoons_cover | B57: Coastal lagoons cover | C57: Please note that only elements which are at least 25 hectares in area are captured here | D57: Copernicus Land Monitoring Service - Corine Land Cover | E57: https://land.copernicus.eu/pan-european/corine-land-cover/clc2018 | F57: Corine Land Cover, ‘CLC 2018 — Copernicus Land Monitoring Service’. https://land.copernicus.eu/pan-european/corine-land-cover/clc2018 (accessed Nov. 29, 2022). | H57: land use, water | K57: coastal area | N57: square kilometer | O57: SUM | P57: LAU | Q57: yes | U57: =IF(COUNTIF(soi_input_variables!A:A,A57)>0,"yes","no") -> no | V57: =IF(COUNTIF(midas_input_variables!A:A,A57)>0,"yes","no") -> yes | W57: =IF(OR(COUNTIF(eucalc_variables_proxies!C:C,"*"&A57&"*")>0,COUNTIF(eucalc_variables_proxies!F:F,"*"&A57&"*")>0),"yes","no") -> no | X57: =IF(COUNTIF(collected_variables_proxies!C:C,"*"&A57&"*")>0,"yes","no") -> no | Y57: =IF(OR(U57="yes",V57="yes",W57="yes",X57="yes"),"yes","no") -> yes | Z57: 0.1
A58: coastline_length | B58: Coastline length | D58: OpenStreetMap | E58: https://download.geofabrik.de/ | F58: OpenStreetMap contributors (2017). Planet dump retrieved from https://planet.osm.org . https://www. openstreetmap.org. | G58: Open Data Commons Open Database License (ODbL) | H58: land use | N58: kilometer | O58: SUM | P58: LAU | Q58: yes | U58: =IF(COUNTIF(soi_input_variables!A:A,A58)>0,"yes","no") -> no | V58: =IF(COUNTIF(midas_input_variables!A:A,A58)>0,"yes","no") -> no | W58: =IF(OR(COUNTIF(eucalc_variables_proxies!C:C,"*"&A58&"*")>0,COUNTIF(eucalc_variables_proxies!F:F,"*"&A58&"*")>0),"yes","no") -> no | X58: =IF(COUNTIF(collected_variables_proxies!C:C,"*"&A58&"*")>0,"yes","no") -> no | Y58: =IF(OR(U58="yes",V58="yes",W58="yes",X58="yes"),"yes","no") -> no | Z58: 0.1
A59: cimp_ts_coldwaves_intensity_maximum | B59: Coldwaves intensity - maximum | C59: Projected annual number of summer coldwave days (2021-2100), rescaled by max, expressed in average number of days per year | D59: EURO-CORDEX: new high-resolution climate change projections for European impact research | E59: https://www.euro-cordex.net/060378/index.php.en | F59: D. Jacob et al., ‘EURO-CORDEX: new high-resolution climate change projections for European impact research’, Regional environmental change, vol. 14, no. 2, pp. 563–578, 2014. | H59: climate hazard | N59: number | O59: AVG | P59: NUTS3 | Q59: yes | U59: =IF(COUNTIF(soi_input_variables!A:A,A59)>0,"yes","no") -> no | V59: =IF(COUNTIF(midas_input_variables!A:A,A59)>0,"yes","no") -> no | W59: =IF(OR(COUNTIF(eucalc_variables_proxies!C:C,"*"&A59&"*")>0,COUNTIF(eucalc_variables_proxies!F:F,"*"&A59&"*")>0),"yes","no") -> no | X59: =IF(COUNTIF(collected_variables_proxies!C:C,"*"&A59&"*")>0,"yes","no") -> no | Y59: =IF(OR(U59="yes",V59="yes",W59="yes",X59="yes"),"yes","no") -> no
A60: cimp_ts_coldwaves_intensity_mean | B60: Coldwaves intensity - mean | C60: Projected annual number of summer coldwave days (2021-2100), rescaled by mean, expressed in average number of days per year | D60: EURO-CORDEX: new high-resolution climate change projections for European impact research | E60: https://www.euro-cordex.net/060378/index.php.en | F60: D. Jacob et al., ‘EURO-CORDEX: new high-resolution climate change projections for European impact research’, Regional environmental change, vol. 14, no. 2, pp. 563–578, 2014. | H60: climate hazard | N60: number | O60: AVG | P60: NUTS3 | Q60: yes | U60: =IF(COUNTIF(soi_input_variables!A:A,A60)>0,"yes","no") -> no | V60: =IF(COUNTIF(midas_input_variables!A:A,A60)>0,"yes","no") -> no | W60: =IF(OR(COUNTIF(eucalc_variables_proxies!C:C,"*"&A60&"*")>0,COUNTIF(eucalc_variables_proxies!F:F,"*"&A60&"*")>0),"yes","no") -> no | X60: =IF(COUNTIF(collected_variables_proxies!C:C,"*"&A60&"*")>0,"yes","no") -> no | Y60: =IF(OR(U60="yes",V60="yes",W60="yes",X60="yes"),"yes","no") -> no
A61: complex_cultivation_patterns_cover | B61: Complex cultivation patterns cover | C61: Please note that only elements which are at least 25 hectares in area are captured here | D61: Copernicus Land Monitoring Service - Corine Land Cover | E61: https://land.copernicus.eu/pan-european/corine-land-cover/clc2018 | F61: Corine Land Cover, ‘CLC 2018 — Copernicus Land Monitoring Service’. https://land.copernicus.eu/pan-european/corine-land-cover/clc2018 (accessed Nov. 29, 2022). | H61: land use, agriculture and forestry | K61: land area | N61: square kilometer | O61: SUM | P61: LAU | Q61: yes | U61: =IF(COUNTIF(soi_input_variables!A:A,A61)>0,"yes","no") -> yes | V61: =IF(COUNTIF(midas_input_variables!A:A,A61)>0,"yes","no") -> yes | W61: =IF(OR(COUNTIF(eucalc_variables_proxies!C:C,"*"&A61&"*")>0,COUNTIF(eucalc_variables_proxies!F:F,"*"&A61&"*")>0),"yes","no") -> yes | X61: =IF(COUNTIF(collected_variables_proxies!C:C,"*"&A61&"*")>0,"yes","no") -> yes | Y61: =IF(OR(U61="yes",V61="yes",W61="yes",X61="yes"),"yes","no") -> yes | Z61: 0.1
A62: coniferous_forest_cover | B62: Coniferous forest cover | C62: Please note that only elements which are at least 25 hectares in area are captured here | D62: Copernicus Land Monitoring Service - Corine Land Cover | E62: https://land.copernicus.eu/pan-european/corine-land-cover/clc2018 | F62: Corine Land Cover, ‘CLC 2018 — Copernicus Land Monitoring Service’. https://land.copernicus.eu/pan-european/corine-land-cover/clc2018 (accessed Nov. 29, 2022). | H62: land use, agriculture and forestry | K62: land area | N62: square kilometer | O62: SUM | P62: LAU | Q62: yes | U62: =IF(COUNTIF(soi_input_variables!A:A,A62)>0,"yes","no") -> yes | V62: =IF(COUNTIF(midas_input_variables!A:A,A62)>0,"yes","no") -> no | W62: =IF(OR(COUNTIF(eucalc_variables_proxies!C:C,"*"&A62&"*")>0,COUNTIF(eucalc_variables_proxies!F:F,"*"&A62&"*")>0),"yes","no") -> yes | X62: =IF(COUNTIF(collected_variables_proxies!C:C,"*"&A62&"*")>0,"yes","no") -> no | Y62: =IF(OR(U62="yes",V62="yes",W62="yes",X62="yes"),"yes","no") -> yes | Z62: 0.1
A63: construction_sites_cover | B63: Construction sites cover | C63: Please note that only elements which are at least 25 hectares in area are captured here | D63: Copernicus Land Monitoring Service - Corine Land Cover | E63: https://land.copernicus.eu/pan-european/corine-land-cover/clc2018 | F63: Corine Land Cover, ‘CLC 2018 — Copernicus Land Monitoring Service’. https://land.copernicus.eu/pan-european/corine-land-cover/clc2018 (accessed Nov. 29, 2022). | H63: land use, buildings | N63: square kilometer | O63: SUM | P63: LAU | Q63: yes | U63: =IF(COUNTIF(soi_input_variables!A:A,A63)>0,"yes","no") -> no | V63: =IF(COUNTIF(midas_input_variables!A:A,A63)>0,"yes","no") -> no | W63: =IF(OR(COUNTIF(eucalc_variables_proxies!C:C,"*"&A63&"*")>0,COUNTIF(eucalc_variables_proxies!F:F,"*"&A63&"*")>0),"yes","no") -> no | X63: =IF(COUNTIF(collected_variables_proxies!C:C,"*"&A63&"*")>0,"yes","no") -> yes | Y63: =IF(OR(U63="yes",V63="yes",W63="yes",X63="yes"),"yes","no") -> yes | Z63: 0.1
A64: continuous_urban_fabric_cover | B64: Continuous urban fabric cover | C64: Please note that only elements which are at least 25 hectares in area are captured here | D64: Copernicus Land Monitoring Service - Corine Land Cover | E64: https://land.copernicus.eu/pan-european/corine-land-cover/clc2018 | F64: Corine Land Cover, ‘CLC 2018 — Copernicus Land Monitoring Service’. https://land.copernicus.eu/pan-european/corine-land-cover/clc2018 (accessed Nov. 29, 2022). | H64: land use, buildings | N64: square kilometer | O64: SUM | P64: LAU | Q64: yes | T64: Settlement area available for Germany at NUTS3 level - https://www.regionalstatistik.de/genesis/online?operation=abruftabelleBearbeiten&levelindex=2&levelid=1688460055798&auswahloperation=abruftabelleAuspraegungAuswaehlen&auswahlverzeichnis=ordnungsstruktur&auswahlziel=werteabruf&code=33111-02-01-4&auswahltext=&werteabruf=Werteabruf#abreadcrumb | U64: =IF(COUNTIF(soi_input_variables!A:A,A64)>0,"yes","no") -> yes | V64: =IF(COUNTIF(midas_input_variables!A:A,A64)>0,"yes","no") -> yes | W64: =IF(OR(COUNTIF(eucalc_variables_proxies!C:C,"*"&A64&"*")>0,COUNTIF(eucalc_variables_proxies!F:F,"*"&A64&"*")>0),"yes","no") -> yes | X64: =IF(COUNTIF(collected_variables_proxies!C:C,"*"&A64&"*")>0,"yes","no") -> yes | Y64: =IF(OR(U64="yes",V64="yes",W64="yes",X64="yes"),"yes","no") -> yes | Z64: 0.1
A65: cproj_annual_maximum_temperature_cooling_degree_days | B65: Cooling degree days - maximum | C65: Annual sum of daily maximum temperature above a threshold | D65: EURO-CORDEX: new high-resolution climate change projections for European impact research | E65: https://www.euro-cordex.net/060378/index.php.en | F65: D. Jacob et al., ‘EURO-CORDEX: new high-resolution climate change projections for European impact research’, Regional environmental change, vol. 14, no. 2, pp. 563–578, 2014. | H65: weather and climate | N65: cooling degree days | O65: AVG | P65: NUTS3 | Q65: yes | U65: =IF(COUNTIF(soi_input_variables!A:A,A65)>0,"yes","no") -> no | V65: =IF(COUNTIF(midas_input_variables!A:A,A65)>0,"yes","no") -> no | W65: =IF(OR(COUNTIF(eucalc_variables_proxies!C:C,"*"&A65&"*")>0,COUNTIF(eucalc_variables_proxies!F:F,"*"&A65&"*")>0),"yes","no") -> no | X65: =IF(COUNTIF(collected_variables_proxies!C:C,"*"&A65&"*")>0,"yes","no") -> no | Y65: =IF(OR(U65="yes",V65="yes",W65="yes",X65="yes"),"yes","no") -> no | Z65: 0.1
A66: cproj_annual_mean_temperature_cooling_degree_days | B66: Cooling degree days - mean | C66: Annual sum of daily mean temperature above a threshold | D66: EURO-CORDEX: new high-resolution climate change projections for European impact research | E66: https://www.euro-cordex.net/060378/index.php.en | F66: D. Jacob et al., ‘EURO-CORDEX: new high-resolution climate change projections for European impact research’, Regional environmental change, vol. 14, no. 2, pp. 563–578, 2014. | H66: weather and climate | N66: cooling degree days | O66: AVG | P66: NUTS3 | Q66: yes | U66: =IF(COUNTIF(soi_input_variables!A:A,A66)>0,"yes","no") -> yes | V66: =IF(COUNTIF(midas_input_variables!A:A,A66)>0,"yes","no") -> no | W66: =IF(OR(COUNTIF(eucalc_variables_proxies!C:C,"*"&A66&"*")>0,COUNTIF(eucalc_variables_proxies!F:F,"*"&A66&"*")>0),"yes","no") -> yes | X66: =IF(COUNTIF(collected_variables_proxies!C:C,"*"&A66&"*")>0,"yes","no") -> yes | Y66: =IF(OR(U66="yes",V66="yes",W66="yes",X66="yes"),"yes","no") -> yes | Z66: 0.1
A67: cproj_annual_minimum_temperature_cooling_degree_days | B67: Cooling degree days - minimum | C67: Annual sum of daily minimum temperature above a threshold | D67: EURO-CORDEX: new high-resolution climate change projections for European impact research | E67: https://www.euro-cordex.net/060378/index.php.en | F67: D. Jacob et al., ‘EURO-CORDEX: new high-resolution climate change projections for European impact research’, Regional environmental change, vol. 14, no. 2, pp. 563–578, 2014. | H67: weather and climate | N67: cooling degree days | O67: AVG | P67: NUTS3 | Q67: yes | U67: =IF(COUNTIF(soi_input_variables!A:A,A67)>0,"yes","no") -> no | V67: =IF(COUNTIF(midas_input_variables!A:A,A67)>0,"yes","no") -> no | W67: =IF(OR(COUNTIF(eucalc_variables_proxies!C:C,"*"&A67&"*")>0,COUNTIF(eucalc_variables_proxies!F:F,"*"&A67&"*")>0),"yes","no") -> no | X67: =IF(COUNTIF(collected_variables_proxies!C:C,"*"&A67&"*")>0,"yes","no") -> no | Y67: =IF(OR(U67="yes",V67="yes",W67="yes",X67="yes"),"yes","no") -> no | Z67: 0.1
A68: coping_capacity_to_natural_hazards | B68: Coping capacity to natural hazards | C68: Composite indicator obtained with multivariate statistical techniques. Source indicators are: natural population change; migration rate; tertiary educational attainment; R&D expenditure; R&D personnel and researchers; patent applications to the EPO; social capital; risk perception; hospital beds; practising physicians; GDP per inhabitant; professional, scientific and technical employments; spatial distribution of green infrastructure; potential green infrastructure network for Climate Change and Disaster Risk Reduction policies; gender equality index; quality of government index; municipalities signatories to the Covenant of Majors. For more information, please refer to the data source. The indicator value is in the range from 1 to 2, being 2 the highest vulnerability and 1 the lowest | D68: ESPON Database Portal | E68: https://database.espon.eu/indicator/2224/ | F68: ESPON Database Portal, ‘Indicator: Territorial coping capacity to natural hazards | ESPON Database Portal’, 2022. https://database.espon.eu/indicator/2224/ (accessed Nov. 23, 2022). | G68: Creative Commons Attribution 4.0 International (CC BY 4.0) | H68: climate hazard | I68: exposure | L68: vulnerability to natural hazards,susceptibility to natural hazards | N68: index | O68: AVG | P68: NUTS3 | Q68: yes | U68: =IF(COUNTIF(soi_input_variables!A:A,A68)>0,"yes","no") -> no | V68: =IF(COUNTIF(midas_input_variables!A:A,A68)>0,"yes","no") -> yes | W68: =IF(OR(COUNTIF(eucalc_variables_proxies!C:C,"*"&A68&"*")>0,COUNTIF(eucalc_variables_proxies!F:F,"*"&A68&"*")>0),"yes","no") -> no | X68: =IF(COUNTIF(collected_variables_proxies!C:C,"*"&A68&"*")>0,"yes","no") -> no | Y68: =IF(OR(U68="yes",V68="yes",W68="yes",X68="yes"),"yes","no") -> yes | Z68: 0.1
A69: cost_of_final_residential_energy_consumption_compared_to_gross_family_income | B69: Cost of final residential energy consumption compared to gross family income | C69: Classification of individual consumption by purpose (COICOP): Electricity, gas and other fuels | D69: Eurostat | E69: https://ec.europa.eu/eurostat/databrowser/view/ICW_AFF_01/default/table?lang=en | F69: Eurostat, “Disposable income of households (with expenditure greater than zero) spent on essential goods and services by income quantiles - experimental statistics,” Jul. 26, 2023. https://ec.europa.eu/eurostat/databrowser/view/ICW_AFF_01/default/table?lang=en (accessed Aug. 22, 2023). | G69: Creative Commons Attribution 4.0 International (CC BY 4.0) | H69: general stat | N69: percentage | O69: AVG | P69: NUTS0 | Q69: yes | U69: =IF(COUNTIF(soi_input_variables!A:A,A69)>0,"yes","no") -> no | V69: =IF(COUNTIF(midas_input_variables!A:A,A69)>0,"yes","no") -> no | W69: =IF(OR(COUNTIF(eucalc_variables_proxies!C:C,"*"&A69&"*")>0,COUNTIF(eucalc_variables_proxies!F:F,"*"&A69&"*")>0),"yes","no") -> no | X69: =IF(COUNTIF(collected_variables_proxies!C:C,"*"&A69&"*")>0,"yes","no") -> no | Y69: =IF(OR(U69="yes",V69="yes",W69="yes",X69="yes"),"yes","no") -> no | Z69: 0.1
A70: deaths | B70: Deaths | D70: Eurostat | E70: https://ec.europa.eu/eurostat/databrowser/view/demo_r_deaths/default/table?lang=en | F70: Eurostat, ‘Deaths (total) by NUTS 3 region’, 2022. https://ec.europa.eu/eurostat/databrowser/view/demo_r_deaths/default/table?lang=en (accessed Nov. 23, 2022). | G70: Creative Commons Attribution 4.0 International (CC BY 4.0) | H70: general stat | I70: mortality | N70: number | O70: SUM | P70: NUTS3 | Q70: yes | U70: =IF(COUNTIF(soi_input_variables!A:A,A70)>0,"yes","no") -> no | V70: =IF(COUNTIF(midas_input_variables!A:A,A70)>0,"yes","no") -> no | W70: =IF(OR(COUNTIF(eucalc_variables_proxies!C:C,"*"&A70&"*")>0,COUNTIF(eucalc_variables_proxies!F:F,"*"&A70&"*")>0),"yes","no") -> yes | X70: =IF(COUNTIF(collected_variables_proxies!C:C,"*"&A70&"*")>0,"yes","no") -> yes | Y70: =IF(OR(U70="yes",V70="yes",W70="yes",X70="yes"),"yes","no") -> yes | Z70: 0.1
A71: deaths_due_to_accidental_poisoning_by_and_exposure_to_noxious_substances | B71: Deaths due to accidental poisoning by and exposure to noxious substances | D71: Eurostat | E71: https://ec.europa.eu/eurostat/databrowser/view/HLTH_CD_ASDR2__custom_6650106/default/table?lang=en | F71: Eurostat, “Eurostat, “Causes of death - standardised death rate by NUTS 2 region of residence.” https://ec.europa.eu/eurostat/databrowser/view/HLTH_CD_ASDR2__custom_6650106/default/table?lang=en (accessed Jun. 23, 2023). | G71: Creative Commons Attribution 4.0 International (CC BY 4.0) | H71: health | I71: mortality | N71: number | O71: SUM | P71: NUTS2 | Q71: yes | R71: percentage_of_deaths_due_to_accidental_poisoning_by_and_exposure_to_noxious_substances*population|/100 | U71: =IF(COUNTIF(soi_input_variables!A:A,A71)>0,"yes","no") -> yes | V71: =IF(COUNTIF(midas_input_variables!A:A,A71)>0,"yes","no") -> no | W71: =IF(OR(COUNTIF(eucalc_variables_proxies!C:C,"*"&A71&"*")>0,COUNTIF(eucalc_variables_proxies!F:F,"*"&A71&"*")>0),"yes","no") -> no | X71: =IF(COUNTIF(collected_variables_proxies!C:C,"*"&A71&"*")>0,"yes","no") -> no | Y71: =IF(OR(U71="yes",V71="yes",W71="yes",X71="yes"),"yes","no") -> yes | Z71: 0.1
A72: deaths_due_to_road_injuries | B72: Deaths due to road injuries | D72: Our World in Data | E72: https://ourworldindata.org/grapher/annual-number-of-deaths-by-cause | F72: Hannah Ritchie, Fiona Spooner and Max Roser (2018) - \"Causes of death\". Published online at OurWorldInData.org. Retrieved from: \"https://ourworldindata.org/causes-of-death\" [Online Resource] | G72: Creative Commons Attribution 4.0 International (CC BY 4.0) | H72: transport | I72: mortality | N72: number | O72: SUM | P72: NUTS0 | Q72: yes | U72: =IF(COUNTIF(soi_input_variables!A:A,A72)>0,"yes","no") -> yes | V72: =IF(COUNTIF(midas_input_variables!A:A,A72)>0,"yes","no") -> yes | W72: =IF(OR(COUNTIF(eucalc_variables_proxies!C:C,"*"&A72&"*")>0,COUNTIF(eucalc_variables_proxies!F:F,"*"&A72&"*")>0),"yes","no") -> no | X72: =IF(COUNTIF(collected_variables_proxies!C:C,"*"&A72&"*")>0,"yes","no") -> no | Y72: =IF(OR(U72="yes",V72="yes",W72="yes",X72="yes"),"yes","no") -> yes | Z72: 0.1
A73: deaths_due_to_unsafe_water_source_and_sanitation | B73: Deaths due to unsafe water source and sanitation | D73: Our World in Data | E73: https://ourworldindata.org/water-access | F73: Hannah Ritchie and Max Roser (2021) - \"Clean Water and Sanitation\". Published online at OurWorldInData.org. Retrieved from: \"https://ourworldindata.org/clean-water-sanitation\" [Online Resource] | G73: Creative Commons Attribution 4.0 International (CC BY 4.0) | H73: health | I73: mortality | N73: number | O73: SUM | P73: NUTS0 | Q73: yes | U73: =IF(COUNTIF(soi_input_variables!A:A,A73)>0,"yes","no") -> yes | V73: =IF(COUNTIF(midas_input_variables!A:A,A73)>0,"yes","no") -> yes | W73: =IF(OR(COUNTIF(eucalc_variables_proxies!C:C,"*"&A73&"*")>0,COUNTIF(eucalc_variables_proxies!F:F,"*"&A73&"*")>0),"yes","no") -> no | X73: =IF(COUNTIF(collected_variables_proxies!C:C,"*"&A73&"*")>0,"yes","no") -> no | Y73: =IF(OR(U73="yes",V73="yes",W73="yes",X73="yes"),"yes","no") -> yes | Z73: 0.1
A74: degree_of_urbanisation | B74: Degree of urbanisation | C74: cities, otherwise referred to as densely populated areas — code 1; towns and suburbs, otherwise referred to as intermediate density areas — code 2; rural areas, otherwise referred to as thinly populated areas — code 3; areas where the Government of the Republic of Cyprus does not exercise effective control — code 9; | D74: GISCO - Eurostat | E74: https://ec.europa.eu/eurostat/web/gisco/geodata/statistical-units/local-administrative-units | F74: GISCO - Eurostat, ‘NUTS - GISCO - Eurostat’, 2021. https://ec.europa.eu/eurostat/web/gisco/geodata/reference-data/administrative-units-statistical-units/lau (accessed Nov. 23, 2022). | G74: Creative Commons Attribution 4.0 International (CC BY 4.0) | H74: general stat | N74: number | O74: MAX | P74: LAU | Q74: yes | U74: =IF(COUNTIF(soi_input_variables!A:A,A74)>0,"yes","no") -> no | V74: =IF(COUNTIF(midas_input_variables!A:A,A74)>0,"yes","no") -> no | W74: =IF(OR(COUNTIF(eucalc_variables_proxies!C:C,"*"&A74&"*")>0,COUNTIF(eucalc_variables_proxies!F:F,"*"&A74&"*")>0),"yes","no") -> no | X74: =IF(COUNTIF(collected_variables_proxies!C:C,"*"&A74&"*")>0,"yes","no") -> no | Y74: =IF(OR(U74="yes",V74="yes",W74="yes",X74="yes"),"yes","no") -> no | Z74: 0.1
A75: discontinuous_urban_fabric_cover | B75: Discontinuous urban fabric cover | C75: Please note that only elements which are at least 25 hectares in area are captured here | D75: Copernicus Land Monitoring Service - Corine Land Cover | E75: https://land.copernicus.eu/pan-european/corine-land-cover/clc2018 | F75: Corine Land Cover, ‘CLC 2018 — Copernicus Land Monitoring Service’. https://land.copernicus.eu/pan-european/corine-land-cover/clc2018 (accessed Nov. 29, 2022). | H75: land use, buildings | N75: square kilometer | O75: SUM | P75: LAU | Q75: yes | U75: =IF(COUNTIF(soi_input_variables!A:A,A75)>0,"yes","no") -> yes | V75: =IF(COUNTIF(midas_input_variables!A:A,A75)>0,"yes","no") -> no | W75: =IF(OR(COUNTIF(eucalc_variables_proxies!C:C,"*"&A75&"*")>0,COUNTIF(eucalc_variables_proxies!F:F,"*"&A75&"*")>0),"yes","no") -> yes | X75: =IF(COUNTIF(collected_variables_proxies!C:C,"*"&A75&"*")>0,"yes","no") -> yes | Y75: =IF(OR(U75="yes",V75="yes",W75="yes",X75="yes"),"yes","no") -> yes | Z75: 0.1
A76: dump_sites_cover | B76: Dump sites cover | C76: Please note that only elements which are at least 25 hectares in area are captured here | D76: Copernicus Land Monitoring Service - Corine Land Cover | E76: https://land.copernicus.eu/pan-european/corine-land-cover/clc2018 | F76: Corine Land Cover, ‘CLC 2018 — Copernicus Land Monitoring Service’. https://land.copernicus.eu/pan-european/corine-land-cover/clc2018 (accessed Nov. 29, 2022). | H76: land use, waste | N76: square kilometer | O76: SUM | P76: LAU | Q76: yes | U76: =IF(COUNTIF(soi_input_variables!A:A,A76)>0,"yes","no") -> no | V76: =IF(COUNTIF(midas_input_variables!A:A,A76)>0,"yes","no") -> no | W76: =IF(OR(COUNTIF(eucalc_variables_proxies!C:C,"*"&A76&"*")>0,COUNTIF(eucalc_variables_proxies!F:F,"*"&A76&"*")>0),"yes","no") -> no | X76: =IF(COUNTIF(collected_variables_proxies!C:C,"*"&A76&"*")>0,"yes","no") -> yes | Y76: =IF(OR(U76="yes",V76="yes",W76="yes",X76="yes"),"yes","no") -> yes | Z76: 0.1
A77: electricity_prices_for_household_consumers | B77: Electricity prices for household consumers | C77: Bi-annual data available. Data collected for the second half of 2022. | D77: Eurostat | E77: https://ec.europa.eu/eurostat/databrowser/view/nrg_pc_204/default/table?lang=en | F77: Eurostat, “Electricity prices for household consumers - bi-annual data (from 2007 onwards),” 2022. https://ec.europa.eu/eurostat/databrowser/view/nrg_pc_204/default/table?lang=en (accessed Apr. 03, 2023). | G77: Creative Commons Attribution 4.0 International (CC BY 4.0) | H77: general stat | I77: finance | N77: Euro/kWh | O77: AVG | P77: NUTS0 | Q77: yes | U77: =IF(COUNTIF(soi_input_variables!A:A,A77)>0,"yes","no") -> no | V77: =IF(COUNTIF(midas_input_variables!A:A,A77)>0,"yes","no") -> no | W77: =IF(OR(COUNTIF(eucalc_variables_proxies!C:C,"*"&A77&"*")>0,COUNTIF(eucalc_variables_proxies!F:F,"*"&A77&"*")>0),"yes","no") -> no | X77: =IF(COUNTIF(collected_variables_proxies!C:C,"*"&A77&"*")>0,"yes","no") -> no | Y77: =IF(OR(U77="yes",V77="yes",W77="yes",X77="yes"),"yes","no") -> no | Z77: 0.1
A78: electricity_production_with_anthracite | B78: Electricity production with anthracite | D78: Eurostat | E78: https://ec.europa.eu/eurostat/databrowser/view/NRG_BAL_C/default/table?lang=en | F78: Eurostat, “Complete energy balances,” Apr. 28, 2023. https://ec.europa.eu/eurostat/databrowser/view/NRG_BAL_C/default/table?lang=en (accessed Aug. 01, 2023). | G78: Creative Commons Attribution 4.0 International (CC BY 4.0) | H78: energy | N78: MWh | O78: SUM | P78: NUTS0 | Q78: yes | U78: =IF(COUNTIF(soi_input_variables!A:A,A78)>0,"yes","no") -> yes | V78: =IF(COUNTIF(midas_input_variables!A:A,A78)>0,"yes","no") -> no | W78: =IF(OR(COUNTIF(eucalc_variables_proxies!C:C,"*"&A78&"*")>0,COUNTIF(eucalc_variables_proxies!F:F,"*"&A78&"*")>0),"yes","no") -> no | X78: =IF(COUNTIF(collected_variables_proxies!C:C,"*"&A78&"*")>0,"yes","no") -> no | Y78: =IF(OR(U78="yes",V78="yes",W78="yes",X78="yes"),"yes","no") -> yes | Z78: 0.1
A79: electricity_production_with_biogases | B79: Electricity production with biogases | D79: Eurostat | E79: https://ec.europa.eu/eurostat/databrowser/view/NRG_BAL_C/default/table?lang=en | F79: Eurostat, “Complete energy balances,” Apr. 28, 2023. https://ec.europa.eu/eurostat/databrowser/view/NRG_BAL_C/default/table?lang=en (accessed Aug. 01, 2023). | G79: Creative Commons Attribution 4.0 International (CC BY 4.0) | H79: energy | N79: MWh | O79: SUM | P79: NUTS0 | Q79: yes | U79: =IF(COUNTIF(soi_input_variables!A:A,A79)>0,"yes","no") -> no | V79: =IF(COUNTIF(midas_input_variables!A:A,A79)>0,"yes","no") -> no | W79: =IF(OR(COUNTIF(eucalc_variables_proxies!C:C,"*"&A79&"*")>0,COUNTIF(eucalc_variables_proxies!F:F,"*"&A79&"*")>0),"yes","no") -> no | X79: =IF(COUNTIF(collected_variables_proxies!C:C,"*"&A79&"*")>0,"yes","no") -> no | Y79: =IF(OR(U79="yes",V79="yes",W79="yes",X79="yes"),"yes","no") -> no | Z79: 0.1
A80: electricity_production_with_bitumen | B80: Electricity production with bitumen | D80: Eurostat | E80: https://ec.europa.eu/eurostat/databrowser/view/NRG_BAL_C/default/table?lang=en | F80: Eurostat, “Complete energy balances,” Apr. 28, 2023. https://ec.europa.eu/eurostat/databrowser/view/NRG_BAL_C/default/table?lang=en (accessed Aug. 01, 2023). | G80: Creative Commons Attribution 4.0 International (CC BY 4.0) | H80: energy | N80: MWh | O80: SUM | P80: NUTS0 | Q80: yes | U80: =IF(COUNTIF(soi_input_variables!A:A,A80)>0,"yes","no") -> no | V80: =IF(COUNTIF(midas_input_variables!A:A,A80)>0,"yes","no") -> no | W80: =IF(OR(COUNTIF(eucalc_variables_proxies!C:C,"*"&A80&"*")>0,COUNTIF(eucalc_variables_proxies!F:F,"*"&A80&"*")>0),"yes","no") -> no | X80: =IF(COUNTIF(collected_variables_proxies!C:C,"*"&A80&"*")>0,"yes","no") -> no | Y80: =IF(OR(U80="yes",V80="yes",W80="yes",X80="yes"),"yes","no") -> no | Z80: 0.1
A81: electricity_production_with_blast_furnace_gas | B81: Electricity production with blast furnace gas | D81: Eurostat | E81: https://ec.europa.eu/eurostat/databrowser/view/NRG_BAL_C/default/table?lang=en | F81: Eurostat, “Complete energy balances,” Apr. 28, 2023. https://ec.europa.eu/eurostat/databrowser/view/NRG_BAL_C/default/table?lang=en (accessed Aug. 01, 2023). | G81: Creative Commons Attribution 4.0 International (CC BY 4.0) | H81: energy | N81: MWh | O81: SUM | P81: NUTS0 | Q81: yes | U81: =IF(COUNTIF(soi_input_variables!A:A,A81)>0,"yes","no") -> no | V81: =IF(COUNTIF(midas_input_variables!A:A,A81)>0,"yes","no") -> no | W81: =IF(OR(COUNTIF(eucalc_variables_proxies!C:C,"*"&A81&"*")>0,COUNTIF(eucalc_variables_proxies!F:F,"*"&A81&"*")>0),"yes","no") -> no | X81: =IF(COUNTIF(collected_variables_proxies!C:C,"*"&A81&"*")>0,"yes","no") -> no | Y81: =IF(OR(U81="yes",V81="yes",W81="yes",X81="yes"),"yes","no") -> no | Z81: 0.1
A82: electricity_production_with_brown_coal_briquettes | B82: Electricity production with brown coal briquettes | D82: Eurostat | E82: https://ec.europa.eu/eurostat/databrowser/view/NRG_BAL_C/default/table?lang=en | F82: Eurostat, “Complete energy balances,” Apr. 28, 2023. https://ec.europa.eu/eurostat/databrowser/view/NRG_BAL_C/default/table?lang=en (accessed Aug. 01, 2023). | G82: Creative Commons Attribution 4.0 International (CC BY 4.0) | H82: energy | N82: MWh | O82: SUM | P82: NUTS0 | Q82: yes | U82: =IF(COUNTIF(soi_input_variables!A:A,A82)>0,"yes","no") -> no | V82: =IF(COUNTIF(midas_input_variables!A:A,A82)>0,"yes","no") -> no | W82: =IF(OR(COUNTIF(eucalc_variables_proxies!C:C,"*"&A82&"*")>0,COUNTIF(eucalc_variables_proxies!F:F,"*"&A82&"*")>0),"yes","no") -> no | X82: =IF(COUNTIF(collected_variables_proxies!C:C,"*"&A82&"*")>0,"yes","no") -> no | Y82: =IF(OR(U82="yes",V82="yes",W82="yes",X82="yes"),"yes","no") -> no | Z82: 0.1
A83: electricity_production_with_coal_tar | B83: Electricity production with coal tar | D83: Eurostat | E83: https://ec.europa.eu/eurostat/databrowser/view/NRG_BAL_C/default/table?lang=en | F83: Eurostat, “Complete energy balances,” Apr. 28, 2023. https://ec.europa.eu/eurostat/databrowser/view/NRG_BAL_C/default/table?lang=en (accessed Aug. 01, 2023). | G83: Creative Commons Attribution 4.0 International (CC BY 4.0) | H83: energy | N83: MWh | O83: SUM | P83: NUTS0 | Q83: yes | U83: =IF(COUNTIF(soi_input_variables!A:A,A83)>0,"yes","no") -> no | V83: =IF(COUNTIF(midas_input_variables!A:A,A83)>0,"yes","no") -> no | W83: =IF(OR(COUNTIF(eucalc_variables_proxies!C:C,"*"&A83&"*")>0,COUNTIF(eucalc_variables_proxies!F:F,"*"&A83&"*")>0),"yes","no") -> no | X83: =IF(COUNTIF(collected_variables_proxies!C:C,"*"&A83&"*")>0,"yes","no") -> no | Y83: =IF(OR(U83="yes",V83="yes",W83="yes",X83="yes"),"yes","no") -> no | Z83: 0.1
A84: electricity_production_with_coke_oven_coke | B84: Electricity production with coke oven coke | D84: Eurostat | E84: https://ec.europa.eu/eurostat/databrowser/view/NRG_BAL_C/default/table?lang=en | F84: Eurostat, “Complete energy balances,” Apr. 28, 2023. https://ec.europa.eu/eurostat/databrowser/view/NRG_BAL_C/default/table?lang=en (accessed Aug. 01, 2023). | G84: Creative Commons Attribution 4.0 International (CC BY 4.0) | H84: energy | N84: MWh | O84: SUM | P84: NUTS0 | Q84: yes | U84: =IF(COUNTIF(soi_input_variables!A:A,A84)>0,"yes","no") -> no | V84: =IF(COUNTIF(midas_input_variables!A:A,A84)>0,"yes","no") -> no | W84: =IF(OR(COUNTIF(eucalc_variables_proxies!C:C,"*"&A84&"*")>0,COUNTIF(eucalc_variables_proxies!F:F,"*"&A84&"*")>0),"yes","no") -> no | X84: =IF(COUNTIF(collected_variables_proxies!C:C,"*"&A84&"*")>0,"yes","no") -> no | Y84: =IF(OR(U84="yes",V84="yes",W84="yes",X84="yes"),"yes","no") -> no | Z84: 0.1
A85: electricity_production_with_coke_oven_gas | B85: Electricity production with coke oven gas | D85: Eurostat | E85: https://ec.europa.eu/eurostat/databrowser/view/NRG_BAL_C/default/table?lang=en | F85: Eurostat, “Complete energy balances,” Apr. 28, 2023. https://ec.europa.eu/eurostat/databrowser/view/NRG_BAL_C/default/table?lang=en (accessed Aug. 01, 2023). | G85: Creative Commons Attribution 4.0 International (CC BY 4.0) | H85: energy | N85: MWh | O85: SUM | P85: NUTS0 | Q85: yes | U85: =IF(COUNTIF(soi_input_variables!A:A,A85)>0,"yes","no") -> no | V85: =IF(COUNTIF(midas_input_variables!A:A,A85)>0,"yes","no") -> no | W85: =IF(OR(COUNTIF(eucalc_variables_proxies!C:C,"*"&A85&"*")>0,COUNTIF(eucalc_variables_proxies!F:F,"*"&A85&"*")>0),"yes","no") -> no | X85: =IF(COUNTIF(collected_variables_proxies!C:C,"*"&A85&"*")>0,"yes","no") -> no | Y85: =IF(OR(U85="yes",V85="yes",W85="yes",X85="yes"),"yes","no") -> no
A86: electricity_production_with_coking_coal | B86: Electricity production with coking coal | D86: Eurostat | E86: https://ec.europa.eu/eurostat/databrowser/view/NRG_BAL_C/default/table?lang=en | F86: Eurostat, “Complete energy balances,” Apr. 28, 2023. https://ec.europa.eu/eurostat/databrowser/view/NRG_BAL_C/default/table?lang=en (accessed Aug. 01, 2023). | G86: Creative Commons Attribution 4.0 International (CC BY 4.0) | H86: energy | N86: MWh | O86: SUM | P86: NUTS0 | Q86: yes | U86: =IF(COUNTIF(soi_input_variables!A:A,A86)>0,"yes","no") -> no | V86: =IF(COUNTIF(midas_input_variables!A:A,A86)>0,"yes","no") -> no | W86: =IF(OR(COUNTIF(eucalc_variables_proxies!C:C,"*"&A86&"*")>0,COUNTIF(eucalc_variables_proxies!F:F,"*"&A86&"*")>0),"yes","no") -> no | X86: =IF(COUNTIF(collected_variables_proxies!C:C,"*"&A86&"*")>0,"yes","no") -> no | Y86: =IF(OR(U86="yes",V86="yes",W86="yes",X86="yes"),"yes","no") -> no | Z86: 1
A87: electricity_production_with_crude_oil | B87: Electricity production with crude oil | D87: Eurostat | E87: https://ec.europa.eu/eurostat/databrowser/view/NRG_BAL_C/default/table?lang=en | F87: Eurostat, “Complete energy balances,” Apr. 28, 2023. https://ec.europa.eu/eurostat/databrowser/view/NRG_BAL_C/default/table?lang=en (accessed Aug. 01, 2023). | G87: Creative Commons Attribution 4.0 International (CC BY 4.0) | H87: energy | N87: MWh | O87: SUM | P87: NUTS0 | Q87: yes | U87: =IF(COUNTIF(soi_input_variables!A:A,A87)>0,"yes","no") -> no | V87: =IF(COUNTIF(midas_input_variables!A:A,A87)>0,"yes","no") -> no | W87: =IF(OR(COUNTIF(eucalc_variables_proxies!C:C,"*"&A87&"*")>0,COUNTIF(eucalc_variables_proxies!F:F,"*"&A87&"*")>0),"yes","no") -> no | X87: =IF(COUNTIF(collected_variables_proxies!C:C,"*"&A87&"*")>0,"yes","no") -> no | Y87: =IF(OR(U87="yes",V87="yes",W87="yes",X87="yes"),"yes","no") -> no
A88: electricity_production_with_fuel_oil | B88: Electricity production with fuel oil | D88: Eurostat | E88: https://ec.europa.eu/eurostat/databrowser/view/NRG_BAL_C/default/table?lang=en | F88: Eurostat, “Complete energy balances,” Apr. 28, 2023. https://ec.europa.eu/eurostat/databrowser/view/NRG_BAL_C/default/table?lang=en (accessed Aug. 01, 2023). | G88: Creative Commons Attribution 4.0 International (CC BY 4.0) | H88: energy | N88: MWh | O88: SUM | P88: NUTS0 | Q88: yes | U88: =IF(COUNTIF(soi_input_variables!A:A,A88)>0,"yes","no") -> no | V88: =IF(COUNTIF(midas_input_variables!A:A,A88)>0,"yes","no") -> no | W88: =IF(OR(COUNTIF(eucalc_variables_proxies!C:C,"*"&A88&"*")>0,COUNTIF(eucalc_variables_proxies!F:F,"*"&A88&"*")>0),"yes","no") -> no | X88: =IF(COUNTIF(collected_variables_proxies!C:C,"*"&A88&"*")>0,"yes","no") -> no | Y88: =IF(OR(U88="yes",V88="yes",W88="yes",X88="yes"),"yes","no") -> no
A89: electricity_production_with_gas_coke | B89: Electricity production with gas coke | D89: Eurostat | E89: https://ec.europa.eu/eurostat/databrowser/view/NRG_BAL_C/default/table?lang=en | F89: Eurostat, “Complete energy balances,” Apr. 28, 2023. https://ec.europa.eu/eurostat/databrowser/view/NRG_BAL_C/default/table?lang=en (accessed Aug. 01, 2023). | G89: Creative Commons Attribution 4.0 International (CC BY 4.0) | H89: energy | N89: MWh | O89: SUM | P89: NUTS0 | Q89: yes | U89: =IF(COUNTIF(soi_input_variables!A:A,A89)>0,"yes","no") -> no | V89: =IF(COUNTIF(midas_input_variables!A:A,A89)>0,"yes","no") -> no | W89: =IF(OR(COUNTIF(eucalc_variables_proxies!C:C,"*"&A89&"*")>0,COUNTIF(eucalc_variables_proxies!F:F,"*"&A89&"*")>0),"yes","no") -> no | X89: =IF(COUNTIF(collected_variables_proxies!C:C,"*"&A89&"*")>0,"yes","no") -> no | Y89: =IF(OR(U89="yes",V89="yes",W89="yes",X89="yes"),"yes","no") -> no
A90: electricity_production_with_gas_oil_and_diesel_oil_excluding_biofuel_portion | B90: Electricity production with gas oil and diesel oil excluding biofuel portion | D90: Eurostat | E90: https://ec.europa.eu/eurostat/databrowser/view/NRG_BAL_C/default/table?lang=en | F90: Eurostat, “Complete energy balances,” Apr. 28, 2023. https://ec.europa.eu/eurostat/databrowser/view/NRG_BAL_C/default/table?lang=en (accessed Aug. 01, 2023). | G90: Creative Commons Attribution 4.0 International (CC BY 4.0) | H90: energy | N90: MWh | O90: SUM | P90: NUTS0 | Q90: yes | U90: =IF(COUNTIF(soi_input_variables!A:A,A90)>0,"yes","no") -> no | V90: =IF(COUNTIF(midas_input_variables!A:A,A90)>0,"yes","no") -> no | W90: =IF(OR(COUNTIF(eucalc_variables_proxies!C:C,"*"&A90&"*")>0,COUNTIF(eucalc_variables_proxies!F:F,"*"&A90&"*")>0),"yes","no") -> no | X90: =IF(COUNTIF(collected_variables_proxies!C:C,"*"&A90&"*")>0,"yes","no") -> no | Y90: =IF(OR(U90="yes",V90="yes",W90="yes",X90="yes"),"yes","no") -> no
A91: electricity_production_with_gas_works_gas | B91: Electricity production with gas works gas | D91: Eurostat | E91: https://ec.europa.eu/eurostat/databrowser/view/NRG_BAL_C/default/table?lang=en | F91: Eurostat, “Complete energy balances,” Apr. 28, 2023. https://ec.europa.eu/eurostat/databrowser/view/NRG_BAL_C/default/table?lang=en (accessed Aug. 01, 2023). | G91: Creative Commons Attribution 4.0 International (CC BY 4.0) | H91: energy | N91: MWh | O91: SUM | P91: NUTS0 | Q91: yes | U91: =IF(COUNTIF(soi_input_variables!A:A,A91)>0,"yes","no") -> no | V91: =IF(COUNTIF(midas_input_variables!A:A,A91)>0,"yes","no") -> no | W91: =IF(OR(COUNTIF(eucalc_variables_proxies!C:C,"*"&A91&"*")>0,COUNTIF(eucalc_variables_proxies!F:F,"*"&A91&"*")>0),"yes","no") -> no | X91: =IF(COUNTIF(collected_variables_proxies!C:C,"*"&A91&"*")>0,"yes","no") -> no | Y91: =IF(OR(U91="yes",V91="yes",W91="yes",X91="yes"),"yes","no") -> no
A92: electricity_production_with_geothermal | B92: Electricity production with geothermal | D92: Eurostat | E92: https://ec.europa.eu/eurostat/databrowser/view/NRG_BAL_C/default/table?lang=en | F92: Eurostat, “Complete energy balances,” Apr. 28, 2023. https://ec.europa.eu/eurostat/databrowser/view/NRG_BAL_C/default/table?lang=en (accessed Aug. 01, 2023). | G92: Creative Commons Attribution 4.0 International (CC BY 4.0) | H92: energy | N92: MWh | O92: SUM | P92: NUTS0 | Q92: yes | U92: =IF(COUNTIF(soi_input_variables!A:A,A92)>0,"yes","no") -> no | V92: =IF(COUNTIF(midas_input_variables!A:A,A92)>0,"yes","no") -> no | W92: =IF(OR(COUNTIF(eucalc_variables_proxies!C:C,"*"&A92&"*")>0,COUNTIF(eucalc_variables_proxies!F:F,"*"&A92&"*")>0),"yes","no") -> no | X92: =IF(COUNTIF(collected_variables_proxies!C:C,"*"&A92&"*")>0,"yes","no") -> no | Y92: =IF(OR(U92="yes",V92="yes",W92="yes",X92="yes"),"yes","no") -> no
A93: electricity_production_with_heat | B93: Electricity production with heat | D93: Eurostat | E93: https://ec.europa.eu/eurostat/databrowser/view/NRG_BAL_C/default/table?lang=en | F93: Eurostat, “Complete energy balances,” Apr. 28, 2023. https://ec.europa.eu/eurostat/databrowser/view/NRG_BAL_C/default/table?lang=en (accessed Aug. 01, 2023). | G93: Creative Commons Attribution 4.0 International (CC BY 4.0) | H93: energy | N93: MWh | O93: SUM | P93: NUTS0 | Q93: yes | U93: =IF(COUNTIF(soi_input_variables!A:A,A93)>0,"yes","no") -> no | V93: =IF(COUNTIF(midas_input_variables!A:A,A93)>0,"yes","no") -> no | W93: =IF(OR(COUNTIF(eucalc_variables_proxies!C:C,"*"&A93&"*")>0,COUNTIF(eucalc_variables_proxies!F:F,"*"&A93&"*")>0),"yes","no") -> no | X93: =IF(COUNTIF(collected_variables_proxies!C:C,"*"&A93&"*")>0,"yes","no") -> no | Y93: =IF(OR(U93="yes",V93="yes",W93="yes",X93="yes"),"yes","no") -> no
A94: electricity_production_with_hydro | B94: Electricity production with hydro | D94: Eurostat | E94: https://ec.europa.eu/eurostat/databrowser/view/NRG_BAL_C/default/table?lang=en | F94: Eurostat, “Complete energy balances,” Apr. 28, 2023. https://ec.europa.eu/eurostat/databrowser/view/NRG_BAL_C/default/table?lang=en (accessed Aug. 01, 2023). | G94: Creative Commons Attribution 4.0 International (CC BY 4.0) | H94: energy | N94: MWh | O94: SUM | P94: NUTS0 | Q94: yes | U94: =IF(COUNTIF(soi_input_variables!A:A,A94)>0,"yes","no") -> no | V94: =IF(COUNTIF(midas_input_variables!A:A,A94)>0,"yes","no") -> no | W94: =IF(OR(COUNTIF(eucalc_variables_proxies!C:C,"*"&A94&"*")>0,COUNTIF(eucalc_variables_proxies!F:F,"*"&A94&"*")>0),"yes","no") -> no | X94: =IF(COUNTIF(collected_variables_proxies!C:C,"*"&A94&"*")>0,"yes","no") -> no | Y94: =IF(OR(U94="yes",V94="yes",W94="yes",X94="yes"),"yes","no") -> no
A95: electricity_production_with_industrial_waste_non_renewable | B95: Electricity production with industrial waste non-renewable | D95: Eurostat | E95: https://ec.europa.eu/eurostat/databrowser/view/NRG_BAL_C/default/table?lang=en | F95: Eurostat, “Complete energy balances,” Apr. 28, 2023. https://ec.europa.eu/eurostat/databrowser/view/NRG_BAL_C/default/table?lang=en (accessed Aug. 01, 2023). | G95: Creative Commons Attribution 4.0 International (CC BY 4.0) | H95: energy | N95: MWh | O95: SUM | P95: NUTS0 | Q95: yes | U95: =IF(COUNTIF(soi_input_variables!A:A,A95)>0,"yes","no") -> no | V95: =IF(COUNTIF(midas_input_variables!A:A,A95)>0,"yes","no") -> no | W95: =IF(OR(COUNTIF(eucalc_variables_proxies!C:C,"*"&A95&"*")>0,COUNTIF(eucalc_variables_proxies!F:F,"*"&A95&"*")>0),"yes","no") -> no | X95: =IF(COUNTIF(collected_variables_proxies!C:C,"*"&A95&"*")>0,"yes","no") -> no | Y95: =IF(OR(U95="yes",V95="yes",W95="yes",X95="yes"),"yes","no") -> no
A96: electricity_production_with_kerosene_type_jet_fuel_excluding_biofuel_portion | B96: Electricity production with kerosene type jet fuel excluding biofuel portion | D96: Eurostat | E96: https://ec.europa.eu/eurostat/databrowser/view/NRG_BAL_C/default/table?lang=en | F96: Eurostat, “Complete energy balances,” Apr. 28, 2023. https://ec.europa.eu/eurostat/databrowser/view/NRG_BAL_C/default/table?lang=en (accessed Aug. 01, 2023). | G96: Creative Commons Attribution 4.0 International (CC BY 4.0) | H96: energy | N96: MWh | O96: SUM | P96: NUTS0 | Q96: yes | U96: =IF(COUNTIF(soi_input_variables!A:A,A96)>0,"yes","no") -> no | V96: =IF(COUNTIF(midas_input_variables!A:A,A96)>0,"yes","no") -> no | W96: =IF(OR(COUNTIF(eucalc_variables_proxies!C:C,"*"&A96&"*")>0,COUNTIF(eucalc_variables_proxies!F:F,"*"&A96&"*")>0),"yes","no") -> no | X96: =IF(COUNTIF(collected_variables_proxies!C:C,"*"&A96&"*")>0,"yes","no") -> no | Y96: =IF(OR(U96="yes",V96="yes",W96="yes",X96="yes"),"yes","no") -> no
A97: electricity_production_with_lignite | B97: Electricity production with lignite | D97: Eurostat | E97: https://ec.europa.eu/eurostat/databrowser/view/NRG_BAL_C/default/table?lang=en | F97: Eurostat, “Complete energy balances,” Apr. 28, 2023. https://ec.europa.eu/eurostat/databrowser/view/NRG_BAL_C/default/table?lang=en (accessed Aug. 01, 2023). | G97: Creative Commons Attribution 4.0 International (CC BY 4.0) | H97: energy | N97: MWh | O97: SUM | P97: NUTS0 | Q97: yes | U97: =IF(COUNTIF(soi_input_variables!A:A,A97)>0,"yes","no") -> yes | V97: =IF(COUNTIF(midas_input_variables!A:A,A97)>0,"yes","no") -> no | W97: =IF(OR(COUNTIF(eucalc_variables_proxies!C:C,"*"&A97&"*")>0,COUNTIF(eucalc_variables_proxies!F:F,"*"&A97&"*")>0),"yes","no") -> no | X97: =IF(COUNTIF(collected_variables_proxies!C:C,"*"&A97&"*")>0,"yes","no") -> no | Y97: =IF(OR(U97="yes",V97="yes",W97="yes",X97="yes"),"yes","no") -> yes
A98: electricity_production_with_liquefied_petroleum_gases | B98: Electricity production with liquefied petroleum gases | D98: Eurostat | E98: https://ec.europa.eu/eurostat/databrowser/view/NRG_BAL_C/default/table?lang=en | F98: Eurostat, “Complete energy balances,” Apr. 28, 2023. https://ec.europa.eu/eurostat/databrowser/view/NRG_BAL_C/default/table?lang=en (accessed Aug. 01, 2023). | G98: Creative Commons Attribution 4.0 International (CC BY 4.0) | H98: energy | N98: MWh | O98: SUM | P98: NUTS0 | Q98: yes | U98: =IF(COUNTIF(soi_input_variables!A:A,A98)>0,"yes","no") -> yes | V98: =IF(COUNTIF(midas_input_variables!A:A,A98)>0,"yes","no") -> no | W98: =IF(OR(COUNTIF(eucalc_variables_proxies!C:C,"*"&A98&"*")>0,COUNTIF(eucalc_variables_proxies!F:F,"*"&A98&"*")>0),"yes","no") -> no | X98: =IF(COUNTIF(collected_variables_proxies!C:C,"*"&A98&"*")>0,"yes","no") -> no | Y98: =IF(OR(U98="yes",V98="yes",W98="yes",X98="yes"),"yes","no") -> yes
... A123: embankment_or_dyke_length | B123: Embankment or dyke length | D123: OpenStreetMap | E123: https://download.geofabrik.de/ | F123: OpenStreetMap contributors (2017). Planet dump retrieved from https://planet.osm.org . https://www. openstreetmap.org. | G123: Open Data Commons Open Database License (ODbL) | H123: land use | N123: kilometer | O123: SUM | P123: LAU | Q123: yes | U123: =IF(COUNTIF(soi_input_variables!A:A,A123)>0,"yes","no") -> no | V123: =IF(COUNTIF(midas_input_variables!A:A,A123)>0,"yes","no") -> no | W123: =IF(OR(COUNTIF(eucalc_variables_proxies!C:C,"*"&A123&"*")>0,COUNTIF(eucalc_variables_proxies!F:F,"*"&A123&"*")>0),"yes","no") -> no | X123: =IF(COUNTIF(collected_variables_proxies!C:C,"*"&A123&"*")>0,"yes","no") -> no | Y123: =IF(OR(U123="yes",V123="yes",W123="yes",X123="yes"),"yes","no") -> no
A124: emission_factor_of_anthracite | B124: Emission factor of anthracite | D124: Covenant of Mayors | E124: https://data.jrc.ec.europa.eu/dataset/919df040-0252-4e4e-ad82-c054896e1641 | F124: Lo Vullo, E., Muntean, M., Duerr, M., Kona, A. and Bertoldi, P., Covenant of Mayors, European Commission, 2020, JRC119906. | G124: Creative Commons Attribution 4.0 International (CC BY 4.0) | H124: general stat | I124: emission intensity | J124: coal | N124: MtCO2-eq/TWh | O124: AVG | P124: NUTS0 | Q124: yes | U124: =IF(COUNTIF(soi_input_variables!A:A,A124)>0,"yes","no") -> no | V124: =IF(COUNTIF(midas_input_variables!A:A,A124)>0,"yes","no") -> no | W124: =IF(OR(COUNTIF(eucalc_variables_proxies!C:C,"*"&A124&"*")>0,COUNTIF(eucalc_variables_proxies!F:F,"*"&A124&"*")>0),"yes","no") -> no | X124: =IF(COUNTIF(collected_variables_proxies!C:C,"*"&A124&"*")>0,"yes","no") -> no | Y124: =IF(OR(U124="yes",V124="yes",W124="yes",X124="yes"),"yes","no") -> no
A125: emission_factor_of_diesel | B125: Emission factor of diesel | D125: Covenant of Mayors | E125: https://data.jrc.ec.europa.eu/dataset/919df040-0252-4e4e-ad82-c054896e1641 | F125: Lo Vullo, E., Muntean, M., Duerr, M., Kona, A. and Bertoldi, P., Covenant of Mayors, European Commission, 2020, JRC119906. | G125: Creative Commons Attribution 4.0 International (CC BY 4.0) | H125: general stat | I125: emission intensity | J125: diesel | N125: MtCO2-eq/TWh | O125: AVG | P125: NUTS0 | Q125: yes | U125: =IF(COUNTIF(soi_input_variables!A:A,A125)>0,"yes","no") -> no | V125: =IF(COUNTIF(midas_input_variables!A:A,A125)>0,"yes","no") -> no | W125: =IF(OR(COUNTIF(eucalc_variables_proxies!C:C,"*"&A125&"*")>0,COUNTIF(eucalc_variables_proxies!F:F,"*"&A125&"*")>0),"yes","no") -> no | X125: =IF(COUNTIF(collected_variables_proxies!C:C,"*"&A125&"*")>0,"yes","no") -> no | Y125: =IF(OR(U125="yes",V125="yes",W125="yes",X125="yes"),"yes","no") -> no
...

Sheet collected_variables_proxies
B1: EU
A2: var_name | B2: disaggregation_binary_criteria | C2: disaggregation_proxy | D2: proxy_reasoning | E2: use_random_forest_model? | F2: proxy_confidence_level
A3: population_age_less_than_5 | C3: population | E3: yes | F3: 3
A4: population_age_between_5_and_9 | C4: population | E4: yes | F4: 3
A5: population_age_between_10_and_14 | C5: population | E5: yes | F5: 3
A6: population_age_between_15_and_19 | C6: population | E6: yes | F6: 3
A7: population_age_between_20_and_24 | C7: population | E7: yes | F7: 3
A8: population_age_between_25_and_29 | C8: population | E8: yes | F8: 3
A9: population_age_between_30_and_34 | C9: population | E9: yes | F9: 3
A10: population_age_between_35_and_39 | C10: population | E10: yes | F10: 3
A11: population_age_between_40_and_44 | C11: population | E11: yes | F11: 3
A12: population_age_between_45_and_49 | C12: population | E12: yes | F12: 3
A13: population_age_between_50_and_54 | C13: population | E13: yes | F13: 3
A14: population_age_between_55_and_59 | C14: population | E14: yes | F14: 3
... A368: heat_production_with_electricity | C368: generation_capacity_of_other_plants | E368: no | F368: 4
A369: residential_final_energy_consumption_from_anthracite | C369: population*cproj_annual_mean_temperature_heating_degree_days | F369: 2
A370: residential_final_energy_consumption_from_coking_coal | C370: population*cproj_annual_mean_temperature_heating_degree_days | F370: 2
A371: residential_final_energy_consumption_from_other_bituminous_coal | C371: population*cproj_annual_mean_temperature_heating_degree_days | F371: 2
A372: residential_final_energy_consumption_from_sub_bituminous_coal | C372: population*cproj_annual_mean_temperature_heating_degree_days | F372: 2
A373: residential_final_energy_consumption_from_lignite | C373: population*cproj_annual_mean_temperature_heating_degree_days | F373: 2
A374: residential_final_energy_consumption_from_coke_oven_coke | C374: population*cproj_annual_mean_temperature_heating_degree_days | F374: 2
A375: residential_final_energy_consumption_from_gas_coke | C375: population*cproj_annual_mean_temperature_heating_degree_days | F375: 2
A376: residential_final_energy_consumption_from_patent_fuel | C376: population*cproj_annual_mean_temperature_heating_degree_days | F376: 2
A377: residential_final_energy_consumption_from_brown_coal_briquettes | C377: population*cproj_annual_mean_temperature_heating_degree_days | F377: 2
A378: residential_final_energy_consumption_from_coal_tar | C378: population*cproj_annual_mean_temperature_heating_degree_days | F378: 2
A379: residential_final_energy_consumption_from_coke_oven_gas | C379: population*cproj_annual_mean_temperature_heating_degree_days | F379: 2
A380: residential_final_energy_consumption_from_gas_works_gas | C380: population*cproj_annual_mean_temperature_heating_degree_days | F380: 2
... A433: energy_demand_in_agriculture_and_forestry_and_fisheries_from_geothermal | C433: gross_value_added_nace_sector_a | F433: 2
A434: energy_demand_in_transport_from_blended_biodiesels | C434: gross_value_added_nace_sector_g_i | E434: no | F434: 4
A435: energy_demand_in_transport_from_liquefied_petroleum_gases | C435: gross_value_added_nace_sector_g_i | E435: no | F435: 4
A436: energy_demand_in_transport_from_blended_biogasoline | C436: gross_value_added_nace_sector_g_i | E436: no | F436: 4
A437: energy_demand_in_transport_from_pure_biogasoline | C437: gross_value_added_nace_sector_g_i | E437: no | F437: 4
A438: final_energy_consumption_from_manufacture_of_paper_and_paper_products_using_liquefied_petroleum_gases | C438: number_of_paper_and_printing_industries | F438: 3
A439: final_energy_consumption_from_manufacture_of_paper_and_paper_products_using_fuel_oil | C439: number_of_paper_and_printing_industries | F439: 3
A440: final_energy_consumption_from_manufacture_of_paper_and_paper_products_using_gas_oil_and_diesel_oil | C440: number_of_paper_and_printing_industries | F440: 3
A441: final_energy_consumption_from_manufacture_of_paper_and_paper_products_using_motor_gasoline | C441: number_of_paper_and_printing_industries | F441: 3
A442: final_energy_consumption_from_manufacture_of_paper_and_paper_products_using_anthracite | C442: number_of_paper_and_printing_industries | F442: 3
A443: final_energy_consumption_from_manufacture_of_paper_and_paper_products_using_coking_coal | C443: number_of_paper_and_printing_industries | F443: 3
A444: final_energy_consumption_from_manufacture_of_paper_and_paper_products_using_other_bituminous_coal | C444: number_of_paper_and_printing_industries | F444: 3
A445: final_energy_consumption_from_manufacture_of_paper_and_paper_products_using_sub_bituminous_coal | C445: number_of_paper_and_printing_industries | F445: 3
A446: final_energy_consumption_from_manufacture_of_paper_and_paper_products_using_lignite | C446: number_of_paper_and_printing_industries | F446: 3
A447: final_energy_consumption_from_manufacture_of_paper_and_paper_products_using_solar_thermal | C447: number_of_paper_and_printing_industries | F447: 3
A448: final_energy_consumption_from_manufacture_of_paper_and_paper_products_using_geothermal | C448: number_of_paper_and_printing_industries | F448: 3
A449: final_energy_consumption_from_manufacture_of_chemicals_using_liquefied_petroleum_gases | C449: number_of_chemical_industries | F449: 3
... A569: final_energy_consumption_from_manufacture_of_wood_and_wood_products_using_geothermal | C569: employment_in_manufacturing | F569: 3
A570: residential_energy_demand_space_heating | C570: population+cproj_annual_mean_temperature_heating_degree_days | E570: no | F570: 3
A571: residential_energy_demand_space_cooling | C571: cproj_annual_mean_temperature_cooling_degree_days+income_of_households+population | E571: no | F571: 3
A572: non_residential_energy_demand_space_heating | C572: gross_value_added+cproj_annual_mean_temperature_heating_degree_days | E572: no | F572: 3
A573: non_residential_energy_demand_space_cooling | C573: cproj_annual_mean_temperature_cooling_degree_days+gross_value_added | E573: no | F573: 3
A574: final_energy_consumption_in_iron_and_steel_industries | C574: number_of_iron_and_steel_industries | E574: no | F574: 4
A575: final_energy_consumption_in_chemical_and_petrochemical_industries | C575: number_of_chemical_industries | E575: no | F575: 4
A576: final_energy_consumption_in_non_ferrous_metals_industries | C576: number_of_non_ferrous_metals_industries | E576: no | F576: 4
A577: final_energy_consumption_in_non_metallic_minerals_industries | C577: number_of_non_metallic_minerals_industries | E577: no | F577: 4
A578: final_energy_consumption_in_transport_equipment_industries | C578: employment_in_manufacturing | E578: no | F578: 4
A579: final_energy_consumption_in_machinery_industries | C579: employment_in_manufacturing | E579: no | F579: 4
A580: final_energy_consumption_in_mining_and_quarrying_industries | C580: mineral_extraction_sites_cover | E580: no | F580: 4
A581: final_energy_consumption_in_food_beverages_and_tobacco_industries | C581: employment_in_manufacturing | E581: no | F581: 4
... A629: ghg_emissions_in_agriculture_from_other_agriculture | C629: employment_in_agriculture_forestry_and_fishing | E629: no | F629: 4
A630: ghg_emissions_in_lulucf_from_grassland_other | C630: =collected_variables_EU!A114 -> electricity_production_with_pure_biodiesels | E630: no | F630: 4
A631: ghg_emissions_in_lulucf_from_unconverted_grassland | C631: =collected_variables_EU!A114 -> electricity_production_with_pure_biodiesels | E631: no | F631: 4
A632: ghg_emissions_in_lulucf_from_land_converted_to_grassland | C632: =collected_variables_EU!A114 -> electricity_production_with_pure_biodiesels | E632: no | F632: 4
A633: ghg_emissions_in_nace_sector_a | C633: employment_in_agriculture_forestry_and_fishing_nuts2 | E633: yes | F633: 5
A634: ghg_emissions_in_nace_sector_b | C634: employment_in_nace_sector_b_e_nuts2 | E634: yes | F634: 4
A635: ghg_emissions_in_nace_sector_c | C635: employment_in_manufacturing_nuts2 | E635: yes | F635: 5
A636: ghg_emissions_in_nace_sector_d | C636: employment_in_nace_sector_b_e_nuts2 | E636: yes | F636: 4
A637: ghg_emissions_in_nace_sector_e | C637: employment_in_nace_sector_b_e_nuts2 | E637: yes | F637: 4
A638: ghg_emissions_in_nace_sector_f | C638: employment_in_construction_nuts2 | E638: yes | F638: 5
A639: ghg_emissions_in_nace_sector_g | C639: employment_in_nace_sector_g_i_nuts2 | E639: yes | F639: 4
A640: ghg_emissions_in_nace_sector_h | C640: employment_in_nace_sector_g_i_nuts2 | E640: yes | F640: 4
A641: ghg_emissions_in_nace_sector_i | C641: employment_in_nace_sector_g_i_nuts2 | E641: yes | F641: 4
A642: ghg_emissions_in_nace_sector_j | C642: employment_in_nace_sector_j_nuts2 | E642: yes | F642: 5
A643: ghg_emissions_in_nace_sector_k | C643: employment_in_nace_sector_k_nuts2 | E643: yes | F643: 5
A644: ghg_emissions_in_nace_sector_l | C644: employment_in_nace_sector_l_nuts2 | E644: yes | F644: 5
... A653: ghg_emissions_in_nace_sector_u | C653: employment_in_nace_sector_r_u_nuts2 | E653: yes | F653: 4

Sheet deleted_variables
A1: final_energy_consumption_from_anthracite | B1: final_energy_consumption_from_anthracite | C1: final_energy_consumption_from_anthracite | D1: https://ec.europa.eu/eurostat/databrowser/view/NRG_BAL_C/default/table?lang=en | E1: Eurostat, “Complete energy balances,” Apr. 28, 2023. https://ec.europa.eu/eurostat/databrowser/view/NRG_BAL_C/default/table?lang=en (accessed Aug. 01, 2023). | F1: Creative Commons Attribution 4.0 International (CC BY 4.0) | G1: energy | H1: demand | M1: MWh | N1: SUM | O1: NUTS0 | P1: no | S1: 27 | T1: 0 | U1: =ROUND(T1/S1*100,2) -> 0 | W1: =IF(COUNTIF(soi_input_variables!A:A,A1)>0,"yes","no") -> no | X1: =IF(COUNTIF(midas_input_variables!A:A,A1)>0,"yes","no") -> no | Y1: =IF(OR(COUNTIF(eucalc_variables_proxies!C:C,"*"&A1&"*")>0,COUNTIF(eucalc_variables_proxies!F:F,"*"&A1&"*")>0),"yes","no") -> no | Z1: =IF(COUNTIF(collected_variables_proxies!C:C,"*"&A1&"*")>0,"yes","no") -> no | AA1: =IF(OR(W1="yes",X1="yes",Y1="yes",Z1="yes"),"yes","no") -> no | AB1: 500
A2: final_energy_consumption_from_coking_coal | B2: final_energy_consumption_from_coking_coal | C2: final_energy_consumption_from_coking_coal | D2: https://ec.europa.eu/eurostat/databrowser/view/NRG_BAL_C/default/table?lang=en | E2: Eurostat, “Complete energy balances,” Apr. 28, 2023. https://ec.europa.eu/eurostat/databrowser/view/NRG_BAL_C/default/table?lang=en (accessed Aug. 01, 2023). | F2: Creative Commons Attribution 4.0 International (CC BY 4.0) | G2: energy | H2: demand | M2: MWh | N2: SUM | O2: NUTS0 | P2: no | S2: 27 | T2: 0 | U2: =ROUND(T2/S2*100,2) -> 0 | W2: =IF(COUNTIF(soi_input_variables!A:A,A2)>0,"yes","no") -> no | X2: =IF(COUNTIF(midas_input_variables!A:A,A2)>0,"yes","no") -> no | Y2: =IF(OR(COUNTIF(eucalc_variables_proxies!C:C,"*"&A2&"*")>0,COUNTIF(eucalc_variables_proxies!F:F,"*"&A2&"*")>0),"yes","no") -> no | Z2: =IF(COUNTIF(collected_variables_proxies!C:C,"*"&A2&"*")>0,"yes","no") -> no | AA2: =IF(OR(W2="yes",X2="yes",Y2="yes",Z2="yes"),"yes","no") -> no | AB2: 500
A3: final_energy_consumption_from_lignite | B3: final_energy_consumption_from_lignite | C3: final_energy_consumption_from_lignite | D3: https://ec.europa.eu/eurostat/databrowser/view/NRG_BAL_C/default/table?lang=en | E3: Eurostat, “Complete energy balances,” Apr. 28, 2023. https://ec.europa.eu/eurostat/databrowser/view/NRG_BAL_C/default/table?lang=en (accessed Aug. 01, 2023). | F3: Creative Commons Attribution 4.0 International (CC BY 4.0) | G3: energy | H3: demand | M3: MWh | N3: SUM | O3: NUTS0 | P3: no | S3: 27 | T3: 0 | U3: =ROUND(T3/S3*100,2) -> 0 | W3: =IF(COUNTIF(soi_input_variables!A:A,A3)>0,"yes","no") -> no | X3: =IF(COUNTIF(midas_input_variables!A:A,A3)>0,"yes","no") -> no | Y3: =IF(OR(COUNTIF(eucalc_variables_proxies!C:C,"*"&A3&"*")>0,COUNTIF(eucalc_variables_proxies!F:F,"*"&A3&"*")>0),"yes","no") -> no | Z3: =IF(COUNTIF(collected_variables_proxies!C:C,"*"&A3&"*")>0,"yes","no") -> no | AA3: =IF(OR(W3="yes",X3="yes",Y3="yes",Z3="yes"),"yes","no") -> no | AB3: 500
A4: final_energy_consumption_from_other_bituminous_coal | B4: final_energy_consumption_from_other_bituminous_coal | C4: final_energy_consumption_from_other_bituminous_coal | D4: https://ec.europa.eu/eurostat/databrowser/view/NRG_BAL_C/default/table?lang=en | E4: Eurostat, “Complete energy balances,” Apr. 28, 2023. https://ec.europa.eu/eurostat/databrowser/view/NRG_BAL_C/default/table?lang=en (accessed Aug. 01, 2023). | F4: Creative Commons Attribution 4.0 International (CC BY 4.0) | G4: energy | H4: demand | M4: MWh | N4: SUM | O4: NUTS0 | P4: no | S4: 27 | T4: 0 | U4: =ROUND(T4/S4*100,2) -> 0 | W4: =IF(COUNTIF(soi_input_variables!A:A,A4)>0,"yes","no") -> no | X4: =IF(COUNTIF(midas_input_variables!A:A,A4)>0,"yes","no") -> no | Y4: =IF(OR(COUNTIF(eucalc_variables_proxies!C:C,"*"&A4&"*")>0,COUNTIF(eucalc_variables_proxies!F:F,"*"&A4&"*")>0),"yes","no") -> no | Z4: =IF(COUNTIF(collected_variables_proxies!C:C,"*"&A4&"*")>0,"yes","no") -> no | AA4: =IF(OR(W4="yes",X4="yes",Y4="yes",Z4="yes"),"yes","no") -> no | AB4: 500
A5: final_energy_consumption_from_sub_bituminous_coal | B5: final_energy_consumption_from_sub_bituminous_coal | C5: final_energy_consumption_from_sub_bituminous_coal | D5: https://ec.europa.eu/eurostat/databrowser/view/NRG_BAL_C/default/table?lang=en | E5: Eurostat, “Complete energy balances,” Apr. 28, 2023. https://ec.europa.eu/eurostat/databrowser/view/NRG_BAL_C/default/table?lang=en (accessed Aug. 01, 2023). | F5: Creative Commons Attribution 4.0 International (CC BY 4.0) | G5: energy | H5: demand | M5: MWh | N5: SUM | O5: NUTS0 | P5: no | S5: 27 | T5: 0 | U5: =ROUND(T5/S5*100,2) -> 0 | W5: =IF(COUNTIF(soi_input_variables!A:A,A5)>0,"yes","no") -> no | X5: =IF(COUNTIF(midas_input_variables!A:A,A5)>0,"yes","no") -> no | Y5: =IF(OR(COUNTIF(eucalc_variables_proxies!C:C,"*"&A5&"*")>0,COUNTIF(eucalc_variables_proxies!F:F,"*"&A5&"*")>0),"yes","no") -> no | Z5: =IF(COUNTIF(collected_variables_proxies!C:C,"*"&A5&"*")>0,"yes","no") -> no | AA5: =IF(OR(W5="yes",X5="yes",Y5="yes",Z5="yes"),"yes","no") -> no | AB5: 500
A6: final_energy_consumption_from_coke_oven_coke | B6: final_energy_consumption_from_coke_oven_coke | C6: final_energy_consumption_from_coke_oven_coke | D6: https://ec.europa.eu/eurostat/databrowser/view/NRG_BAL_C/default/table?lang=en | E6: Eurostat, “Complete energy balances,” Apr. 28, 2023. https://ec.europa.eu/eurostat/databrowser/view/NRG_BAL_C/default/table?lang=en (accessed Aug. 01, 2023). | F6: Creative Commons Attribution 4.0 International (CC BY 4.0) | G6: energy | H6: demand | M6: MWh | N6: SUM | O6: NUTS0 | P6: no | S6: 27 | T6: 0 | U6: =ROUND(T6/S6*100,2) -> 0 | W6: =IF(COUNTIF(soi_input_variables!A:A,A6)>0,"yes","no") -> no | X6: =IF(COUNTIF(midas_input_variables!A:A,A6)>0,"yes","no") -> no | Y6: =IF(OR(COUNTIF(eucalc_variables_proxies!C:C,"*"&A6&"*")>0,COUNTIF(eucalc_variables_proxies!F:F,"*"&A6&"*")>0),"yes","no") -> no | Z6: =IF(COUNTIF(collected_variables_proxies!C:C,"*"&A6&"*")>0,"yes","no") -> no | AA6: =IF(OR(W6="yes",X6="yes",Y6="yes",Z6="yes"),"yes","no") -> no | AB6: 500
A7: final_energy_consumption_from_gas_coke | B7: final_energy_consumption_from_gas_coke | C7: final_energy_consumption_from_gas_coke | D7: https://ec.europa.eu/eurostat/databrowser/view/NRG_BAL_C/default/table?lang=en | E7: Eurostat, “Complete energy balances,” Apr. 28, 2023. https://ec.europa.eu/eurostat/databrowser/view/NRG_BAL_C/default/table?lang=en (accessed Aug. 01, 2023). | F7: Creative Commons Attribution 4.0 International (CC BY 4.0) | G7: energy | H7: demand | M7: MWh | N7: SUM | O7: NUTS0 | P7: no | S7: 27 | T7: 0 | U7: =ROUND(T7/S7*100,2) -> 0 | W7: =IF(COUNTIF(soi_input_variables!A:A,A7)>0,"yes","no") -> no | X7: =IF(COUNTIF(midas_input_variables!A:A,A7)>0,"yes","no") -> no | Y7: =IF(OR(COUNTIF(eucalc_variables_proxies!C:C,"*"&A7&"*")>0,COUNTIF(eucalc_variables_proxies!F:F,"*"&A7&"*")>0),"yes","no") -> no | Z7: =IF(COUNTIF(collected_variables_proxies!C:C,"*"&A7&"*")>0,"yes","no") -> no | AA7: =IF(OR(W7="yes",X7="yes",Y7="yes",Z7="yes"),"yes","no") -> no | AB7: 500
A8: final_energy_consumption_from_patent_fuel | B8: final_energy_consumption_from_patent_fuel | C8: final_energy_consumption_from_patent_fuel | D8: https://ec.europa.eu/eurostat/databrowser/view/NRG_BAL_C/default/table?lang=en | E8: Eurostat, “Complete energy balances,” Apr. 28, 2023. https://ec.europa.eu/eurostat/databrowser/view/NRG_BAL_C/default/table?lang=en (accessed Aug. 01, 2023). | F8: Creative Commons Attribution 4.0 International (CC BY 4.0) | G8: energy | H8: demand | M8: MWh | N8: SUM | O8: NUTS0 | P8: no | S8: 27 | T8: 0 | U8: =ROUND(T8/S8*100,2) -> 0 | W8: =IF(COUNTIF(soi_input_variables!A:A,A8)>0,"yes","no") -> no | X8: =IF(COUNTIF(midas_input_variables!A:A,A8)>0,"yes","no") -> no | Y8: =IF(OR(COUNTIF(eucalc_variables_proxies!C:C,"*"&A8&"*")>0,COUNTIF(eucalc_variables_proxies!F:F,"*"&A8&"*")>0),"yes","no") -> no | Z8: =IF(COUNTIF(collected_variables_proxies!C:C,"*"&A8&"*")>0,"yes","no") -> no | AA8: =IF(OR(W8="yes",X8="yes",Y8="yes",Z8="yes"),"yes","no") -> no | AB8: 500
A9: final_energy_consumption_from_brown_coal_briquettes | B9: final_energy_consumption_from_brown_coal_briquettes | C9: final_energy_consumption_from_brown_coal_briquettes | D9: https://ec.europa.eu/eurostat/databrowser/view/NRG_BAL_C/default/table?lang=en | E9: Eurostat, “Complete energy balances,” Apr. 28, 2023. https://ec.europa.eu/eurostat/databrowser/view/NRG_BAL_C/default/table?lang=en (accessed Aug. 01, 2023). | F9: Creative Commons Attribution 4.0 International (CC BY 4.0) | G9: energy | H9: demand | M9: MWh | N9: SUM | O9: NUTS0 | P9: no | S9: 27 | T9: 0 | U9: =ROUND(T9/S9*100,2) -> 0 | W9: =IF(COUNTIF(soi_input_variables!A:A,A9)>0,"yes","no") -> no | X9: =IF(COUNTIF(midas_input_variables!A:A,A9)>0,"yes","no") -> no | Y9: =IF(OR(COUNTIF(eucalc_variables_proxies!C:C,"*"&A9&"*")>0,COUNTIF(eucalc_variables_proxies!F:F,"*"&A9&"*")>0),"yes","no") -> no | Z9: =IF(COUNTIF(collected_variables_proxies!C:C,"*"&A9&"*")>0,"yes","no") -> no | AA9: =IF(OR(W9="yes",X9="yes",Y9="yes",Z9="yes"),"yes","no") -> no | AB9: 500
A10: final_energy_consumption_from_coal_tar | B10: final_energy_consumption_from_coal_tar | C10: final_energy_consumption_from_coal_tar | D10: https://ec.europa.eu/eurostat/databrowser/view/NRG_BAL_C/default/table?lang=en | E10: Eurostat, “Complete energy balances,” Apr. 28, 2023. https://ec.europa.eu/eurostat/databrowser/view/NRG_BAL_C/default/table?lang=en (accessed Aug. 01, 2023). | F10: Creative Commons Attribution 4.0 International (CC BY 4.0) | G10: energy | H10: demand | M10: MWh | N10: SUM | O10: NUTS0 | P10: no | S10: 27 | T10: 0 | U10: =ROUND(T10/S10*100,2) -> 0 | W10: =IF(COUNTIF(soi_input_variables!A:A,A10)>0,"yes","no") -> no | X10: =IF(COUNTIF(midas_input_variables!A:A,A10)>0,"yes","no") -> no | Y10: =IF(OR(COUNTIF(eucalc_variables_proxies!C:C,"*"&A10&"*")>0,COUNTIF(eucalc_variables_proxies!F:F,"*"&A10&"*")>0),"yes","no") -> no | Z10: =IF(COUNTIF(collected_variables_proxies!C:C,"*"&A10&"*")>0,"yes","no") -> no | AA10: =IF(OR(W10="yes",X10="yes",Y10="yes",Z10="yes"),"yes","no") -> no | AB10: 500
A11: final_energy_consumption_from_coke_oven_gas | B11: final_energy_consumption_from_coke_oven_gas | C11: final_energy_consumption_from_coke_oven_gas | D11: https://ec.europa.eu/eurostat/databrowser/view/NRG_BAL_C/default/table?lang=en | E11: Eurostat, “Complete energy balances,” Apr. 28, 2023. https://ec.europa.eu/eurostat/databrowser/view/NRG_BAL_C/default/table?lang=en (accessed Aug. 01, 2023). | F11: Creative Commons Attribution 4.0 International (CC BY 4.0) | G11: energy | H11: demand | M11: MWh | N11: SUM | O11: NUTS0 | P11: no | S11: 27 | T11: 0 | U11: =ROUND(T11/S11*100,2) -> 0 | W11: =IF(COUNTIF(soi_input_variables!A:A,A11)>0,"yes","no") -> no | X11: =IF(COUNTIF(midas_input_variables!A:A,A11)>0,"yes","no") -> no | Y11: =IF(OR(COUNTIF(eucalc_variables_proxies!C:C,"*"&A11&"*")>0,COUNTIF(eucalc_variables_proxies!F:F,"*"&A11&"*")>0),"yes","no") -> no | Z11: =IF(COUNTIF(collected_variables_proxies!C:C,"*"&A11&"*")>0,"yes","no") -> no | AA11: =IF(OR(W11="yes",X11="yes",Y11="yes",Z11="yes"),"yes","no") -> no | AB11: 500
A12: final_energy_consumption_from_gas_works_gas | B12: final_energy_consumption_from_gas_works_gas | C12: final_energy_consumption_from_gas_works_gas | D12: https://ec.europa.eu/eurostat/databrowser/view/NRG_BAL_C/default/table?lang=en | E12: Eurostat, “Complete energy balances,” Apr. 28, 2023. https://ec.europa.eu/eurostat/databrowser/view/NRG_BAL_C/default/table?lang=en (accessed Aug. 01, 2023). | F12: Creative Commons Attribution 4.0 International (CC BY 4.0) | G12: energy | H12: demand | M12: MWh | N12: SUM | O12: NUTS0 | P12: no | S12: 27 | T12: 0 | U12: =ROUND(T12/S12*100,2) -> 0 | W12: =IF(COUNTIF(soi_input_variables!A:A,A12)>0,"yes","no") -> no | X12: =IF(COUNTIF(midas_input_variables!A:A,A12)>0,"yes","no") -> no | Y12: =IF(OR(COUNTIF(eucalc_variables_proxies!C:C,"*"&A12&"*")>0,COUNTIF(eucalc_variables_proxies!F:F,"*"&A12&"*")>0),"yes","no") -> no | Z12: =IF(COUNTIF(collected_variables_proxies!C:C,"*"&A12&"*")>0,"yes","no") -> no | AA12: =IF(OR(W12="yes",X12="yes",Y12="yes",Z12="yes"),"yes","no") -> no | AB12: 500
... A339: ghg_emissions_in_waste_management | B339: ghg_emissions_in_waste_management | C339: ghg_emissions_in_waste_management | D339: https://ec.europa.eu/eurostat/databrowser/view/env_air_gge__custom_12410313/default/table?lang=en | E339: Eurostat. “Greenhouse Gas Emissions by Source Sector.” Accessed July 31, 2024. https://ec.europa.eu/eurostat/databrowser/view/env_air_gge__custom_12410313/default/table?lang=en. | F339: Creative Commons Attribution 4.0 International (CC BY 4.0) | G339: agriculture and forestry | H339: emissions | M339: Mt | N339: SUM | O339: NUTS0 | P339: no | S339: 27 | T339: 0 | U339: =ROUND(T339/S339*100,2) -> 0 | W339: =IF(COUNTIF(soi_input_variables!A:A,A339)>0,"yes","no") -> no | X339: =IF(COUNTIF(midas_input_variables!A:A,A339)>0,"yes","no") -> no | Y339: =IF(OR(COUNTIF(eucalc_variables_proxies!C:C,"*"&A339&"*")>0,COUNTIF(eucalc_variables_proxies!F:F,"*"&A339&"*")>0),"yes","no") -> no | Z339: =IF(COUNTIF(collected_variables_proxies!C:C,"*"&A339&"*")>0,"yes","no") -> no | AA339: =IF(OR(W339="yes",X339="yes",Y339="yes",Z339="yes"),"yes","no") -> no | AB339: 0.02
A340: es_number_of_cattle | C340: INE - The National Statistics Institute of Spain | D340: https://www.ine.es/jaxi/Tabla.htm?tpx=51184&L=0 | M340: number | N340: sum | O340: LAU | P340: ES | X340: 8043 | Y340: 1945 | Z340: =ROUND(Y340/X340*100,2) -> 24.18
A341: es_number_of_sheeps_and_goats | C341: INE - The National Statistics Institute of Spain | D341: https://www.ine.es/jaxi/Tabla.htm?tpx=51184&L=0 | M341: number | N341: sum | O341: LAU | P341: ES | X341: 8043 | Y341: 2333 | Z341: =ROUND(Y341/X341*100,2) -> 29.01
A342: es_number_of_pigs | C342: INE - The National Statistics Institute of Spain | D342: https://www.ine.es/jaxi/Tabla.htm?tpx=51184&L=0 | M342: number | N342: sum | O342: LAU | P342: ES | X342: 8043 | Y342: 2210 | Z342: =ROUND(Y342/X342*100,2) -> 27.48
A343: es_number_of_poultry | C343: INE - The National Statistics Institute of Spain | D343: https://www.ine.es/jaxi/Tabla.htm?tpx=51184&L=0 | M343: number | N343: sum | O343: LAU | P343: ES | X343: 8043 | Y343: 2460 | Z343: =ROUND(Y343/X343*100,2) -> 30.59
A344: deaths_due_to_indoor_and_outdoor_air_pollution | C344: Our World in Data | D344: https://ourworldindata.org/water-access | E344: Hannah Ritchie and Max Roser (2021) - \"Clean Water and Sanitation\". Published online at OurWorldInData.org. Retrieved from: \"https://ourworldindata.org/clean-water-sanitation\" [Online Resource] | F344: Creative Commons Attribution 4.0 International (CC BY 4.0) | G344: health | H344: mortality | M344: number | N344: SUM | O344: NUTS0 | P344: yes | S344: 27 | T344: 0 | U344: =ROUND(T344/S344*100,2) -> 0 | W344: =IF(COUNTIF(soi_input_variables!A:A,A344)>0,"yes","no") -> no | X344: =IF(COUNTIF(midas_input_variables!A:A,A344)>0,"yes","no") -> no | Y344: =IF(OR(COUNTIF(eucalc_variables_proxies!C:C,"*"&A344&"*")>0,COUNTIF(eucalc_variables_proxies!F:F,"*"&A344&"*")>0),"yes","no") -> no | Z344: =IF(COUNTIF(collected_variables_proxies!C:C,"*"&A344&"*")>0,"yes","no") -> no | AA344: =IF(OR(W344="yes",X344="yes",Y344="yes",Z344="yes"),"yes","no") -> no | AB344: 10
A345: deaths_due_to_infectious_diseases | C345: Eurostat | D345: https://ec.europa.eu/eurostat/databrowser/view/HLTH_CD_IDO/default/table?lang=en | E345: Eurostat, “Deaths related to infectious diseases,” 2023. https://ec.europa.eu/eurostat/databrowser/view/HLTH_CD_IDO/bookmark/table?lang=en&bookmarkId=b1ce4851-f494-430f-be4b-e4896733c46b (accessed Apr. 05, 2023). | F345: Creative Commons Attribution 4.0 International (CC BY 4.0) | G345: health | H345: mortality | M345: number | N345: SUM | O345: NUTS0 | P345: yes | S345: 27 | T345: 0 | U345: =ROUND(T345/S345*100,2) -> 0 | W345: =IF(COUNTIF(soi_input_variables!A:A,A345)>0,"yes","no") -> no | X345: =IF(COUNTIF(midas_input_variables!A:A,A345)>0,"yes","no") -> no | Y345: =IF(OR(COUNTIF(eucalc_variables_proxies!C:C,"*"&A345&"*")>0,COUNTIF(eucalc_variables_proxies!F:F,"*"&A345&"*")>0),"yes","no") -> no | Z345: =IF(COUNTIF(collected_variables_proxies!C:C,"*"&A345&"*")>0,"yes","no") -> no | AA345: =IF(OR(W345="yes",X345="yes",Y345="yes",Z345="yes"),"yes","no") -> no | AB345: 10
A346: statistical_area | B346: Statistical area | D346: Eurostat | E346: https://ec.europa.eu/eurostat/databrowser/view/reg_area3/default/table?lang=en | F346: Eurostat, ‘Area by NUTS 3 region’, 2022. https://ec.europa.eu/eurostat/databrowser/view/reg_area3/default/table?lang=en (accessed Nov. 23, 2022). | G346: Creative Commons Attribution 4.0 International (CC BY 4.0) | H346: general stat | N346: square kilometer | O346: SUM | P346: NUTS3 | Q346: yes | T346: 1155 | U346: 0 | V346: =ROUND(U346/T346*100,2) -> 0 | X346: =IF(COUNTIF(soi_input_variables!A:A,A346)>0,"yes","no") -> yes | Y346: =IF(COUNTIF(midas_input_variables!A:A,A346)>0,"yes","no") -> no | Z346: =IF(OR(COUNTIF(eucalc_variables_proxies!C:C,"*"&A346&"*")>0,COUNTIF(eucalc_variables_proxies!F:F,"*"&A346&"*")>0),"yes","no") -> no | AA346: =IF(COUNTIF(collected_variables_proxies!C:C,"*"&A346&"*")>0,"yes","no") -> no | AB346: =IF(OR(X346="yes",Y346="yes",Z346="yes",AA346="yes"),"yes","no") -> yes

Sheet collected_variables_countries
A1: var_name | B1: var_description | C1: var_source_name | D1: var_source_link | E1: var_source_citation | F1: var_source_license | G1: tag_sector | H1: tag_type | I1: tag_commodity | J1: tag_resource | K1: tag_link | L1: tag_other | M1: var_unit | N1: var_aggregation_method | O1: spatial_level | P1: geo_coverage | Q1: to_stage? | R1: staging_calculation | S1: disaggregation_binary_criteria | T1: disaggregation_proxy | U1: proxy_reasoning | V1: use_random_forest_model? | W1: disaggregation_quality_rating | X1: total_number_of_regions | Y1: number_of_regions_missing_data | Z1: percentage_of_missing_data | AA1: Shruthi's notes
A2: number_of_buildings_germany | C2: BUILDA | D2: https://jugit.fz-juelich.de/iek-3/groups/urbanmodels/personal/dabrock/building-database-builda/builda | E2: BUILDA in-progress, in-house project | G2: buildings | H2: stock | L2: total | M2: number | N2: sum | O2: LAU | P2: DE | Q2: yes | V2: no | W2: 3 | X2: 11087 | Y2: 0 | Z2: =ROUND(Y2/X2*100,2) -> 0
A3: number_of_residential_buildings_germany | C3: BUILDA | D3: https://jugit.fz-juelich.de/iek-3/groups/urbanmodels/personal/dabrock/building-database-builda/builda | E3: BUILDA in-progress, in-house project | G3: buildings | H3: stock | L3: total | M3: number | N3: sum | O3: LAU | P3: DE | Q3: yes | V3: no | W3: 3 | X3: 11087 | Y3: 0 | Z3: =ROUND(Y3/X3*100,2) -> 0
A4: number_of_non_residential_buildings_germany | C4: BUILDA | D4: https://jugit.fz-juelich.de/iek-3/groups/urbanmodels/personal/dabrock/building-database-builda/builda | E4: BUILDA in-progress, in-house project | G4: buildings | H4: stock | L4: total | M4: number | N4: sum | O4: LAU | P4: DE | Q4: yes | V4: no | W4: 3 | X4: 11087 | Y4: 0 | Z4: =ROUND(Y4/X4*100,2) -> 0
A5: residential_footprint_area_germany | C5: BUILDA | D5: https://jugit.fz-juelich.de/iek-3/groups/urbanmodels/personal/dabrock/building-database-builda/builda | E5: BUILDA in-progress, in-house project | G5: buildings | J5: footprint area | L5: total | M5: square kilometer | N5: sum | O5: LAU | P5: DE | Q5: yes | V5: no | W5: 3 | X5: 11087 | Y5: 0 | Z5: =ROUND(Y5/X5*100,2) -> 0
A6: non_residential_footprint_area_germany | C6: BUILDA | D6: https://jugit.fz-juelich.de/iek-3/groups/urbanmodels/personal/dabrock/building-database-builda/builda | E6: BUILDA in-progress, in-house project | G6: buildings | J6: footprint area | L6: total | M6: square kilometer | N6: sum | O6: LAU | P6: DE | Q6: yes | V6: no | W6: 3 | X6: 11087 | Y6: 0 | Z6: =ROUND(Y6/X6*100,2) -> 0
A7: residential_heat_demand_germany | C7: BUILDA | D7: https://jugit.fz-juelich.de/iek-3/groups/urbanmodels/personal/dabrock/building-database-builda/builda | E7: BUILDA in-progress, in-house project | G7: buildings, energy | H7: demand | I7: heat | L7: total | M7: MWh | N7: sum | O7: LAU | P7: DE | Q7: yes | V7: no | W7: 3 | X7: 11087 | Y7: 0 | Z7: =ROUND(Y7/X7*100,2) -> 0
A8: residential_energy_demand_germany | C8: BUILDA | D8: https://jugit.fz-juelich.de/iek-3/groups/urbanmodels/personal/dabrock/building-database-builda/builda | E8: BUILDA in-progress, in-house project | G8: buildings, energy | H8: demand | I8: energy | L8: total, final | M8: MWh | N8: sum | O8: LAU | P8: DE | Q8: yes | V8: no | W8: 3 | X8: 11087 | Y8: 0 | Z8: =ROUND(Y8/X8*100,2) -> 0
A9: residential_energy_demand_from_solids_germany | C9: BUILDA | D9: https://jugit.fz-juelich.de/iek-3/groups/urbanmodels/personal/dabrock/building-database-builda/builda | E9: BUILDA in-progress, in-house project | G9: buildings, energy | H9: demand | I9: energy | L9: final | M9: MWh | N9: sum | O9: LAU | P9: DE | Q9: yes | V9: no | W9: 3 | X9: 11087 | Y9: 0 | Z9: =ROUND(Y9/X9*100,2) -> 0
A10: residential_energy_demand_from_liquified_petroleum_gas_germany | C10: BUILDA | D10: https://jugit.fz-juelich.de/iek-3/groups/urbanmodels/personal/dabrock/building-database-builda/builda | E10: BUILDA in-progress, in-house project | G10: buildings, energy | H10: demand | I10: energy, lpg | L10: final | M10: MWh | N10: sum | O10: LAU | P10: DE | Q10: yes | V10: no | W10: 3 | X10: 11087 | Y10: 0 | Z10: =ROUND(Y10/X10*100,2) -> 0
A11: residential_energy_demand_from_gas_or_diesel_oil_including_biofuels_germany | C11: BUILDA | D11: https://jugit.fz-juelich.de/iek-3/groups/urbanmodels/personal/dabrock/building-database-builda/builda | E11: BUILDA in-progress, in-house project | G11: buildings, energy | H11: demand | I11: energy, biofuel, gasoline, diesel | L11: final | M11: MWh | N11: sum | O11: LAU | P11: DE | Q11: yes | V11: no | W11: 3 | X11: 11087 | Y11: 0 | Z11: =ROUND(Y11/X11*100,2) -> 0
A12: residential_energy_demand_from_gases_including_biogas_germany | C12: BUILDA | D12: https://jugit.fz-juelich.de/iek-3/groups/urbanmodels/personal/dabrock/building-database-builda/builda | E12: BUILDA in-progress, in-house project | G12: buildings, energy | H12: demand | I12: energy, biogas, natural gas | L12: final | M12: MWh | N12: sum | O12: LAU | P12: DE | Q12: yes | V12: no | W12: 3 | X12: 11087 | Y12: 0 | Z12: =ROUND(Y12/X12*100,2) -> 0
A13: residential_energy_demand_from_biomass_and_wastes_germany | C13: BUILDA | D13: https://jugit.fz-juelich.de/iek-3/groups/urbanmodels/personal/dabrock/building-database-builda/builda | E13: BUILDA in-progress, in-house project | G13: buildings, energy, waste | H13: demand | I13: energy, biomass | L13: final | M13: MWh | N13: sum | O13: LAU | P13: DE | Q13: yes | V13: no | W13: 3 | X13: 11087 | Y13: 0 | Z13: =ROUND(Y13/X13*100,2) -> 0
A14: residential_energy_demand_from_geothermal_energy_germany | C14: BUILDA | D14: https://jugit.fz-juelich.de/iek-3/groups/urbanmodels/personal/dabrock/building-database-builda/builda | E14: BUILDA in-progress, in-house project | G14: buildings, energy | H14: demand | I14: energy | L14: final | M14: MWh | N14: sum | O14: LAU | P14: DE | Q14: yes | V14: no | W14: 3 | X14: 11087 | Y14: 0 | Z14: =ROUND(Y14/X14*100,2) -> 0
A15: residential_energy_demand_from_derived_heat_germany | C15: BUILDA | D15: https://jugit.fz-juelich.de/iek-3/groups/urbanmodels/personal/dabrock/building-database-builda/builda | E15: BUILDA in-progress, in-house project | G15: buildings, energy | H15: demand | I15: energy, heat | L15: final | M15: MWh | N15: sum | O15: LAU | P15: DE | Q15: yes | V15: no | W15: 3 | X15: 11087 | Y15: 0 | Z15: =ROUND(Y15/X15*100,2) -> 0
A16: residential_energy_demand_from_electricity_germany | C16: BUILDA | D16: https://jugit.fz-juelich.de/iek-3/groups/urbanmodels/personal/dabrock/building-database-builda/builda | E16: BUILDA in-progress, in-house project | G16: buildings, energy | H16: demand | I16: energy, electricity | L16: final | M16: MWh | N16: sum | O16: LAU | P16: DE | Q16: yes | V16: no | W16: 3 | X16: 11087 | Y16: 0 | Z16: =ROUND(Y16/X16*100,2) -> 0
A17: residential_rooftop_pv_potential_capacity_germany | C17: BUILDA | D17: https://jugit.fz-juelich.de/iek-3/groups/urbanmodels/personal/dabrock/building-database-builda/builda | E17: BUILDA in-progress, in-house project | G17: buildings, energy | H17: potential, capacity | M17: kWh | N17: sum | O17: LAU | P17: DE | Q17: yes | V17: no | W17: 3 | X17: 11087 | Y17: 0 | Z17: =ROUND(Y17/X17*100,2) -> 0
A18: non_residential_rooftop_pv_potential_capacity_germany | C18: BUILDA | D18: https://jugit.fz-juelich.de/iek-3/groups/urbanmodels/personal/dabrock/building-database-builda/builda | E18: BUILDA in-progress, in-house project | G18: buildings, energy | H18: potential, capacity | M18: kWh | N18: sum | O18: LAU | P18: DE | Q18: yes | V18: no | W18: 3 | X18: 11087 | Y18: 0 | Z18: =ROUND(Y18/X18*100,2) -> 0
A19: utility_pv_potential_area_germany | C19: Tool for Renewable Energy Potentials - Database | D19: https://zenodo.org/record/6414018#.Y35BznbMIuU | E19: S. Risch et al., ‘Tool for Renewable Energy Potentials - Database’. Zenodo, Apr. 05, 2022. doi: 10.5281/zenodo.6414018. | F19: Creative Commons Attribution 4.0 International (CC BY 4.0) | G19: energy | H19: potential | J19: land area | M19: square kilometer | N19: sum | O19: LAU | P19: DE | Q19: yes | V19: no | W19: 3 | X19: 11087 | Y19: 0 | Z19: =ROUND(Y19/X19*100,2) -> 0
A20: utility_pv_potential_capacity_germany | C20: Tool for Renewable Energy Potentials - Database | D20: https://zenodo.org/record/6414018#.Y35BznbMIuU | E20: S. Risch et al., ‘Tool for Renewable Energy Potentials - Database’. Zenodo, Apr. 05, 2022. doi: 10.5281/zenodo.6414018. | F20: Creative Commons Attribution 4.0 International (CC BY 4.0) | G20: energy | H20: potential, capacity | M20: kW | N20: sum | O20: LAU | P20: DE | Q20: yes | V20: no | W20: 3 | X20: 11087 | Y20: 0 | Z20: =ROUND(Y20/X20*100,2) -> 0
A21: onshore_wind_potential_capacity_germany | C21: Tool for Renewable Energy Potentials - Database | D21: https://zenodo.org/record/6414018#.Y35BznbMIuU | E21: S. Risch et al., ‘Tool for Renewable Energy Potentials - Database’. Zenodo, Apr. 05, 2022. doi: 10.5281/zenodo.6414018. | F21: Creative Commons Attribution 4.0 International (CC BY 4.0) | G21: energy | H21: potential, capacity | M21: kW | N21: sum | O21: LAU | P21: DE | Q21: yes | V21: no | W21: 3 | X21: 11087 | Y21: 0 | Z21: =ROUND(Y21/X21*100,2) -> 0
A22: de_number_of_passenger_cars | C22: Destatis | D22: https://www-genesis.destatis.de/genesis//online?operation=table&code=46251-0020&bypass=true&levelindex=1&levelid=1722261103925#abreadcrumb | E22: Statistisches Bundesamt Deutschland - GENESIS-Online. “Kraftfahrzeugbestand: Kreise, Stichtag, Kraftfahrzeugarten.” Text, July 29, 2024. https://www-genesis.destatis.de/genesis//online?operation=table&code=46251-0020&bypass=true&levelindex=1&levelid=1722261103925#abreadcrumb. | F22: Creative Commons Attribution 4.0 International (CC BY 4.0) | G22: transport | M22: number | N22: sum | O22: NUTS3 | P22: DE | Q22: yes | X22: 401 | Y22: 2 | Z22: =ROUND(Y22/X22*100,2) -> 0.5
A23: de_number_of_buses | C23: Destatis | D23: https://www-genesis.destatis.de/genesis//online?operation=table&code=46251-0020&bypass=true&levelindex=1&levelid=1722261103925#abreadcrumb | E23: Statistisches Bundesamt Deutschland - GENESIS-Online. “Kraftfahrzeugbestand: Kreise, Stichtag, Kraftfahrzeugarten.” Text, July 29, 2024. https://www-genesis.destatis.de/genesis//online?operation=table&code=46251-0020&bypass=true&levelindex=1&levelid=1722261103925#abreadcrumb. | F23: Creative Commons Attribution 4.0 International (CC BY 4.0) | G23: transport | M23: number | N23: sum | O23: NUTS3 | P23: DE | Q23: yes | X23: 401 | Y23: 3 | Z23: =ROUND(Y23/X23*100,2) -> 0.75
A24: de_number_of_trucks_or_lorries | C24: Destatis | D24: https://www-genesis.destatis.de/genesis//online?operation=table&code=46251-0020&bypass=true&levelindex=1&levelid=1722261103925#abreadcrumb | E24: Statistisches Bundesamt Deutschland - GENESIS-Online. “Kraftfahrzeugbestand: Kreise, Stichtag, Kraftfahrzeugarten.” Text, July 29, 2024. https://www-genesis.destatis.de/genesis//online?operation=table&code=46251-0020&bypass=true&levelindex=1&levelid=1722261103925#abreadcrumb. | F24: Creative Commons Attribution 4.0 International (CC BY 4.0) | G24: transport | M24: number | N24: sum | O24: NUTS3 | P24: DE | Q24: yes | X24: 401 | Y24: 2 | Z24: =ROUND(Y24/X24*100,2) -> 0.5
A25: de_number_of_agricultural_tractors | C25: Destatis | D25: https://www-genesis.destatis.de/genesis//online?operation=table&code=46251-0020&bypass=true&levelindex=1&levelid=1722261103925#abreadcrumb | E25: Statistisches Bundesamt Deutschland - GENESIS-Online. “Kraftfahrzeugbestand: Kreise, Stichtag, Kraftfahrzeugarten.” Text, July 29, 2024. https://www-genesis.destatis.de/genesis//online?operation=table&code=46251-0020&bypass=true&levelindex=1&levelid=1722261103925#abreadcrumb. | F25: Creative Commons Attribution 4.0 International (CC BY 4.0) | G25: transport | M25: number | N25: sum | O25: NUTS3 | P25: DE | Q25: yes | X25: 401 | Y25: 2 | Z25: =ROUND(Y25/X25*100,2) -> 0.5
A26: de_number_of_passenger_cars_emission_group_euro_1 | C26: Destatis | D26: https://www-genesis.destatis.de/genesis/online#astructure | E26: Statistisches Bundesamt Deutschland - GENESIS-Online. “Personenkraftwagen: Kreise, Stichtag, Kraftstoffarten, Emissionsgruppen.” Text, July 29, 2024. https://www-genesis.destatis.de/genesis/online#astructure. | F26: Creative Commons Attribution 4.0 International (CC BY 4.0) | G26: transport | M26: number | N26: sum | O26: NUTS3 | P26: DE | Q26: yes | X26: 401 | Y26: 2 | Z26: =ROUND(Y26/X26*100,2) -> 0.5
A27: de_number_of_passenger_cars_emission_group_euro_2 | C27: Destatis | D27: https://www-genesis.destatis.de/genesis/online#astructure | E27: Statistisches Bundesamt Deutschland - GENESIS-Online. “Personenkraftwagen: Kreise, Stichtag, Kraftstoffarten, Emissionsgruppen.” Text, July 29, 2024. https://www-genesis.destatis.de/genesis/online#astructure. | F27: Creative Commons Attribution 4.0 International (CC BY 4.0) | G27: transport | M27: number | N27: sum | O27: NUTS3 | P27: DE | Q27: yes | X27: 401 | Y27: 2 | Z27: =ROUND(Y27/X27*100,2) -> 0.5
A28: de_number_of_passenger_cars_emission_group_euro_3 | C28: Destatis | D28: https://www-genesis.destatis.de/genesis/online#astructure | E28: Statistisches Bundesamt Deutschland - GENESIS-Online. “Personenkraftwagen: Kreise, Stichtag, Kraftstoffarten, Emissionsgruppen.” Text, July 29, 2024. https://www-genesis.destatis.de/genesis/online#astructure. | F28: Creative Commons Attribution 4.0 International (CC BY 4.0) | G28: transport | M28: number | N28: sum | O28: NUTS3 | P28: DE | Q28: yes | X28: 401 | Y28: 2 | Z28: =ROUND(Y28/X28*100,2) -> 0.5
A29: de_number_of_passenger_cars_emission_group_euro_4 | C29: Destatis | D29: https://www-genesis.destatis.de/genesis/online#astructure | E29: Statistisches Bundesamt Deutschland - GENESIS-Online. “Personenkraftwagen: Kreise, Stichtag, Kraftstoffarten, Emissionsgruppen.” Text, July 29, 2024. https://www-genesis.destatis.de/genesis/online#astructure. | F29: Creative Commons Attribution 4.0 International (CC BY 4.0) | G29: transport | M29: number | N29: sum | O29: NUTS3 | P29: DE | Q29: yes | X29: 401 | Y29: 2 | Z29: =ROUND(Y29/X29*100,2) -> 0.5
A30: de_number_of_passenger_cars_emission_group_euro_5 | C30: Destatis | D30: https://www-genesis.destatis.de/genesis/online#astructure | E30: Statistisches Bundesamt Deutschland - GENESIS-Online. “Personenkraftwagen: Kreise, Stichtag, Kraftstoffarten, Emissionsgruppen.” Text, July 29, 2024. https://www-genesis.destatis.de/genesis/online#astructure. | F30: Creative Commons Attribution 4.0 International (CC BY 4.0) | G30: transport | M30: number | N30: sum | O30: NUTS3 | P30: DE | Q30: yes | X30: 401 | Y30: 2 | Z30: =ROUND(Y30/X30*100,2) -> 0.5
A31: de_number_of_passenger_cars_emission_group_euro_6r | C31: Destatis | D31: https://www-genesis.destatis.de/genesis/online#astructure | E31: Statistisches Bundesamt Deutschland - GENESIS-Online. “Personenkraftwagen: Kreise, Stichtag, Kraftstoffarten, Emissionsgruppen.” Text, July 29, 2024. https://www-genesis.destatis.de/genesis/online#astructure. | F31: Creative Commons Attribution 4.0 International (CC BY 4.0) | G31: transport | M31: number | N31: sum | O31: NUTS3 | P31: DE | Q31: yes | X31: 401 | Y31: 2 | Z31: =ROUND(Y31/X31*100,2) -> 0.5
A32: de_number_of_passenger_cars_emission_group_euro_6dt | C32: Destatis | D32: https://www-genesis.destatis.de/genesis/online#astructure | E32: Statistisches Bundesamt Deutschland - GENESIS-Online. “Personenkraftwagen: Kreise, Stichtag, Kraftstoffarten, Emissionsgruppen.” Text, July 29, 2024. https://www-genesis.destatis.de/genesis/online#astructure. | F32: Creative Commons Attribution 4.0 International (CC BY 4.0) | G32: transport | M32: number | N32: sum | O32: NUTS3 | P32: DE | Q32: yes | X32: 401 | Y32: 2 | Z32: =ROUND(Y32/X32*100,2) -> 0.5
A33: de_number_of_passenger_cars_emission_group_euro_6d | C33: Destatis | D33: https://www-genesis.destatis.de/genesis/online#astructure | E33: Statistisches Bundesamt Deutschland - GENESIS-Online. “Personenkraftwagen: Kreise, Stichtag, Kraftstoffarten, Emissionsgruppen.” Text, July 29, 2024. https://www-genesis.destatis.de/genesis/online#astructure. | F33: Creative Commons Attribution 4.0 International (CC BY 4.0) | G33: transport | M33: number | N33: sum | O33: NUTS3 | P33: DE | Q33: yes | X33: 401 | Y33: 2 | Z33: =ROUND(Y33/X33*100,2) -> 0.5
... A44: de_employment_in_textile_and_leather_manufacturing | C44: Bundesagentur für Arbeit | D44: https://statistik.arbeitsagentur.de/DE/Navigation/Statistiken/Interaktive-Statistiken/Datenbanken/Datenbanken-BST-Nav.html | E44: Federal Employment Agency. “Employment Database - Statistics of the Federal Employment Agency.” Accessed July 30, 2024. https://statistik.arbeitsagentur.de/DE/Navigation/Statistiken/Interaktive-Statistiken/Datenbanken/Datenbanken-BST-Nav.html. | F44: Creative Commons Attribution 4.0 International (CC BY 4.0) | G44: general stat | M44: number | N44: sum | O44: NUTS3 | P44: DE | Q44: yes | X44: 401 | Y44: 34 | Z44: =ROUND(Y44/X44*100,2) -> 8.48
A45: number_of_residential_buildings_poland | C45: Statistics Poland - Local Data Bank | D45: https://bdl.stat.gov.pl/bdl/metadane/cechy/2909 | E45: Statistics Poland - Local Data Bank, ‘Polish residential buildings in the gmina’. https://bdl.stat.gov.pl/bdl/metadane/cechy/2909 (accessed Jul. 27, 2022). | F45: Creative Commons Attribution 4.0 International (CC BY 4.0) | G45: buildings | H45: stock | L45: total | M45: number | N45: sum | O45: NUTS3 | P45: PL | Q45: yes | T45: =collected_variables_EU!A134 -> emission_factor_of_sub_bituminous_coal | V45: no | W45: 3 | X45: 73 | Y45: 0 | Z45: =ROUND(Y45/X45*100,2) -> 0
A46: number_of_dwellings_poland | C46: Statistics Poland - Local Data Bank | D46: https://bdl.stat.gov.pl/bdl/metadane/cechy/2166 | E46: Statistics Poland - Local Data Bank, ‘Polish dwelling stocks’. https://bdl.stat.gov.pl/bdl/metadane/cechy/2166 (accessed Jul. 27, 2022). | F46: Creative Commons Attribution 4.0 International (CC BY 4.0) | G46: buildings | H46: stock | L46: total | M46: number | N46: sum | O46: NUTS3 | P46: PL | Q46: yes | T46: =collected_variables_EU!A134 -> emission_factor_of_sub_bituminous_coal | V46: no | W46: 3 | X46: 73 | Y46: 0 | Z46: =ROUND(Y46/X46*100,2) -> 0
A47: number_of_dwelling_rooms_poland | C47: Statistics Poland - Local Data Bank | D47: https://bdl.stat.gov.pl/bdl/metadane/cechy/2166 | E47: Statistics Poland - Local Data Bank, ‘Polish dwelling stocks’. https://bdl.stat.gov.pl/bdl/metadane/cechy/2166 (accessed Jul. 27, 2022). | F47: Creative Commons Attribution 4.0 International (CC BY 4.0) | G47: buildings | H47: stock | L47: total | M47: number | N47: sum | O47: NUTS3 | P47: PL | Q47: yes | T47: =collected_variables_EU!A134 -> emission_factor_of_sub_bituminous_coal | V47: no | W47: 3 | X47: 73 | Y47: 0 | Z47: =ROUND(Y47/X47*100,2) -> 0
A48: useful_floor_area_of_dwellings_poland | C48: Statistics Poland - Local Data Bank | D48: https://bdl.stat.gov.pl/bdl/metadane/cechy/2166 | E48: Statistics Poland - Local Data Bank, ‘Polish dwelling stocks’. https://bdl.stat.gov.pl/bdl/metadane/cechy/2166 (accessed Jul. 27, 2022). | F48: Creative Commons Attribution 4.0 International (CC BY 4.0) | G48: buildings | J48: floor area | L48: total | M48: square kilometer | N48: sum | O48: NUTS3 | P48: PL | Q48: yes | T48: =collected_variables_EU!A134 -> emission_factor_of_sub_bituminous_coal | V48: no | W48: 3 | X48: 73 | Y48: 0 | Z48: =ROUND(Y48/X48*100,2) -> 0
A49: waste_from_households_batteries_and_accumulators_hazardous_poland | C49: Statistics Poland - Local Data Bank | D49: https://bdl.stat.gov.pl/bdl/metadane/cechy/2128 | E49: Statistics Poland - Local Data Bank, ‘Polish waste collected separately during the year’. https://bdl.stat.gov.pl/bdl/metadane/cechy/2175 (accessed Dec. 12, 2022). | F49: Creative Commons Attribution 4.0 International (CC BY 4.0) | G49: waste | H49: waste, supply | I49: equipment | M49: ton | N49: sum | O49: NUTS3 | P49: PL | Q49: yes | T49: =collected_variables_EU!A96 -> electricity_production_with_kerosene_type_jet_fuel_excluding_biofuel_portion | V49: no | W49: 3 | X49: 73 | Y49: 0 | Z49: =ROUND(Y49/X49*100,2) -> 0
A50: waste_from_other_sources_batteries_and_accumulators_hazardous_poland | B50: waste from other sources (commerce, small business, offices and institutions) - batteries and accumulators - hazardous | C50: Statistics Poland - Local Data Bank | D50: https://bdl.stat.gov.pl/bdl/metadane/cechy/2128 | E50: Statistics Poland - Local Data Bank, ‘Polish waste collected separately during the year’. https://bdl.stat.gov.pl/bdl/metadane/cechy/2175 (accessed Dec. 12, 2022). | F50: Creative Commons Attribution 4.0 International (CC BY 4.0) | G50: waste | H50: waste, supply | I50: equipment | M50: ton | N50: sum | O50: NUTS3 | P50: PL | Q50: yes | T50: =collected_variables_EU!A96 -> electricity_production_with_kerosene_type_jet_fuel_excluding_biofuel_portion | V50: no | W50: 3 | X50: 73 | Y50: 0 | Z50: =ROUND(Y50/X50*100,2) -> 0
A51: waste_total_batteries_and_accumulators_hazardous_poland | C51: Statistics Poland - Local Data Bank | D51: https://bdl.stat.gov.pl/bdl/metadane/cechy/2128 | E51: Statistics Poland - Local Data Bank, ‘Polish waste collected separately during the year’. https://bdl.stat.gov.pl/bdl/metadane/cechy/2175 (accessed Dec. 12, 2022). | F51: Creative Commons Attribution 4.0 International (CC BY 4.0) | G51: waste | H51: waste, supply | I51: equipment | L51: total | M51: ton | N51: sum | O51: NUTS3 | P51: PL | Q51: yes | T51: =collected_variables_EU!A96 -> electricity_production_with_kerosene_type_jet_fuel_excluding_biofuel_portion | V51: no | W51: 3 | X51: 73 | Y51: 0 | Z51: =ROUND(Y51/X51*100,2) -> 0
A52: waste_from_households_batteries_and_accumulators_total_poland | C52: Statistics Poland - Local Data Bank | D52: https://bdl.stat.gov.pl/bdl/metadane/cechy/2128 | E52: Statistics Poland - Local Data Bank, ‘Polish waste collected separately during the year’. https://bdl.stat.gov.pl/bdl/metadane/cechy/2175 (accessed Dec. 12, 2022). | F52: Creative Commons Attribution 4.0 International (CC BY 4.0) | G52: waste | H52: waste, supply | I52: equipment | M52: ton | N52: sum | O52: NUTS3 | P52: PL | Q52: yes | T52: =collected_variables_EU!A96 -> electricity_production_with_kerosene_type_jet_fuel_excluding_biofuel_portion | V52: no | W52: 3 | X52: 73 | Y52: 0 | Z52: =ROUND(Y52/X52*100,2) -> 0
A53: waste_from_other_sources_batteries_and_accumulators_total_poland | B53: waste from other sources (commerce, small business, offices and institutions) - batteries and accumulators - total | C53: Statistics Poland - Local Data Bank | D53: https://bdl.stat.gov.pl/bdl/metadane/cechy/2128 | E53: Statistics Poland - Local Data Bank, ‘Polish waste collected separately during the year’. https://bdl.stat.gov.pl/bdl/metadane/cechy/2175 (accessed Dec. 12, 2022). | F53: Creative Commons Attribution 4.0 International (CC BY 4.0) | G53: waste | H53: waste, supply | I53: equipment | M53: ton | N53: sum | O53: NUTS3 | P53: PL | Q53: yes | T53: =collected_variables_EU!A96 -> electricity_production_with_kerosene_type_jet_fuel_excluding_biofuel_portion | V53: no | W53: 3 | X53: 73 | Y53: 0 | Z53: =ROUND(Y53/X53*100,2) -> 0
A54: waste_total_batteries_and_accumulators_total_poland | C54: Statistics Poland - Local Data Bank | D54: https://bdl.stat.gov.pl/bdl/metadane/cechy/2128 | E54: Statistics Poland - Local Data Bank, ‘Polish waste collected separately during the year’. https://bdl.stat.gov.pl/bdl/metadane/cechy/2175 (accessed Dec. 12, 2022). | F54: Creative Commons Attribution 4.0 International (CC BY 4.0) | G54: waste | H54: waste, supply | I54: equipment | L54: total | M54: ton | N54: sum | O54: NUTS3 | P54: PL | Q54: yes | T54: =collected_variables_EU!A96 -> electricity_production_with_kerosene_type_jet_fuel_excluding_biofuel_portion | V54: no | W54: 3 | X54: 73 | Y54: 0 | Z54: =ROUND(Y54/X54*100,2) -> 0
A55: waste_from_households_biodegradable_poland | C55: Statistics Poland - Local Data Bank | D55: https://bdl.stat.gov.pl/bdl/metadane/cechy/2128 | E55: Statistics Poland - Local Data Bank, ‘Polish waste collected separately during the year’. https://bdl.stat.gov.pl/bdl/metadane/cechy/2175 (accessed Dec. 12, 2022). | F55: Creative Commons Attribution 4.0 International (CC BY 4.0) | G55: waste | H55: waste, supply | I55: biodegradable | M55: ton | N55: sum | O55: NUTS3 | P55: PL | Q55: yes | T55: =collected_variables_EU!A96 -> electricity_production_with_kerosene_type_jet_fuel_excluding_biofuel_portion | V55: no | W55: 3 | X55: 73 | Y55: 0 | Z55: =ROUND(Y55/X55*100,2) -> 0
A56: waste_from_other_sources_biodegradable_poland | B56: waste from other sources (commerce, small business, offices and institutions) - biodegradable | C56: Statistics Poland - Local Data Bank | D56: https://bdl.stat.gov.pl/bdl/metadane/cechy/2128 | E56: Statistics Poland - Local Data Bank, ‘Polish waste collected separately during the year’. https://bdl.stat.gov.pl/bdl/metadane/cechy/2175 (accessed Dec. 12, 2022). | F56: Creative Commons Attribution 4.0 International (CC BY 4.0) | G56: waste | H56: waste, supply | I56: biodegradable | M56: ton | N56: sum | O56: NUTS3 | P56: PL | Q56: yes | T56: =collected_variables_EU!A96 -> electricity_production_with_kerosene_type_jet_fuel_excluding_biofuel_portion | V56: no | W56: 3 | X56: 73 | Y56: 0 | Z56: =ROUND(Y56/X56*100,2) -> 0
A57: waste_total_biodegradable_poland | C57: Statistics Poland - Local Data Bank | D57: https://bdl.stat.gov.pl/bdl/metadane/cechy/2128 | E57: Statistics Poland - Local Data Bank, ‘Polish waste collected separately during the year’. https://bdl.stat.gov.pl/bdl/metadane/cechy/2175 (accessed Dec. 12, 2022). | F57: Creative Commons Attribution 4.0 International (CC BY 4.0) | G57: waste | H57: waste, supply | I57: biodegradable | L57: total | M57: ton | N57: sum | O57: NUTS3 | P57: PL | Q57: yes | T57: =collected_variables_EU!A96 -> electricity_production_with_kerosene_type_jet_fuel_excluding_biofuel_portion | V57: no | W57: 3 | X57: 73 | Y57: 0 | Z57: =ROUND(Y57/X57*100,2) -> 0
A58: waste_from_households_bulky_waste_poland | C58: Statistics Poland - Local Data Bank | D58: https://bdl.stat.gov.pl/bdl/metadane/cechy/2128 | E58: Statistics Poland - Local Data Bank, ‘Polish waste collected separately during the year’. https://bdl.stat.gov.pl/bdl/metadane/cechy/2175 (accessed Dec. 12, 2022). | F58: Creative Commons Attribution 4.0 International (CC BY 4.0) | G58: waste | H58: waste, supply | I58: bulk | M58: ton | N58: sum | O58: NUTS3 | P58: PL | Q58: yes | T58: =collected_variables_EU!A96 -> electricity_production_with_kerosene_type_jet_fuel_excluding_biofuel_portion | V58: no | W58: 3 | X58: 73 | Y58: 0 | Z58: =ROUND(Y58/X58*100,2) -> 0
A59: waste_from_other_sources_bulky_waste_poland | B59: waste from other sources (commerce, small business, offices and institutions) - bulky waste | C59: Statistics Poland - Local Data Bank | D59: https://bdl.stat.gov.pl/bdl/metadane/cechy/2128 | E59: Statistics Poland - Local Data Bank, ‘Polish waste collected separately during the year’. https://bdl.stat.gov.pl/bdl/metadane/cechy/2175 (accessed Dec. 12, 2022). | F59: Creative Commons Attribution 4.0 International (CC BY 4.0) | G59: waste | H59: waste, supply | I59: bulk | M59: ton | N59: sum | O59: NUTS3 | P59: PL | Q59: yes | T59: =collected_variables_EU!A96 -> electricity_production_with_kerosene_type_jet_fuel_excluding_biofuel_portion | V59: no | W59: 3 | X59: 73 | Y59: 0 | Z59: =ROUND(Y59/X59*100,2) -> 0
A60: waste_total_bulky_waste_poland | C60: Statistics Poland - Local Data Bank | D60: https://bdl.stat.gov.pl/bdl/metadane/cechy/2128 | E60: Statistics Poland - Local Data Bank, ‘Polish waste collected separately during the year’. https://bdl.stat.gov.pl/bdl/metadane/cechy/2175 (accessed Dec. 12, 2022). | F60: Creative Commons Attribution 4.0 International (CC BY 4.0) | G60: waste | H60: waste, supply | I60: bulk | L60: total | M60: ton | N60: sum | O60: NUTS3 | P60: PL | Q60: yes | T60: =collected_variables_EU!A96 -> electricity_production_with_kerosene_type_jet_fuel_excluding_biofuel_portion | V60: no | W60: 3 | X60: 73 | Y60: 0 | Z60: =ROUND(Y60/X60*100,2) -> 0
A61: waste_from_households_composite_packaging_poland | C61: Statistics Poland - Local Data Bank | D61: https://bdl.stat.gov.pl/bdl/metadane/cechy/2128 | E61: Statistics Poland - Local Data Bank, ‘Polish waste collected separately during the year’. https://bdl.stat.gov.pl/bdl/metadane/cechy/2175 (accessed Dec. 12, 2022). | F61: Creative Commons Attribution 4.0 International (CC BY 4.0) | G61: waste | H61: waste, supply | I61: packaging | M61: ton | N61: sum | O61: NUTS3 | P61: PL | Q61: yes | T61: =collected_variables_EU!A96 -> electricity_production_with_kerosene_type_jet_fuel_excluding_biofuel_portion | V61: no | W61: 3 | X61: 73 | Y61: 0 | Z61: =ROUND(Y61/X61*100,2) -> 0
A62: waste_from_other_sources_composite_packaging_poland | B62: waste from other sources (commerce, small business, offices and institutions) - composite packaging | C62: Statistics Poland - Local Data Bank | D62: https://bdl.stat.gov.pl/bdl/metadane/cechy/2128 | E62: Statistics Poland - Local Data Bank, ‘Polish waste collected separately during the year’. https://bdl.stat.gov.pl/bdl/metadane/cechy/2175 (accessed Dec. 12, 2022). | F62: Creative Commons Attribution 4.0 International (CC BY 4.0) | G62: waste | H62: waste, supply | I62: packaging | M62: ton | N62: sum | O62: NUTS3 | P62: PL | Q62: yes | T62: =collected_variables_EU!A96 -> electricity_production_with_kerosene_type_jet_fuel_excluding_biofuel_portion | V62: no | W62: 3 | X62: 73 | Y62: 0 | Z62: =ROUND(Y62/X62*100,2) -> 0
A63: waste_total_composite_packaging_poland | C63: Statistics Poland - Local Data Bank | D63: https://bdl.stat.gov.pl/bdl/metadane/cechy/2128 | E63: Statistics Poland - Local Data Bank, ‘Polish waste collected separately during the year’. https://bdl.stat.gov.pl/bdl/metadane/cechy/2175 (accessed Dec. 12, 2022). | F63: Creative Commons Attribution 4.0 International (CC BY 4.0) | G63: waste | H63: waste, supply | I63: packaging | L63: total | M63: ton | N63: sum | O63: NUTS3 | P63: PL | Q63: yes | T63: =collected_variables_EU!A96 -> electricity_production_with_kerosene_type_jet_fuel_excluding_biofuel_portion | V63: no | W63: 3 | X63: 73 | Y63: 0 | Z63: =ROUND(Y63/X63*100,2) -> 0
A64: waste_from_households_glass_poland | C64: Statistics Poland - Local Data Bank | D64: https://bdl.stat.gov.pl/bdl/metadane/cechy/2128 | E64: Statistics Poland - Local Data Bank, ‘Polish waste collected separately during the year’. https://bdl.stat.gov.pl/bdl/metadane/cechy/2175 (accessed Dec. 12, 2022). | F64: Creative Commons Attribution 4.0 International (CC BY 4.0) | G64: waste | H64: waste, supply | I64: glass | M64: ton | N64: sum | O64: NUTS3 | P64: PL | Q64: yes | T64: =collected_variables_EU!A96 -> electricity_production_with_kerosene_type_jet_fuel_excluding_biofuel_portion | V64: no | W64: 3 | X64: 73 | Y64: 0 | Z64: =ROUND(Y64/X64*100,2) -> 0
A65: waste_from_other_sources_glass_poland | B65: waste from other sources (commerce, small business, offices and institutions) - glass | C65: Statistics Poland - Local Data Bank | D65: https://bdl.stat.gov.pl/bdl/metadane/cechy/2128 | E65: Statistics Poland - Local Data Bank, ‘Polish waste collected separately during the year’. https://bdl.stat.gov.pl/bdl/metadane/cechy/2175 (accessed Dec. 12, 2022). | F65: Creative Commons Attribution 4.0 International (CC BY 4.0) | G65: waste | H65: waste, supply | I65: glass | M65: ton | N65: sum | O65: NUTS3 | P65: PL | Q65: yes | T65: =collected_variables_EU!A96 -> electricity_production_with_kerosene_type_jet_fuel_excluding_biofuel_portion | V65: no | W65: 3 | X65: 73 | Y65: 0 | Z65: =ROUND(Y65/X65*100,2) -> 0
A66: waste_total_glass_poland | C66: Statistics Poland - Local Data Bank | D66: https://bdl.stat.gov.pl/bdl/metadane/cechy/2128 | E66: Statistics Poland - Local Data Bank, ‘Polish waste collected separately during the year’. https://bdl.stat.gov.pl/bdl/metadane/cechy/2175 (accessed Dec. 12, 2022). | F66: Creative Commons Attribution 4.0 International (CC BY 4.0) | G66: waste | H66: waste, supply | I66: glass | L66: total | M66: ton | N66: sum | O66: NUTS3 | P66: PL | Q66: yes | T66: =collected_variables_EU!A96 -> electricity_production_with_kerosene_type_jet_fuel_excluding_biofuel_portion | V66: no | W66: 3 | X66: 73 | Y66: 0 | Z66: =ROUND(Y66/X66*100,2) -> 0
A67: waste_from_households_hazardous_poland | C67: Statistics Poland - Local Data Bank | D67: https://bdl.stat.gov.pl/bdl/metadane/cechy/2128 | E67: Statistics Poland - Local Data Bank, ‘Polish waste collected separately during the year’. https://bdl.stat.gov.pl/bdl/metadane/cechy/2175 (accessed Dec. 12, 2022). | F67: Creative Commons Attribution 4.0 International (CC BY 4.0) | G67: waste | H67: waste, supply | I67: hazardous | M67: ton | N67: sum | O67: NUTS3 | P67: PL | Q67: yes | T67: =collected_variables_EU!A96 -> electricity_production_with_kerosene_type_jet_fuel_excluding_biofuel_portion | V67: no | W67: 3 | X67: 73 | Y67: 0 | Z67: =ROUND(Y67/X67*100,2) -> 0
A68: waste_from_other_sources_hazardous_poland | B68: waste from other sources (commerce, small business, offices and institutions) - hazardous | C68: Statistics Poland - Local Data Bank | D68: https://bdl.stat.gov.pl/bdl/metadane/cechy/2128 | E68: Statistics Poland - Local Data Bank, ‘Polish waste collected separately during the year’. https://bdl.stat.gov.pl/bdl/metadane/cechy/2175 (accessed Dec. 12, 2022). | F68: Creative Commons Attribution 4.0 International (CC BY 4.0) | G68: waste | H68: waste, supply | I68: hazardous | M68: ton | N68: sum | O68: NUTS3 | P68: PL | Q68: yes | T68: =collected_variables_EU!A96 -> electricity_production_with_kerosene_type_jet_fuel_excluding_biofuel_portion | V68: no | W68: 3 | X68: 73 | Y68: 0 | Z68: =ROUND(Y68/X68*100,2) -> 0
A69: waste_total_hazardous_poland | C69: Statistics Poland - Local Data Bank | D69: https://bdl.stat.gov.pl/bdl/metadane/cechy/2128 | E69: Statistics Poland - Local Data Bank, ‘Polish waste collected separately during the year’. https://bdl.stat.gov.pl/bdl/metadane/cechy/2175 (accessed Dec. 12, 2022). | F69: Creative Commons Attribution 4.0 International (CC BY 4.0) | G69: waste | H69: waste, supply | I69: hazardous | L69: total | M69: ton | N69: sum | O69: NUTS3 | P69: PL | Q69: yes | T69: =collected_variables_EU!A96 -> electricity_production_with_kerosene_type_jet_fuel_excluding_biofuel_portion | V69: no | W69: 3 | X69: 73 | Y69: 0 | Z69: =ROUND(Y69/X69*100,2) -> 0
A70: waste_from_households_metals_poland | C70: Statistics Poland - Local Data Bank | D70: https://bdl.stat.gov.pl/bdl/metadane/cechy/2128 | E70: Statistics Poland - Local Data Bank, ‘Polish waste collected separately during the year’. https://bdl.stat.gov.pl/bdl/metadane/cechy/2175 (accessed Dec. 12, 2022). | F70: Creative Commons Attribution 4.0 International (CC BY 4.0) | G70: waste | H70: waste, supply | I70: metal | M70: ton | N70: sum | O70: NUTS3 | P70: PL | Q70: yes | T70: =collected_variables_EU!A96 -> electricity_production_with_kerosene_type_jet_fuel_excluding_biofuel_portion | V70: no | W70: 3 | X70: 73 | Y70: 0 | Z70: =ROUND(Y70/X70*100,2) -> 0
A71: waste_from_other_sources_metals_poland | B71: waste from other sources (commerce, small business, offices and institutions) - metals | C71: Statistics Poland - Local Data Bank | D71: https://bdl.stat.gov.pl/bdl/metadane/cechy/2128 | E71: Statistics Poland - Local Data Bank, ‘Polish waste collected separately during the year’. https://bdl.stat.gov.pl/bdl/metadane/cechy/2175 (accessed Dec. 12, 2022). | F71: Creative Commons Attribution 4.0 International (CC BY 4.0) | G71: waste | H71: waste, supply | I71: metal | M71: ton | N71: sum | O71: NUTS3 | P71: PL | Q71: yes | T71: =collected_variables_EU!A96 -> electricity_production_with_kerosene_type_jet_fuel_excluding_biofuel_portion | V71: no | W71: 3 | X71: 73 | Y71: 0 | Z71: =ROUND(Y71/X71*100,2) -> 0
A72: waste_total_metals_poland | C72: Statistics Poland - Local Data Bank | D72: https://bdl.stat.gov.pl/bdl/metadane/cechy/2128 | E72: Statistics Poland - Local Data Bank, ‘Polish waste collected separately during the year’. https://bdl.stat.gov.pl/bdl/metadane/cechy/2175 (accessed Dec. 12, 2022). | F72: Creative Commons Attribution 4.0 International (CC BY 4.0) | G72: waste | H72: waste, supply | I72: metal | L72: total | M72: ton | N72: sum | O72: NUTS3 | P72: PL | Q72: yes | T72: =collected_variables_EU!A96 -> electricity_production_with_kerosene_type_jet_fuel_excluding_biofuel_portion | V72: no | W72: 3 | X72: 73 | Y72: 0 | Z72: =ROUND(Y72/X72*100,2) -> 0
A73: waste_from_households_mixed_waste_packaging_poland | C73: Statistics Poland - Local Data Bank | D73: https://bdl.stat.gov.pl/bdl/metadane/cechy/2128 | E73: Statistics Poland - Local Data Bank, ‘Polish waste collected separately during the year’. https://bdl.stat.gov.pl/bdl/metadane/cechy/2175 (accessed Dec. 12, 2022). | F73: Creative Commons Attribution 4.0 International (CC BY 4.0) | G73: waste | H73: waste, supply | I73: packaging | M73: ton | N73: sum | O73: NUTS3 | P73: PL | Q73: yes | T73: =collected_variables_EU!A96 -> electricity_production_with_kerosene_type_jet_fuel_excluding_biofuel_portion | V73: no | W73: 3 | X73: 73 | Y73: 0 | Z73: =ROUND(Y73/X73*100,2) -> 0
A74: waste_from_other_sources_mixed_waste_packaging_poland | B74: waste from other sources (commerce, small business, offices and institutions) - mixed waste packaging | C74: Statistics Poland - Local Data Bank | D74: https://bdl.stat.gov.pl/bdl/metadane/cechy/2128 | E74: Statistics Poland - Local Data Bank, ‘Polish waste collected separately during the year’. https://bdl.stat.gov.pl/bdl/metadane/cechy/2175 (accessed Dec. 12, 2022). | F74: Creative Commons Attribution 4.0 International (CC BY 4.0) | G74: waste | H74: waste, supply | I74: packaging | M74: ton | N74: sum | O74: NUTS3 | P74: PL | Q74: yes | T74: =collected_variables_EU!A96 -> electricity_production_with_kerosene_type_jet_fuel_excluding_biofuel_portion | V74: no | W74: 3 | X74: 73 | Y74: 0 | Z74: =ROUND(Y74/X74*100,2) -> 0
A75: waste_total_mixed_waste_packaging_poland | C75: Statistics Poland - Local Data Bank | D75: https://bdl.stat.gov.pl/bdl/metadane/cechy/2128 | E75: Statistics Poland - Local Data Bank, ‘Polish waste collected separately during the year’. https://bdl.stat.gov.pl/bdl/metadane/cechy/2175 (accessed Dec. 12, 2022). | F75: Creative Commons Attribution 4.0 International (CC BY 4.0) | G75: waste | H75: waste, supply | I75: packaging | L75: total | M75: ton | N75: sum | O75: NUTS3 | P75: PL | Q75: yes | T75: =collected_variables_EU!A96 -> electricity_production_with_kerosene_type_jet_fuel_excluding_biofuel_portion | V75: no | W75: 3 | X75: 73 | Y75: 0 | Z75: =ROUND(Y75/X75*100,2) -> 0
A76: waste_from_households_other_poland | C76: Statistics Poland - Local Data Bank | D76: https://bdl.stat.gov.pl/bdl/metadane/cechy/2128 | E76: Statistics Poland - Local Data Bank, ‘Polish waste collected separately during the year’. https://bdl.stat.gov.pl/bdl/metadane/cechy/2175 (accessed Dec. 12, 2022). | F76: Creative Commons Attribution 4.0 International (CC BY 4.0) | G76: waste | H76: waste, supply | I76: other | M76: ton | N76: sum | O76: NUTS3 | P76: PL | Q76: yes | T76: =collected_variables_EU!A96 -> electricity_production_with_kerosene_type_jet_fuel_excluding_biofuel_portion | V76: no | W76: 3 | X76: 73 | Y76: 0 | Z76: =ROUND(Y76/X76*100,2) -> 0
A77: waste_from_other_sources_other_poland | B77: waste from other sources (commerce, small business, offices and institutions) - other | C77: Statistics Poland - Local Data Bank | D77: https://bdl.stat.gov.pl/bdl/metadane/cechy/2128 | E77: Statistics Poland - Local Data Bank, ‘Polish waste collected separately during the year’. https://bdl.stat.gov.pl/bdl/metadane/cechy/2175 (accessed Dec. 12, 2022). | F77: Creative Commons Attribution 4.0 International (CC BY 4.0) | G77: waste | H77: waste, supply | I77: other | M77: ton | N77: sum | O77: NUTS3 | P77: PL | Q77: yes | T77: =collected_variables_EU!A96 -> electricity_production_with_kerosene_type_jet_fuel_excluding_biofuel_portion | V77: no | W77: 3 | X77: 73 | Y77: 0 | Z77: =ROUND(Y77/X77*100,2) -> 0
A78: waste_total_other_poland | C78: Statistics Poland - Local Data Bank | D78: https://bdl.stat.gov.pl/bdl/metadane/cechy/2128 | E78: Statistics Poland - Local Data Bank, ‘Polish waste collected separately during the year’. https://bdl.stat.gov.pl/bdl/metadane/cechy/2175 (accessed Dec. 12, 2022). | F78: Creative Commons Attribution 4.0 International (CC BY 4.0) | G78: waste | H78: waste, supply | I78: other | L78: total | M78: ton | N78: sum | O78: NUTS3 | P78: PL | Q78: yes | T78: =collected_variables_EU!A96 -> electricity_production_with_kerosene_type_jet_fuel_excluding_biofuel_portion | V78: no | W78: 3 | X78: 73 | Y78: 0 | Z78: =ROUND(Y78/X78*100,2) -> 0
A79: waste_from_households_paper_and_cardboard_poland | C79: Statistics Poland - Local Data Bank | D79: https://bdl.stat.gov.pl/bdl/metadane/cechy/2128 | E79: Statistics Poland - Local Data Bank, ‘Polish waste collected separately during the year’. https://bdl.stat.gov.pl/bdl/metadane/cechy/2175 (accessed Dec. 12, 2022). | F79: Creative Commons Attribution 4.0 International (CC BY 4.0) | G79: waste | H79: waste, supply | I79: paper | M79: ton | N79: sum | O79: NUTS3 | P79: PL | Q79: yes | T79: =collected_variables_EU!A96 -> electricity_production_with_kerosene_type_jet_fuel_excluding_biofuel_portion | V79: no | W79: 3 | X79: 73 | Y79: 0 | Z79: =ROUND(Y79/X79*100,2) -> 0
A80: waste_from_other_sources_paper_and_cardboard_poland | B80: waste from other sources (commerce, small business, offices and institutions) - paper and cardboard | C80: Statistics Poland - Local Data Bank | D80: https://bdl.stat.gov.pl/bdl/metadane/cechy/2128 | E80: Statistics Poland - Local Data Bank, ‘Polish waste collected separately during the year’. https://bdl.stat.gov.pl/bdl/metadane/cechy/2175 (accessed Dec. 12, 2022). | F80: Creative Commons Attribution 4.0 International (CC BY 4.0) | G80: waste | H80: waste, supply | I80: paper | M80: ton | N80: sum | O80: NUTS3 | P80: PL | Q80: yes | T80: =collected_variables_EU!A96 -> electricity_production_with_kerosene_type_jet_fuel_excluding_biofuel_portion | V80: no | W80: 3 | X80: 73 | Y80: 0 | Z80: =ROUND(Y80/X80*100,2) -> 0
A81: waste_total_paper_and_cardboard_poland | C81: Statistics Poland - Local Data Bank | D81: https://bdl.stat.gov.pl/bdl/metadane/cechy/2128 | E81: Statistics Poland - Local Data Bank, ‘Polish waste collected separately during the year’. https://bdl.stat.gov.pl/bdl/metadane/cechy/2175 (accessed Dec. 12, 2022). | F81: Creative Commons Attribution 4.0 International (CC BY 4.0) | G81: waste | H81: waste, supply | I81: paper | L81: total | M81: ton | N81: sum | O81: NUTS3 | P81: PL | Q81: yes | T81: =collected_variables_EU!A96 -> electricity_production_with_kerosene_type_jet_fuel_excluding_biofuel_portion | V81: no | W81: 3 | X81: 73 | Y81: 0 | Z81: =ROUND(Y81/X81*100,2) -> 0
A82: waste_from_households_plastics_poland | C82: Statistics Poland - Local Data Bank | D82: https://bdl.stat.gov.pl/bdl/metadane/cechy/2128 | E82: Statistics Poland - Local Data Bank, ‘Polish waste collected separately during the year’. https://bdl.stat.gov.pl/bdl/metadane/cechy/2175 (accessed Dec. 12, 2022). | F82: Creative Commons Attribution 4.0 International (CC BY 4.0) | G82: waste | H82: waste, supply | I82: chemicals and plastics | M82: ton | N82: sum | O82: NUTS3 | P82: PL | Q82: yes | T82: =collected_variables_EU!A96 -> electricity_production_with_kerosene_type_jet_fuel_excluding_biofuel_portion | V82: no | W82: 3 | X82: 73 | Y82: 0 | Z82: =ROUND(Y82/X82*100,2) -> 0
A83: waste_from_other_sources_plastics_poland | B83: waste from other sources (commerce, small business, offices and institutions) - plastics | C83: Statistics Poland - Local Data Bank | D83: https://bdl.stat.gov.pl/bdl/metadane/cechy/2128 | E83: Statistics Poland - Local Data Bank, ‘Polish waste collected separately during the year’. https://bdl.stat.gov.pl/bdl/metadane/cechy/2175 (accessed Dec. 12, 2022). | F83: Creative Commons Attribution 4.0 International (CC BY 4.0) | G83: waste | H83: waste, supply | I83: chemicals and plastics | M83: ton | N83: sum | O83: NUTS3 | P83: PL | Q83: yes | T83: =collected_variables_EU!A96 -> electricity_production_with_kerosene_type_jet_fuel_excluding_biofuel_portion | V83: no | W83: 3 | X83: 73 | Y83: 0 | Z83: =ROUND(Y83/X83*100,2) -> 0
A84: waste_total_plastics_poland | C84: Statistics Poland - Local Data Bank | D84: https://bdl.stat.gov.pl/bdl/metadane/cechy/2128 | E84: Statistics Poland - Local Data Bank, ‘Polish waste collected separately during the year’. https://bdl.stat.gov.pl/bdl/metadane/cechy/2175 (accessed Dec. 12, 2022). | F84: Creative Commons Attribution 4.0 International (CC BY 4.0) | G84: waste | H84: waste, supply | I84: chemicals and plastics | L84: total | M84: ton | N84: sum | O84: NUTS3 | P84: PL | Q84: yes | T84: =collected_variables_EU!A96 -> electricity_production_with_kerosene_type_jet_fuel_excluding_biofuel_portion | V84: no | W84: 3 | X84: 73 | Y84: 0 | Z84: =ROUND(Y84/X84*100,2) -> 0
A85: waste_from_households_textiles_poland | C85: Statistics Poland - Local Data Bank | D85: https://bdl.stat.gov.pl/bdl/metadane/cechy/2128 | E85: Statistics Poland - Local Data Bank, ‘Polish waste collected separately during the year’. https://bdl.stat.gov.pl/bdl/metadane/cechy/2175 (accessed Dec. 12, 2022). | F85: Creative Commons Attribution 4.0 International (CC BY 4.0) | G85: waste | H85: waste, supply | I85: textiles | M85: ton | N85: sum | O85: NUTS3 | P85: PL | Q85: yes | T85: =collected_variables_EU!A96 -> electricity_production_with_kerosene_type_jet_fuel_excluding_biofuel_portion | V85: no | W85: 3 | X85: 73 | Y85: 0 | Z85: =ROUND(Y85/X85*100,2) -> 0
A86: waste_from_other_sources_textiles_poland | B86: waste from other sources (commerce, small business, offices and institutions) - textiles | C86: Statistics Poland - Local Data Bank | D86: https://bdl.stat.gov.pl/bdl/metadane/cechy/2128 | E86: Statistics Poland - Local Data Bank, ‘Polish waste collected separately during the year’. https://bdl.stat.gov.pl/bdl/metadane/cechy/2175 (accessed Dec. 12, 2022). | F86: Creative Commons Attribution 4.0 International (CC BY 4.0) | G86: waste | H86: waste, supply | I86: textiles | M86: ton | N86: sum | O86: NUTS3 | P86: PL | Q86: yes | T86: =collected_variables_EU!A96 -> electricity_production_with_kerosene_type_jet_fuel_excluding_biofuel_portion | V86: no | W86: 3 | X86: 73 | Y86: 0 | Z86: =ROUND(Y86/X86*100,2) -> 0
A87: waste_total_textiles_poland | C87: Statistics Poland - Local Data Bank | D87: https://bdl.stat.gov.pl/bdl/metadane/cechy/2128 | E87: Statistics Poland - Local Data Bank, ‘Polish waste collected separately during the year’. https://bdl.stat.gov.pl/bdl/metadane/cechy/2175 (accessed Dec. 12, 2022). | F87: Creative Commons Attribution 4.0 International (CC BY 4.0) | G87: waste | H87: waste, supply | I87: textiles | L87: total | M87: ton | N87: sum | O87: NUTS3 | P87: PL | Q87: yes | T87: =collected_variables_EU!A96 -> electricity_production_with_kerosene_type_jet_fuel_excluding_biofuel_portion | V87: no | W87: 3 | X87: 73 | Y87: 0 | Z87: =ROUND(Y87/X87*100,2) -> 0
A88: waste_from_households_total_poland | C88: Statistics Poland - Local Data Bank | D88: https://bdl.stat.gov.pl/bdl/metadane/cechy/2128 | E88: Statistics Poland - Local Data Bank, ‘Polish waste collected separately during the year’. https://bdl.stat.gov.pl/bdl/metadane/cechy/2175 (accessed Dec. 12, 2022). | F88: Creative Commons Attribution 4.0 International (CC BY 4.0) | G88: waste | H88: waste, supply | M88: ton | N88: sum | O88: NUTS3 | P88: PL | Q88: yes | T88: =collected_variables_EU!A96 -> electricity_production_with_kerosene_type_jet_fuel_excluding_biofuel_portion | V88: no | W88: 3 | X88: 73 | Y88: 0 | Z88: =ROUND(Y88/X88*100,2) -> 0
A89: waste_from_other_sources_total_poland | B89: waste from other sources (commerce, small business, offices and institutions) - total | C89: Statistics Poland - Local Data Bank | D89: https://bdl.stat.gov.pl/bdl/metadane/cechy/2128 | E89: Statistics Poland - Local Data Bank, ‘Polish waste collected separately during the year’. https://bdl.stat.gov.pl/bdl/metadane/cechy/2175 (accessed Dec. 12, 2022). | F89: Creative Commons Attribution 4.0 International (CC BY 4.0) | G89: waste | H89: waste, supply | M89: ton | N89: sum | O89: NUTS3 | P89: PL | Q89: yes | T89: =collected_variables_EU!A96 -> electricity_production_with_kerosene_type_jet_fuel_excluding_biofuel_portion | V89: no | W89: 3 | X89: 73 | Y89: 0 | Z89: =ROUND(Y89/X89*100,2) -> 0
A90: waste_poland | C90: Statistics Poland - Local Data Bank | D90: https://bdl.stat.gov.pl/bdl/metadane/cechy/2128 | E90: Statistics Poland - Local Data Bank, ‘Polish waste collected separately during the year’. https://bdl.stat.gov.pl/bdl/metadane/cechy/2175 (accessed Dec. 12, 2022). | F90: Creative Commons Attribution 4.0 International (CC BY 4.0) | G90: waste | H90: waste, supply | L90: total | M90: ton | N90: sum | O90: NUTS3 | P90: PL | Q90: yes | T90: =collected_variables_EU!A96 -> electricity_production_with_kerosene_type_jet_fuel_excluding_biofuel_portion | V90: no | W90: 3 | X90: 73 | Y90: 0 | Z90: =ROUND(Y90/X90*100,2) -> 0
A91: waste_from_households_waste_electrical_and_electronic_equipment_hazardous_poland | C91: Statistics Poland - Local Data Bank | D91: https://bdl.stat.gov.pl/bdl/metadane/cechy/2128 | E91: Statistics Poland - Local Data Bank, ‘Polish waste collected separately during the year’. https://bdl.stat.gov.pl/bdl/metadane/cechy/2175 (accessed Dec. 12, 2022). | F91: Creative Commons Attribution 4.0 International (CC BY 4.0) | G91: waste | H91: waste, supply | I91: equipment | M91: ton | N91: sum | O91: NUTS3 | P91: PL | Q91: yes | T91: =collected_variables_EU!A96 -> electricity_production_with_kerosene_type_jet_fuel_excluding_biofuel_portion | V91: no | W91: 3 | X91: 73 | Y91: 0 | Z91: =ROUND(Y91/X91*100,2) -> 0
A92: waste_from_other_sources_waste_electrical_and_electronic_equipment_hazardous_poland | B92: waste from other sources (commerce, small business, offices and institutions) - waste electrical and electronic equipment - hazardous | C92: Statistics Poland - Local Data Bank | D92: https://bdl.stat.gov.pl/bdl/metadane/cechy/2128 | E92: Statistics Poland - Local Data Bank, ‘Polish waste collected separately during the year’. https://bdl.stat.gov.pl/bdl/metadane/cechy/2175 (accessed Dec. 12, 2022). | F92: Creative Commons Attribution 4.0 International (CC BY 4.0) | G92: waste | H92: waste, supply | I92: equipment | M92: ton | N92: sum | O92: NUTS3 | P92: PL | Q92: yes | T92: =collected_variables_EU!A96 -> electricity_production_with_kerosene_type_jet_fuel_excluding_biofuel_portion | V92: no | W92: 3 | X92: 73 | Y92: 0 | Z92: =ROUND(Y92/X92*100,2) -> 0
A93: waste_total_waste_electrical_and_electronic_equipment_hazardous_poland | C93: Statistics Poland - Local Data Bank | D93: https://bdl.stat.gov.pl/bdl/metadane/cechy/2128 | E93: Statistics Poland - Local Data Bank, ‘Polish waste collected separately during the year’. https://bdl.stat.gov.pl/bdl/metadane/cechy/2175 (accessed Dec. 12, 2022). | F93: Creative Commons Attribution 4.0 International (CC BY 4.0) | G93: waste | H93: waste, supply | I93: equipment | L93: total | M93: ton | N93: sum | O93: NUTS3 | P93: PL | Q93: yes | T93: =collected_variables_EU!A96 -> electricity_production_with_kerosene_type_jet_fuel_excluding_biofuel_portion | V93: no | W93: 3 | X93: 73 | Y93: 0 | Z93: =ROUND(Y93/X93*100,2) -> 0
A94: waste_from_households_waste_electrical_and_electronic_equipment_total_poland | C94: Statistics Poland - Local Data Bank | D94: https://bdl.stat.gov.pl/bdl/metadane/cechy/2128 | E94: Statistics Poland - Local Data Bank, ‘Polish waste collected separately during the year’. https://bdl.stat.gov.pl/bdl/metadane/cechy/2175 (accessed Dec. 12, 2022). | F94: Creative Commons Attribution 4.0 International (CC BY 4.0) | G94: waste | H94: waste, supply | I94: equipment | M94: ton | N94: sum | O94: NUTS3 | P94: PL | Q94: yes | T94: =collected_variables_EU!A96 -> electricity_production_with_kerosene_type_jet_fuel_excluding_biofuel_portion | V94: no | W94: 3 | X94: 73 | Y94: 0 | Z94: =ROUND(Y94/X94*100,2) -> 0
A95: waste_from_other_sources_waste_electrical_and_electronic_equipment_total_poland | B95: waste from other sources (commerce, small business, offices and institutions) - waste electrical and electronic equipment - total | C95: Statistics Poland - Local Data Bank | D95: https://bdl.stat.gov.pl/bdl/metadane/cechy/2128 | E95: Statistics Poland - Local Data Bank, ‘Polish waste collected separately during the year’. https://bdl.stat.gov.pl/bdl/metadane/cechy/2175 (accessed Dec. 12, 2022). | F95: Creative Commons Attribution 4.0 International (CC BY 4.0) | G95: waste | H95: waste, supply | I95: equipment | M95: ton | N95: sum | O95: NUTS3 | P95: PL | Q95: yes | T95: =collected_variables_EU!A96 -> electricity_production_with_kerosene_type_jet_fuel_excluding_biofuel_portion | V95: no | W95: 3 | X95: 73 | Y95: 0 | Z95: =ROUND(Y95/X95*100,2) -> 0
A96: waste_total_waste_electrical_and_electronic_equipment_total_poland | C96: Statistics Poland - Local Data Bank | D96: https://bdl.stat.gov.pl/bdl/metadane/cechy/2128 | E96: Statistics Poland - Local Data Bank, ‘Polish waste collected separately during the year’. https://bdl.stat.gov.pl/bdl/metadane/cechy/2175 (accessed Dec. 12, 2022). | F96: Creative Commons Attribution 4.0 International (CC BY 4.0) | G96: waste | H96: waste, supply | I96: equipment | L96: total | M96: ton | N96: sum | O96: NUTS3 | P96: PL | Q96: yes | T96: =collected_variables_EU!A96 -> electricity_production_with_kerosene_type_jet_fuel_excluding_biofuel_portion | V96: no | W96: 3 | X96: 73 | Y96: 0 | Z96: =ROUND(Y96/X96*100,2) -> 0
A97: number_of_busses_poland | C97: Statistics Poland - Local Data Bank | D97: https://bdl.stat.gov.pl/bdl/metadane/cechy/3584 | E97: Statistics Poland - Local Data Bank, ‘Polish vehicles by age groups’. https://bdl.stat.gov.pl/bdl/metadane/cechy/3584 (accessed Jul. 27, 2022). | F97: Creative Commons Attribution 4.0 International (CC BY 4.0) | G97: transport | H97: stock | M97: number | N97: sum | O97: NUTS3 | P97: PL | Q97: yes | T97: =collected_variables_EU!A134 -> emission_factor_of_sub_bituminous_coal | V97: no | W97: 3 | X97: 73 | Y97: 0 | Z97: =ROUND(Y97/X97*100,2) -> 0
A98: number_of_lorries_poland | C98: Statistics Poland - Local Data Bank | D98: https://bdl.stat.gov.pl/bdl/metadane/cechy/3584 | E98: Statistics Poland - Local Data Bank, ‘Polish vehicles by age groups’. https://bdl.stat.gov.pl/bdl/metadane/cechy/3584 (accessed Jul. 27, 2022). | F98: Creative Commons Attribution 4.0 International (CC BY 4.0) | G98: transport | H98: stock | M98: number | N98: sum | O98: NUTS3 | P98: PL | Q98: yes | T98: =collected_variables_EU!A299 -> final_energy_consumption_from_manufacture_of_transport_equipment_using_other_bituminous_coal | V98: no | W98: 3 | X98: 73 | Y98: 0 | Z98: =ROUND(Y98/X98*100,2) -> 0
A99: number_of_mopeds_poland | C99: Statistics Poland - Local Data Bank | D99: https://bdl.stat.gov.pl/bdl/metadane/cechy/3584 | E99: Statistics Poland - Local Data Bank, ‘Polish vehicles by age groups’. https://bdl.stat.gov.pl/bdl/metadane/cechy/3584 (accessed Jul. 27, 2022). | F99: Creative Commons Attribution 4.0 International (CC BY 4.0) | G99: transport | H99: stock | M99: number | N99: sum | O99: NUTS3 | P99: PL | Q99: yes | T99: =collected_variables_EU!A92 -> electricity_production_with_geothermal | V99: no | W99: 3 | X99: 73 | Y99: 0 | Z99: =ROUND(Y99/X99*100,2) -> 0
A100: number_of_motorcycles_poland | C100: Statistics Poland - Local Data Bank | D100: https://bdl.stat.gov.pl/bdl/metadane/cechy/3584 | E100: Statistics Poland - Local Data Bank, ‘Polish vehicles by age groups’. https://bdl.stat.gov.pl/bdl/metadane/cechy/3584 (accessed Jul. 27, 2022). | F100: Creative Commons Attribution 4.0 International (CC BY 4.0) | G100: transport | H100: stock | M100: number | N100: sum | O100: NUTS3 | P100: PL | Q100: yes | T100: =collected_variables_EU!A92 -> electricity_production_with_geothermal | V100: no | W100: 3 | X100: 73 | Y100: 0 | Z100: =ROUND(Y100/X100*100,2) -> 0
A101: number_of_passenger_cars_poland | C101: Statistics Poland - Local Data Bank | D101: https://bdl.stat.gov.pl/bdl/metadane/cechy/3584 | E101: Statistics Poland - Local Data Bank, ‘Polish vehicles by age groups’. https://bdl.stat.gov.pl/bdl/metadane/cechy/3584 (accessed Jul. 27, 2022). | F101: Creative Commons Attribution 4.0 International (CC BY 4.0) | G101: transport | H101: stock | M101: number | N101: sum | O101: NUTS3 | P101: PL | Q101: yes | T101: =collected_variables_EU!A92 -> electricity_production_with_geothermal | V101: no | W101: 3 | X101: 73 | Y101: 0 | Z101: =ROUND(Y101/X101*100,2) -> 0
A102: number_of_road_tractors_poland | C102: Statistics Poland - Local Data Bank | D102: https://bdl.stat.gov.pl/bdl/metadane/cechy/3584 | E102: Statistics Poland - Local Data Bank, ‘Polish vehicles by age groups’. https://bdl.stat.gov.pl/bdl/metadane/cechy/3584 (accessed Jul. 27, 2022). | F102: Creative Commons Attribution 4.0 International (CC BY 4.0) | G102: transport | H102: stock | M102: number | N102: sum | O102: NUTS3 | P102: PL | Q102: yes | T102: =collected_variables_EU!A92 -> electricity_production_with_geothermal | V102: no | W102: 3 | X102: 73 | Y102: 0 | Z102: =ROUND(Y102/X102*100,2) -> 0
A103: es_utilized_agricultural_area | C103: INE - The National Statistics Institute of Spain | D103: https://www.ine.es/jaxi/Tabla.htm?tpx=52071&L=1 | M103: square kilometer | N103: sum | O103: LAU | P103: ES | Q103: yes | X103: 8043 | Y103: 348 | Z103: =ROUND(Y103/X103*100,2) -> 4.33
A104: es_number_of_dwellings | C104: INE - The National Statistics Institute of Spain | D104: https://www.ine.es/jaxi/Tabla.htm?tpx=59531&L=0 | M104: number | N104: sum | O104: LAU | P104: ES | X104: 8043 | Y104: 4992 | Z104: =ROUND(Y104/X104*100,2) -> 62.07
A105: es_number_of_commerical_and_service_companies | C105: INE - The National Statistics Institute of Spain | D105: https://www.ine.es/dynInfo/Infografia/Territoriales/capituloGraficos.html#_graf | M105: number | N105: sum | O105: NUTS3 | P105: ES | X105: 52 | Y105: 3 | Z105: =ROUND(Y105/X105*100,2) -> 5.77
A106: es_average_daily_traffic_light_duty_vehicles | C106: DATAESTUR | D106: https://www.dataestur.es/en/transport/road-traffic/ | M106: number | N106: mean | O106: NUTS3 | P106: ES | X106: 52 | Y106: 10 | Z106: =ROUND(Y106/X106*100,2) -> 19.23

Sheet eucalc_variables
A1: original_eucalc_var_name | B1: var_name | C1: var_display_name | D1: var_description | E1: var_unit | F1: var_aggregation_method | G1: tag_sector | H1: tag_type | I1: tag_commodity | J1: tag_resource | K1: tag_link | L1: tag_other | M1: to_stage? | N1: staging_calculation | O1: proxy_reasoning | P1: eucalc_sum_check | Q1: post_disagg_calculation_eq | R1: is_used_for_SOIs? | S1: is_used_in_midas_model? | T1: used_anywhere? | U1: threshhold for rounding to 0 | V1: proxy_assigned? | W1: new_var | X1: aggregation_tree | Y1: parent_name | Z1: agr_bioenergy_capacity | AA1: eucalc_agr_bioenergy_demand | AB1: agr_total_bioenergy | AI1: var_name | AJ1: aggregation_tree | AK1: parent_name | AL1: affected trees | AO1: aggregation_id | AP1: column | AQ1: check | AR1: list_of_ids_to_aggregate | AS1: aggregation_id | AT1: 1 | AU1: 2 | AV1: 3 | AW1: 4 | AX1: 5 | AY1: 6 | AZ1: 7 | BA1: 8 | BB1: 9 | BC1: 10 | BD1: 11 | BE1: 12 | BF1: 13 | BG1: 14 | BH1: 15 | BI1: 16 | BJ1: 1 | BK1: 2 | BL1: 3 | BM1: 4 | BN1: 5 | BO1: 6 | BP1: 7 | BQ1: 8 | BR1: 9 | BS1: 10 | BT1: 11 | BU1: 12 | BV1: 13 | BW1: 14 | BX1: 15 | BY1: 16 | BZ1: 1 | CA1: 2 | CB1: 3 | CC1: 4 | CD1: 5 | CE1: 6 | CF1: 7 | CG1: 8 | CH1: 9 | CI1: 10 | CJ1: 11 | CK1: 12 | CL1: 13 | CM1: 14 | CN1: 15 | CO1: 16
A2: agr_bioenergy-capacity_biogas_digestor[TWh] | B2: eucalc_agr_bioenergy_capacity_biogas_digestor | C2: Biogas, digestor | E2: TWh | F2: SUM | G2: agriculture and forestry | H2: capacity | I2: biogas,energy,renewables | M2: yes | R2: =IF(COUNTIF(soi_input_variables!A:A,B2)>0,"yes","no") -> no | S2: =IF(COUNTIF(midas_input_variables!A:A,B2)>0,"yes","no") -> no | T2: =IF(OR(R2="yes",S2="yes"),"yes","no") -> no | U2: =0.0005 -> 0.0005 | V2: =IF(COUNTIF(eucalc_variables_proxies!A:A,B2)>0,"yes","no") -> yes | X2: agr_bioenergy_capacity | Z2: eucalc_agr_bioenergy_capacity_biogas | AC2: agr_bioenergy_capacity | AI2: eucalc_agr_bioenergy_capacity_biogas_digestor | AJ2: agr_bioenergy_capacity | AK2: agr_bioenergy-capacity_sum | AL2: land_use? | AP2: agr_domestic-production_liv_abp_processed_afat[kcal] | AQ2: TRUE | AT2: {=IFERROR(_xlfn.TEXTSPLIT(AR2,";",,FALSE),"")} | AU2: {=IF(LEN(AR2)>0,_xlfn.TEXTSPLIT(AR2,";",,TRUE),"")} | BJ2: =IF(LEN(AT2)>0,VALUE(AT2),"") | BK2: =IF(LEN(AU2)>0,VALUE(AU2),"") | BL2: =IF(LEN(AV2)>0,VALUE(AV2),"") | BM2: =IF(LEN(AW2)>0,VALUE(AW2),"") | BN2: =IF(LEN(AX2)>0,VALUE(AX2),"") | BO2: =IF(LEN(AY2)>0,VALUE(AY2),"") | BP2: =IF(LEN(AZ2)>0,VALUE(AZ2),"") | BQ2: =IF(LEN(BA2)>0,VALUE(BA2),"") | ... BY2: =IF(LEN(BI2)>0,VALUE(BI2),"") | BZ2: =IF(LEN(BJ2)>0,VLOOKUP(BJ2,$AO:$AP,2,FALSE),"") | CA2: =IF(LEN(BK2)>0,VLOOKUP(BK2,$AO:$AP,2,FALSE),"") | CB2: =IF(LEN(BL2)>0,VLOOKUP(BL2,$AO:$AP,2,FALSE),"") | CC2: =IF(LEN(BM2)>0,VLOOKUP(BM2,$AO:$AP,2,FALSE),"") | CD2: =IF(LEN(BN2)>0,VLOOKUP(BN2,$AO:$AP,2,FALSE),"") | CE2: =IF(LEN(BO2)>0,VLOOKUP(BO2,$AO:$AP,2,FALSE),"") | CF2: =IF(LEN(BP2)>0,VLOOKUP(BP2,$AO:$AP,2,FALSE),"") | CG2: =IF(LEN(BQ2)>0,VLOOKUP(BQ2,$AO:$AP,2,FALSE),"") | ... CO2: =IF(LEN(BY2)>0,VLOOKUP(BY2,$AO:$AP,2,FALSE),"")
A3: agr_bioenergy-capacity_biogas_landfill[TWh] | B3: eucalc_agr_bioenergy_capacity_biogas_landfill | C3: Biogas, landfill | E3: TWh | F3: SUM | G3: agriculture and forestry | H3: capacity | I3: biogas,energy,renewables | M3: yes | R3: =IF(COUNTIF(soi_input_variables!A:A,B3)>0,"yes","no") -> no | S3: =IF(COUNTIF(midas_input_variables!A:A,B3)>0,"yes","no") -> no | T3: =IF(OR(R3="yes",S3="yes"),"yes","no") -> no | U3: =0.0005 -> 0.0005 | V3: =IF(COUNTIF(eucalc_variables_proxies!A:A,B3)>0,"yes","no") -> yes | X3: agr_bioenergy_capacity | Z3: eucalc_agr_bioenergy_capacity_biogas | AC3: eucalc_agr_bioenergy_demand | AI3: eucalc_agr_bioenergy_capacity_biogas_landfill | AJ3: agr_bioenergy_capacity | AK3: agr_bioenergy-capacity_sum | AP3: agr_domestic-production_liv_abp_hens-egg[kcal] | AQ3: TRUE | AT3: {=IFERROR(_xlfn.TEXTSPLIT(AR3,";",,FALSE),"")} | BJ3: =IF(LEN(AT3)>0,VALUE(AT3),"") | BK3: =IF(LEN(AU3)>0,VALUE(AU3),"") | BL3: =IF(LEN(AV3)>0,VALUE(AV3),"") | BM3: =IF(LEN(AW3)>0,VALUE(AW3),"") | BN3: =IF(LEN(AX3)>0,VALUE(AX3),"") | BO3: =IF(LEN(AY3)>0,VALUE(AY3),"") | BP3: =IF(LEN(AZ3)>0,VALUE(AZ3),"") | BQ3: =IF(LEN(BA3)>0,VALUE(BA3),"") | ... BY3: =IF(LEN(BI3)>0,VALUE(BI3),"") | BZ3: =IF(LEN(BJ3)>0,VLOOKUP(BJ3,$AO:$AP,2,FALSE),"") | CA3: =IF(LEN(BK3)>0,VLOOKUP(BK3,$AO:$AP,2,FALSE),"") | CB3: =IF(LEN(BL3)>0,VLOOKUP(BL3,$AO:$AP,2,FALSE),"") | CC3: =IF(LEN(BM3)>0,VLOOKUP(BM3,$AO:$AP,2,FALSE),"") | CD3: =IF(LEN(BN3)>0,VLOOKUP(BN3,$AO:$AP,2,FALSE),"") | CE3: =IF(LEN(BO3)>0,VLOOKUP(BO3,$AO:$AP,2,FALSE),"") | CF3: =IF(LEN(BP3)>0,VLOOKUP(BP3,$AO:$AP,2,FALSE),"") | CG3: =IF(LEN(BQ3)>0,VLOOKUP(BQ3,$AO:$AP,2,FALSE),"") | ... CO3: =IF(LEN(BY3)>0,VLOOKUP(BY3,$AO:$AP,2,FALSE),"")
A4: agr_bioenergy-capacity_biogas_other-biogases[TWh] | B4: eucalc_agr_bioenergy_capacity_biogas_other_biogases | C4: Biogas, other | E4: TWh | F4: SUM | G4: agriculture and forestry | H4: capacity | I4: biogas,energy,renewables | M4: yes | R4: =IF(COUNTIF(soi_input_variables!A:A,B4)>0,"yes","no") -> no | S4: =IF(COUNTIF(midas_input_variables!A:A,B4)>0,"yes","no") -> no | T4: =IF(OR(R4="yes",S4="yes"),"yes","no") -> no | U4: =0.0005 -> 0.0005 | V4: =IF(COUNTIF(eucalc_variables_proxies!A:A,B4)>0,"yes","no") -> yes | X4: agr_bioenergy_capacity | Z4: eucalc_agr_bioenergy_capacity_biogas | AC4: agr_total_bioenergy_demand | AI4: eucalc_agr_bioenergy_capacity_biogas_other_biogases | AJ4: agr_bioenergy_capacity | AK4: agr_bioenergy-capacity_sum | AP4: agr_domestic-production_liv_abp_dairy-milk[kcal] | AQ4: TRUE | AT4: {=IFERROR(_xlfn.TEXTSPLIT(AR4,";",,FALSE),"")} | BJ4: =IF(LEN(AT4)>0,VALUE(AT4),"") | BK4: =IF(LEN(AU4)>0,VALUE(AU4),"") | BL4: =IF(LEN(AV4)>0,VALUE(AV4),"") | BM4: =IF(LEN(AW4)>0,VALUE(AW4),"") | BN4: =IF(LEN(AX4)>0,VALUE(AX4),"") | BO4: =IF(LEN(AY4)>0,VALUE(AY4),"") | BP4: =IF(LEN(AZ4)>0,VALUE(AZ4),"") | BQ4: =IF(LEN(BA4)>0,VALUE(BA4),"") | ... BY4: =IF(LEN(BI4)>0,VALUE(BI4),"") | BZ4: =IF(LEN(BJ4)>0,VLOOKUP(BJ4,$AO:$AP,2,FALSE),"") | CA4: =IF(LEN(BK4)>0,VLOOKUP(BK4,$AO:$AP,2,FALSE),"") | CB4: =IF(LEN(BL4)>0,VLOOKUP(BL4,$AO:$AP,2,FALSE),"") | CC4: =IF(LEN(BM4)>0,VLOOKUP(BM4,$AO:$AP,2,FALSE),"") | CD4: =IF(LEN(BN4)>0,VLOOKUP(BN4,$AO:$AP,2,FALSE),"") | CE4: =IF(LEN(BO4)>0,VLOOKUP(BO4,$AO:$AP,2,FALSE),"") | CF4: =IF(LEN(BP4)>0,VLOOKUP(BP4,$AO:$AP,2,FALSE),"") | CG4: =IF(LEN(BQ4)>0,VLOOKUP(BQ4,$AO:$AP,2,FALSE),"") | ... CO4: =IF(LEN(BY4)>0,VLOOKUP(BY4,$AO:$AP,2,FALSE),"")
A5: agr_bioenergy-capacity_biogas_ren-mun-wastes[TWh] | B5: eucalc_agr_bioenergy_capacity_biogas_ren_mun_wastes | C5: Biogas, ren-mun-wastes | E5: TWh | F5: SUM | G5: agriculture and forestry | H5: capacity | I5: biogas,energy,renewables | M5: yes | R5: =IF(COUNTIF(soi_input_variables!A:A,B5)>0,"yes","no") -> no | S5: =IF(COUNTIF(midas_input_variables!A:A,B5)>0,"yes","no") -> no | T5: =IF(OR(R5="yes",S5="yes"),"yes","no") -> no | U5: =0.0005 -> 0.0005 | V5: =IF(COUNTIF(eucalc_variables_proxies!A:A,B5)>0,"yes","no") -> yes | X5: agr_bioenergy_capacity | Z5: eucalc_agr_bioenergy_capacity_biogas | AI5: eucalc_agr_bioenergy_capacity_biogas_ren_mun_wastes | AJ5: agr_bioenergy_capacity | AK5: agr_bioenergy-capacity_sum | AP5: agr_domestic-production_liv_abp_processed_offal[kcal] | AQ5: TRUE | AT5: {=IFERROR(_xlfn.TEXTSPLIT(AR5,";",,FALSE),"")} | BJ5: =IF(LEN(AT5)>0,VALUE(AT5),"") | BK5: =IF(LEN(AU5)>0,VALUE(AU5),"") | BL5: =IF(LEN(AV5)>0,VALUE(AV5),"") | BM5: =IF(LEN(AW5)>0,VALUE(AW5),"") | BN5: =IF(LEN(AX5)>0,VALUE(AX5),"") | BO5: =IF(LEN(AY5)>0,VALUE(AY5),"") | BP5: =IF(LEN(AZ5)>0,VALUE(AZ5),"") | BQ5: =IF(LEN(BA5)>0,VALUE(BA5),"") | ... BY5: =IF(LEN(BI5)>0,VALUE(BI5),"") | BZ5: =IF(LEN(BJ5)>0,VLOOKUP(BJ5,$AO:$AP,2,FALSE),"") | CA5: =IF(LEN(BK5)>0,VLOOKUP(BK5,$AO:$AP,2,FALSE),"") | CB5: =IF(LEN(BL5)>0,VLOOKUP(BL5,$AO:$AP,2,FALSE),"") | CC5: =IF(LEN(BM5)>0,VLOOKUP(BM5,$AO:$AP,2,FALSE),"") | CD5: =IF(LEN(BN5)>0,VLOOKUP(BN5,$AO:$AP,2,FALSE),"") | CE5: =IF(LEN(BO5)>0,VLOOKUP(BO5,$AO:$AP,2,FALSE),"") | CF5: =IF(LEN(BP5)>0,VLOOKUP(BP5,$AO:$AP,2,FALSE),"") | CG5: =IF(LEN(BQ5)>0,VLOOKUP(BQ5,$AO:$AP,2,FALSE),"") | ... CO5: =IF(LEN(BY5)>0,VLOOKUP(BY5,$AO:$AP,2,FALSE),"")
A6: agr_bioenergy-capacity_biogas_sewage[TWh] | B6: eucalc_agr_bioenergy_capacity_biogas_sewage | C6: Biogas, sewage | E6: TWh | F6: SUM | G6: agriculture and forestry | H6: capacity | I6: biogas,energy,renewables | M6: yes | R6: =IF(COUNTIF(soi_input_variables!A:A,B6)>0,"yes","no") -> no | S6: =IF(COUNTIF(midas_input_variables!A:A,B6)>0,"yes","no") -> no | T6: =IF(OR(R6="yes",S6="yes"),"yes","no") -> no | U6: =0.0005 -> 0.0005 | V6: =IF(COUNTIF(eucalc_variables_proxies!A:A,B6)>0,"yes","no") -> yes | X6: agr_bioenergy_capacity | Z6: eucalc_agr_bioenergy_capacity_biogas | AC6: eucalc_agr_crop_cons | AI6: eucalc_agr_bioenergy_capacity_biogas_sewage | AJ6: agr_bioenergy_capacity | AK6: agr_bioenergy-capacity_sum | AP6: agr_domestic-production_liv_meat_bovine[kcal] | AQ6: TRUE | AT6: {=IFERROR(_xlfn.TEXTSPLIT(AR6,";",,FALSE),"")} | BJ6: =IF(LEN(AT6)>0,VALUE(AT6),"") | BK6: =IF(LEN(AU6)>0,VALUE(AU6),"") | BL6: =IF(LEN(AV6)>0,VALUE(AV6),"") | BM6: =IF(LEN(AW6)>0,VALUE(AW6),"") | BN6: =IF(LEN(AX6)>0,VALUE(AX6),"") | BO6: =IF(LEN(AY6)>0,VALUE(AY6),"") | BP6: =IF(LEN(AZ6)>0,VALUE(AZ6),"") | BQ6: =IF(LEN(BA6)>0,VALUE(BA6),"") | ... BY6: =IF(LEN(BI6)>0,VALUE(BI6),"") | BZ6: =IF(LEN(BJ6)>0,VLOOKUP(BJ6,$AO:$AP,2,FALSE),"") | CA6: =IF(LEN(BK6)>0,VLOOKUP(BK6,$AO:$AP,2,FALSE),"") | CB6: =IF(LEN(BL6)>0,VLOOKUP(BL6,$AO:$AP,2,FALSE),"") | CC6: =IF(LEN(BM6)>0,VLOOKUP(BM6,$AO:$AP,2,FALSE),"") | CD6: =IF(LEN(BN6)>0,VLOOKUP(BN6,$AO:$AP,2,FALSE),"") | CE6: =IF(LEN(BO6)>0,VLOOKUP(BO6,$AO:$AP,2,FALSE),"") | CF6: =IF(LEN(BP6)>0,VLOOKUP(BP6,$AO:$AP,2,FALSE),"") | CG6: =IF(LEN(BQ6)>0,VLOOKUP(BQ6,$AO:$AP,2,FALSE),"") | ... CO6: =IF(LEN(BY6)>0,VLOOKUP(BY6,$AO:$AP,2,FALSE),"")
